Workbook
Name CFG_CompanyName: 'SETTINGS'!$B$5
Name CFG_CompanyShortName: 'SETTINGS'!$B$6
Name CFG_Tagline: 'SETTINGS'!$B$7
Name CFG_CompanyPhone: 'SETTINGS'!$B$8
Name CFG_CompanyAddress: 'SETTINGS'!$B$9
Name CFG_CustomerIDPrefix: 'SETTINGS'!$B$10
Name CFG_CustomerIDDigits: 'SETTINGS'!$B$11
Name CFG_Currency: 'SETTINGS'!$B$12
Name CFG_CurrencySymbol: 'SETTINGS'!$B$13
Name CFG_DefaultLanguage: 'SETTINGS'!$B$14
Name CFG_PrintLanguage: 'SETTINGS'!$B$15
Name CFG_CurrentMonth: 'SETTINGS'!$B$16
Name CFG_DateFormat: 'SETTINGS'!$B$17
Name CFG_DefaultPaymentMethod: 'SETTINGS'!$B$18
Name CFG_AllowNegativeBalance: 'SETTINGS'!$B$19
Name CFG_OverdueGraceDays: 'SETTINGS'!$B$20
Name CFG_OCRConfidenceThreshold: 'SETTINGS'!$B$21
Name CFG_WhatsAppCountryCode: 'SETTINGS'!$B$22
Name CFG_WhatsAppMessage: 'SETTINGS'!$B$23
Name CFG_PaperSize: 'SETTINGS'!$B$24
Name CFG_PrintOrientation: 'SETTINGS'!$B$25
Name CFG_WorkbookType: 'SETTINGS'!$B$26
Name L_CustStatus: 'LISTS'!$A$4:$A$7
Name L_PayStatus: 'LISTS'!$B$4:$B$6
Name L_Methods: 'LISTS'!$C$4:$C$8
Name L_YesNo: 'LISTS'!$D$4:$D$5
Name L_EventTypes: 'LISTS'!$E$4:$E$18
Name L_AssignStatus: 'LISTS'!$F$4:$F$7
Name L_Languages: 'LISTS'!$G$4:$G$5
Name L_PrintModes: 'LISTS'!$H$4:$H$10
Name L_PrintStatuses: 'LISTS'!$I$4:$I$9
Name L_PrintStatusLabels: 'LISTS'!$J$4:$J$9
Name L_SearchTypes: 'LISTS'!$K$4:$K$10
Name L_Months: 'LISTS'!$L$4:$L$147
Name L_MonthsAll: 'LISTS'!$M$4:$M$148
Name L_DueDaysAll: 'LISTS'!$N$4:$N$35
Name L_AreaCodes: OFFSET('LISTS'!$O$4,0,0,MAX(1,COUNTIF('LISTS'!$O$4:$O$306,"?*")),1)
Name L_AreaNamesAll: OFFSET('LISTS'!$P$4,0,0,MAX(1,COUNTIF('LISTS'!$P$4:$P$306,"?*")),1)
Name L_LocCodes: OFFSET('LISTS'!$Q$4,0,0,MAX(1,COUNTIF('LISTS'!$Q$4:$Q$306,"?*")),1)
Name L_LocCodesAll: OFFSET('LISTS'!$R$4,0,0,MAX(1,COUNTIF('LISTS'!$R$4:$R$306,"?*")),1)
Name L_Packages: OFFSET('LISTS'!$S$4,0,0,MAX(1,COUNTIF('LISTS'!$S$4:$S$306,"?*")),1)
Name L_CollectorIDs: OFFSET('LISTS'!$T$4,0,0,MAX(1,COUNTIF('LISTS'!$T$4:$T$306,"?*")),1)
Name L_CollectorNamesAll: OFFSET('LISTS'!$U$4,0,0,MAX(1,COUNTIF('LISTS'!$U$4:$U$306,"?*")),1)
Name L_CustomerIDs: OFFSET('LISTS'!$V$4,0,0,MAX(1,COUNTIF('LISTS'!$V$4:$V$306,"?*")),1)
Name DB_Month: 'DASHBOARD'!$C$2
Name PC_Mode: 'PRINT_CENTER'!$C$4
Name PC_Month: 'PRINT_CENTER'!$C$5
Name PC_Area: 'PRINT_CENTER'!$C$6
Name PC_Location: 'PRINT_CENTER'!$C$7
Name PC_Collector: 'PRINT_CENTER'!$C$8
Name PC_Status: 'PRINT_CENTER'!$C$9
Name PC_DueDate: 'PRINT_CENTER'!$C$10
Name PC_StatusEff: 'PRINT_CENTER'!$C$12
Name PC_Count: 'PRINT_CENTER'!$C$13
Name PC_Title: 'PRINT_CENTER'!$C$14
Name PC_TotalFee: 'PRINT_CENTER'!$C$15
Name PC_TotalPaid: 'PRINT_CENTER'!$C$16
Name PC_TotalBalance: 'PRINT_CENTER'!$C$17
Name PC_CustomIDs: 'PRINT_CENTER'!$F$4:$F$103
Name PC_CustomCount: 'PRINT_CENTER'!$G$4

Sheet HOME
B2: =CFG_CompanyName
B3: ISP CUSTOMER & RECOVERY MANAGEMENT SYSTEM
B4: =IF(CFG_WorkbookType<>"REAL DATA","*** DEMO WORKBOOK - SAMPLE DATA ONLY - NOT REAL CUSTOMERS ***","")
B6: Current Month: | C6: =CFG_CurrentMonth&" ("&IFERROR(TEXT(DATE(LEFT(CFG_CurrentMonth,4),MID(CFG_CurrentMonth,6,2),1),"mmmm yyyy"),"not set")&")"
B7: Customers (Active / Total): | C7: =COUNTIF(tblCustomers[Customer Status],"Active")&" / "&(COUNTIF(tblCustomers[Customer ID],"?*"))
B8: Next Customer ID: | C8: =CFG_CustomerIDPrefix&"-"&TEXT(IFERROR(AGGREGATE(14,6,--MID(tblCustomers[Customer ID],LEN(CFG_CustomerIDPrefix)+2,10)/(LEFT(tblCustomers[Customer ID],LEN(CFG_CustomerIDPrefix)+1)=CFG_CustomerIDPrefix&"-"),1),0)+1,REPT("0",CFG_CustomerIDDigits))
B9: Open verification items: | C9: =COUNTIF(tblVerify[Status],"Open")
B10: Customers with data problems: | C10: =COUNTIF(tblCustomers[Data Check],"?*")
B12: GO TO | E12: MONTHLY WORKFLOW
B13: ► Dashboard | E13: 1. Double-click CityLinks.bat (menu program). Close this workbook in Excel first.
B14: ► Customer Master | E14: 2. Menu 1: Select / generate the month (GENERATE NEW MONTH). A backup is made first.
B15: ► Add Customer | E15: 3. Menu: Assign customers to collectors (by area / street / customer) if needed.
B16: ► Monthly Recovery | E16: 4. PRINT_CENTER: choose Area / Street / Collector / Status -> print PRINT_SHEET,
B17: ► Payment Entry | E17: or use the menu to save a PDF recovery list.
B18: ► Payments | E18: 5. Recovery boy collects cash and returns the signed list.
B19: ► Print Center | E19: 6. Enter payments: menu 'Record payment' or 'Quick recovery entry' (whole list at once).
B20: ► Customer History | E20: 7. Enter the cash he handed over in CASH_RECONCILIATION (Actual Cash Submitted).
B21: ► Customer Statement | E21: 8. DASHBOARD updates automatically.
B22: ► Pending Recovery | E22: 9. CUSTOMER_HISTORY: type any Customer ID (e.g. CL-0025) to see the complete history.
B23: ► Cash Reconciliation | E23: 10. Menu 'Customer statement PDF' -> PDF saved in exports/statements.
B24: ► Recovery Assignments | E24: 11. Menu shows the WhatsApp link - attach the PDF manually and send.
B25: ► Reports
B26: ► Monthly Archive
B27: ► Connection History | E27: CELL COLOURS
B28: ► Areas | F28: Yellow = you can type / choose here
B29: ► Location Codes | F29: Grey = calculated by formula (do not type)
B30: ► Packages | F30: Light blue = generated by the system (IDs, monthly snapshots)
B31: ► Collectors
B32: ► Verification Queue | E32: SAFETY RULES
B33: ► Settings | E33: • Never delete customers, bills or payments. Use Customer Status / Voided instead.
E34: • Customer ID never changes. VLAN / fee / area changes are recorded in CUSTOMER_EVENTS.
E35: • Backups are created automatically in the backups folder before major operations.
E36: • Handwritten data is never guessed - unclear values go to VERIFICATION_QUEUE.

Sheet DASHBOARD
A1: =CFG_CompanyName&" - RECOVERY DASHBOARD" | N1: ◄ HOME
A2: Month (YYYY-MM): | C2: =CFG_CurrentMonth | D2: =IFERROR(TEXT(DATE(LEFT(DB_Month,4),MID(DB_Month,6,2),1),"mmmm yyyy"),"Select month") | F2: =IF(CFG_WorkbookType<>"REAL DATA","DEMO WORKBOOK - SAMPLE DATA ONLY","")
A3: All figures are calculated from the workbook data. Nothing is typed by hand.
A5: CUSTOMERS | E5: SELECTED MONTH | I5: PAYMENT STATUS | M5: CASH
A6: Total Customers | E6: Customers Billed | I6: Paid Customers | M6: Today's Collection
A7: =COUNTIF(tblCustomers[Customer ID],"?*") | E7: =COUNTIF(tblBilling[Month],DB_Month) | I7: =COUNTIFS(tblBilling[Month],DB_Month,tblBilling[Payment Status],"PAID") | M7: =SUMIFS(tblPayments[Amount],tblPayments[Payment Date],TODAY(),tblPayments[Voided],"<>Yes")
A8: Active Customers | E8: Monthly Billing | I8: Partial Customers | M8: Current Month Collection
A9: =COUNTIF(tblCustomers[Customer Status],"Active") | E9: =SUMIFS(tblBilling[Monthly Fee],tblBilling[Month],DB_Month) | I9: =COUNTIFS(tblBilling[Month],DB_Month,tblBilling[Payment Status],"PARTIAL") | M9: =IFERROR(SUMIFS(tblPayments[Amount],tblPayments[Payment Date],">="&DATE(LEFT(DB_Month,4),MID(DB_Month,6,2),1),tblPayments[Payment Date],"<="&EOMONTH(DATE(LEFT(DB_Month,4),MID(DB_Month,6,2),1),0),tblPayments[Voided],"<>Yes"),0)
A10: Suspended | E10: Total Recovered | I10: Total Partial (Balance) | M10: Outstanding Balance (All Months)
A11: =COUNTIF(tblCustomers[Customer Status],"Suspended") | E11: =SUMIFS(tblBilling[Amount Paid],tblBilling[Month],DB_Month) | I11: =SUMIFS(tblBilling[Balance],tblBilling[Month],DB_Month,tblBilling[Payment Status],"PARTIAL") | M11: =SUM(tblBilling[Balance])
A12: Disconnected Customers | E12: Total Pending (Balance) | I12: Pending Customers | M12: Cash Difference (Month)
A13: =COUNTIF(tblCustomers[Customer Status],"Disconnected") | E13: =SUMIFS(tblBilling[Balance],tblBilling[Month],DB_Month) | I13: =COUNTIFS(tblBilling[Month],DB_Month,tblBilling[Payment Status],"PENDING") | M13: =SUMIFS(tblCash[Cash Difference],tblCash[Month],DB_Month)
A14: On Hold | E14: Recovery Percentage | I14: Overdue Customers | M14: Collectors Not Submitted
A15: =COUNTIF(tblCustomers[Customer Status],"On Hold") | E15: =IF(SUMIFS(tblBilling[Monthly Fee],tblBilling[Month],DB_Month)=0,0,SUMIFS(tblBilling[Amount Paid],tblBilling[Month],DB_Month)/SUMIFS(tblBilling[Monthly Fee],tblBilling[Month],DB_Month)) | I15: =COUNTIFS(tblBilling[Month],DB_Month,tblBilling[Overdue],"OVERDUE") | M15: =COUNTIFS(tblCash[Month],DB_Month,tblCash[Reconciliation Status],"NOT SUBMITTED")
A16: Current Month Collection = all payments received (by payment date) during the selected calendar month, for any bill.
A18: AREA-WISE RECOVERY (selected month)
A19: Area | B19: Customers | C19: Active Customers | D19: Billed | E19: Monthly Billing | F19: Recovered | G19: Pending (Balance) | H19: Paid | I19: Partial | J19: Pending | K19: Recovery %
A20: =IFERROR(INDEX(tblAreas[Area Name],1)&"","") | B20: =IF($A20="","",COUNTIF(tblCustomers[Area],$A20)) | C20: =IF($A20="","",COUNTIFS(tblCustomers[Area],$A20,tblCustomers[Customer Status],"Active")) | D20: =IF($A20="","",COUNTIFS(tblBilling[Month],DB_Month,tblBilling[Area],$A20)) | E20: =IF($A20="","",SUMIFS(tblBilling[Monthly Fee],tblBilling[Month],DB_Month,tblBilling[Area],$A20)) | F20: =IF($A20="","",SUMIFS(tblBilling[Amount Paid],tblBilling[Month],DB_Month,tblBilling[Area],$A20)) | G20: =IF($A20="","",SUMIFS(tblBilling[Balance],tblBilling[Month],DB_Month,tblBilling[Area],$A20)) | H20: =IF($A20="","",COUNTIFS(tblBilling[Month],DB_Month,tblBilling[Area],$A20,tblBilling[Payment Status],"PAID")) | I20: =IF($A20="","",COUNTIFS(tblBilling[Month],DB_Month,tblBilling[Area],$A20,tblBilling[Payment Status],"PARTIAL")) | J20: =IF($A20="","",COUNTIFS(tblBilling[Month],DB_Month,tblBilling[Area],$A20,tblBilling[Payment Status],"PENDING")) | K20: =IF(OR($A20="",N(E20)=0),"",F20/E20)
A21: =IFERROR(INDEX(tblAreas[Area Name],2)&"","") | B21: =IF($A21="","",COUNTIF(tblCustomers[Area],$A21)) | C21: =IF($A21="","",COUNTIFS(tblCustomers[Area],$A21,tblCustomers[Customer Status],"Active")) | D21: =IF($A21="","",COUNTIFS(tblBilling[Month],DB_Month,tblBilling[Area],$A21)) | E21: =IF($A21="","",SUMIFS(tblBilling[Monthly Fee],tblBilling[Month],DB_Month,tblBilling[Area],$A21)) | F21: =IF($A21="","",SUMIFS(tblBilling[Amount Paid],tblBilling[Month],DB_Month,tblBilling[Area],$A21)) | G21: =IF($A21="","",SUMIFS(tblBilling[Balance],tblBilling[Month],DB_Month,tblBilling[Area],$A21)) | H21: =IF($A21="","",COUNTIFS(tblBilling[Month],DB_Month,tblBilling[Area],$A21,tblBilling[Payment Status],"PAID")) | I21: =IF($A21="","",COUNTIFS(tblBilling[Month],DB_Month,tblBilling[Area],$A21,tblBilling[Payment Status],"PARTIAL")) | J21: =IF($A21="","",COUNTIFS(tblBilling[Month],DB_Month,tblBilling[Area],$A21,tblBilling[Payment Status],"PENDING")) | K21: =IF(OR($A21="",N(E21)=0),"",F21/E21)
A22: =IFERROR(INDEX(tblAreas[Area Name],3)&"","") | B22: =IF($A22="","",COUNTIF(tblCustomers[Area],$A22)) | C22: =IF($A22="","",COUNTIFS(tblCustomers[Area],$A22,tblCustomers[Customer Status],"Active")) | D22: =IF($A22="","",COUNTIFS(tblBilling[Month],DB_Month,tblBilling[Area],$A22)) | E22: =IF($A22="","",SUMIFS(tblBilling[Monthly Fee],tblBilling[Month],DB_Month,tblBilling[Area],$A22)) | F22: =IF($A22="","",SUMIFS(tblBilling[Amount Paid],tblBilling[Month],DB_Month,tblBilling[Area],$A22)) | G22: =IF($A22="","",SUMIFS(tblBilling[Balance],tblBilling[Month],DB_Month,tblBilling[Area],$A22)) | H22: =IF($A22="","",COUNTIFS(tblBilling[Month],DB_Month,tblBilling[Area],$A22,tblBilling[Payment Status],"PAID")) | I22: =IF($A22="","",COUNTIFS(tblBilling[Month],DB_Month,tblBilling[Area],$A22,tblBilling[Payment Status],"PARTIAL")) | J22: =IF($A22="","",COUNTIFS(tblBilling[Month],DB_Month,tblBilling[Area],$A22,tblBilling[Payment Status],"PENDING")) | K22: =IF(OR($A22="",N(E22)=0),"",F22/E22)
A23: =IFERROR(INDEX(tblAreas[Area Name],4)&"","") | B23: =IF($A23="","",COUNTIF(tblCustomers[Area],$A23)) | C23: =IF($A23="","",COUNTIFS(tblCustomers[Area],$A23,tblCustomers[Customer Status],"Active")) | D23: =IF($A23="","",COUNTIFS(tblBilling[Month],DB_Month,tblBilling[Area],$A23)) | E23: =IF($A23="","",SUMIFS(tblBilling[Monthly Fee],tblBilling[Month],DB_Month,tblBilling[Area],$A23)) | F23: =IF($A23="","",SUMIFS(tblBilling[Amount Paid],tblBilling[Month],DB_Month,tblBilling[Area],$A23)) | G23: =IF($A23="","",SUMIFS(tblBilling[Balance],tblBilling[Month],DB_Month,tblBilling[Area],$A23)) | H23: =IF($A23="","",COUNTIFS(tblBilling[Month],DB_Month,tblBilling[Area],$A23,tblBilling[Payment Status],"PAID")) | I23: =IF($A23="","",COUNTIFS(tblBilling[Month],DB_Month,tblBilling[Area],$A23,tblBilling[Payment Status],"PARTIAL")) | J23: =IF($A23="","",COUNTIFS(tblBilling[Month],DB_Month,tblBilling[Area],$A23,tblBilling[Payment Status],"PENDING")) | K23: =IF(OR($A23="",N(E23)=0),"",F23/E23)
A24: =IFERROR(INDEX(tblAreas[Area Name],5)&"","") | B24: =IF($A24="","",COUNTIF(tblCustomers[Area],$A24)) | C24: =IF($A24="","",COUNTIFS(tblCustomers[Area],$A24,tblCustomers[Customer Status],"Active")) | D24: =IF($A24="","",COUNTIFS(tblBilling[Month],DB_Month,tblBilling[Area],$A24)) | E24: =IF($A24="","",SUMIFS(tblBilling[Monthly Fee],tblBilling[Month],DB_Month,tblBilling[Area],$A24)) | F24: =IF($A24="","",SUMIFS(tblBilling[Amount Paid],tblBilling[Month],DB_Month,tblBilling[Area],$A24)) | G24: =IF($A24="","",SUMIFS(tblBilling[Balance],tblBilling[Month],DB_Month,tblBilling[Area],$A24)) | H24: =IF($A24="","",COUNTIFS(tblBilling[Month],DB_Month,tblBilling[Area],$A24,tblBilling[Payment Status],"PAID")) | I24: =IF($A24="","",COUNTIFS(tblBilling[Month],DB_Month,tblBilling[Area],$A24,tblBilling[Payment Status],"PARTIAL")) | J24: =IF($A24="","",COUNTIFS(tblBilling[Month],DB_Month,tblBilling[Area],$A24,tblBilling[Payment Status],"PENDING")) | K24: =IF(OR($A24="",N(E24)=0),"",F24/E24)
A25: =IFERROR(INDEX(tblAreas[Area Name],6)&"","") | B25: =IF($A25="","",COUNTIF(tblCustomers[Area],$A25)) | C25: =IF($A25="","",COUNTIFS(tblCustomers[Area],$A25,tblCustomers[Customer Status],"Active")) | D25: =IF($A25="","",COUNTIFS(tblBilling[Month],DB_Month,tblBilling[Area],$A25)) | E25: =IF($A25="","",SUMIFS(tblBilling[Monthly Fee],tblBilling[Month],DB_Month,tblBilling[Area],$A25)) | F25: =IF($A25="","",SUMIFS(tblBilling[Amount Paid],tblBilling[Month],DB_Month,tblBilling[Area],$A25)) | G25: =IF($A25="","",SUMIFS(tblBilling[Balance],tblBilling[Month],DB_Month,tblBilling[Area],$A25)) | H25: =IF($A25="","",COUNTIFS(tblBilling[Month],DB_Month,tblBilling[Area],$A25,tblBilling[Payment Status],"PAID")) | I25: =IF($A25="","",COUNTIFS(tblBilling[Month],DB_Month,tblBilling[Area],$A25,tblBilling[Payment Status],"PARTIAL")) | J25: =IF($A25="","",COUNTIFS(tblBilling[Month],DB_Month,tblBilling[Area],$A25,tblBilling[Payment Status],"PENDING")) | K25: =IF(OR($A25="",N(E25)=0),"",F25/E25)
A26: =IFERROR(INDEX(tblAreas[Area Name],7)&"","") | B26: =IF($A26="","",COUNTIF(tblCustomers[Area],$A26)) | C26: =IF($A26="","",COUNTIFS(tblCustomers[Area],$A26,tblCustomers[Customer Status],"Active")) | D26: =IF($A26="","",COUNTIFS(tblBilling[Month],DB_Month,tblBilling[Area],$A26)) | E26: =IF($A26="","",SUMIFS(tblBilling[Monthly Fee],tblBilling[Month],DB_Month,tblBilling[Area],$A26)) | F26: =IF($A26="","",SUMIFS(tblBilling[Amount Paid],tblBilling[Month],DB_Month,tblBilling[Area],$A26)) | G26: =IF($A26="","",SUMIFS(tblBilling[Balance],tblBilling[Month],DB_Month,tblBilling[Area],$A26)) | H26: =IF($A26="","",COUNTIFS(tblBilling[Month],DB_Month,tblBilling[Area],$A26,tblBilling[Payment Status],"PAID")) | I26: =IF($A26="","",COUNTIFS(tblBilling[Month],DB_Month,tblBilling[Area],$A26,tblBilling[Payment Status],"PARTIAL")) | J26: =IF($A26="","",COUNTIFS(tblBilling[Month],DB_Month,tblBilling[Area],$A26,tblBilling[Payment Status],"PENDING")) | K26: =IF(OR($A26="",N(E26)=0),"",F26/E26)
A27: =IFERROR(INDEX(tblAreas[Area Name],8)&"","") | B27: =IF($A27="","",COUNTIF(tblCustomers[Area],$A27)) | C27: =IF($A27="","",COUNTIFS(tblCustomers[Area],$A27,tblCustomers[Customer Status],"Active")) | D27: =IF($A27="","",COUNTIFS(tblBilling[Month],DB_Month,tblBilling[Area],$A27)) | E27: =IF($A27="","",SUMIFS(tblBilling[Monthly Fee],tblBilling[Month],DB_Month,tblBilling[Area],$A27)) | F27: =IF($A27="","",SUMIFS(tblBilling[Amount Paid],tblBilling[Month],DB_Month,tblBilling[Area],$A27)) | G27: =IF($A27="","",SUMIFS(tblBilling[Balance],tblBilling[Month],DB_Month,tblBilling[Area],$A27)) | H27: =IF($A27="","",COUNTIFS(tblBilling[Month],DB_Month,tblBilling[Area],$A27,tblBilling[Payment Status],"PAID")) | I27: =IF($A27="","",COUNTIFS(tblBilling[Month],DB_Month,tblBilling[Area],$A27,tblBilling[Payment Status],"PARTIAL")) | J27: =IF($A27="","",COUNTIFS(tblBilling[Month],DB_Month,tblBilling[Area],$A27,tblBilling[Payment Status],"PENDING")) | K27: =IF(OR($A27="",N(E27)=0),"",F27/E27)
A28: =IFERROR(INDEX(tblAreas[Area Name],9)&"","") | B28: =IF($A28="","",COUNTIF(tblCustomers[Area],$A28)) | C28: =IF($A28="","",COUNTIFS(tblCustomers[Area],$A28,tblCustomers[Customer Status],"Active")) | D28: =IF($A28="","",COUNTIFS(tblBilling[Month],DB_Month,tblBilling[Area],$A28)) | E28: =IF($A28="","",SUMIFS(tblBilling[Monthly Fee],tblBilling[Month],DB_Month,tblBilling[Area],$A28)) | F28: =IF($A28="","",SUMIFS(tblBilling[Amount Paid],tblBilling[Month],DB_Month,tblBilling[Area],$A28)) | G28: =IF($A28="","",SUMIFS(tblBilling[Balance],tblBilling[Month],DB_Month,tblBilling[Area],$A28)) | H28: =IF($A28="","",COUNTIFS(tblBilling[Month],DB_Month,tblBilling[Area],$A28,tblBilling[Payment Status],"PAID")) | I28: =IF($A28="","",COUNTIFS(tblBilling[Month],DB_Month,tblBilling[Area],$A28,tblBilling[Payment Status],"PARTIAL")) | J28: =IF($A28="","",COUNTIFS(tblBilling[Month],DB_Month,tblBilling[Area],$A28,tblBilling[Payment Status],"PENDING")) | K28: =IF(OR($A28="",N(E28)=0),"",F28/E28)
A29: =IFERROR(INDEX(tblAreas[Area Name],10)&"","") | B29: =IF($A29="","",COUNTIF(tblCustomers[Area],$A29)) | C29: =IF($A29="","",COUNTIFS(tblCustomers[Area],$A29,tblCustomers[Customer Status],"Active")) | D29: =IF($A29="","",COUNTIFS(tblBilling[Month],DB_Month,tblBilling[Area],$A29)) | E29: =IF($A29="","",SUMIFS(tblBilling[Monthly Fee],tblBilling[Month],DB_Month,tblBilling[Area],$A29)) | F29: =IF($A29="","",SUMIFS(tblBilling[Amount Paid],tblBilling[Month],DB_Month,tblBilling[Area],$A29)) | G29: =IF($A29="","",SUMIFS(tblBilling[Balance],tblBilling[Month],DB_Month,tblBilling[Area],$A29)) | H29: =IF($A29="","",COUNTIFS(tblBilling[Month],DB_Month,tblBilling[Area],$A29,tblBilling[Payment Status],"PAID")) | I29: =IF($A29="","",COUNTIFS(tblBilling[Month],DB_Month,tblBilling[Area],$A29,tblBilling[Payment Status],"PARTIAL")) | J29: =IF($A29="","",COUNTIFS(tblBilling[Month],DB_Month,tblBilling[Area],$A29,tblBilling[Payment Status],"PENDING")) | K29: =IF(OR($A29="",N(E29)=0),"",F29/E29)
A30: =IFERROR(INDEX(tblAreas[Area Name],11)&"","") | B30: =IF($A30="","",COUNTIF(tblCustomers[Area],$A30)) | C30: =IF($A30="","",COUNTIFS(tblCustomers[Area],$A30,tblCustomers[Customer Status],"Active")) | D30: =IF($A30="","",COUNTIFS(tblBilling[Month],DB_Month,tblBilling[Area],$A30)) | E30: =IF($A30="","",SUMIFS(tblBilling[Monthly Fee],tblBilling[Month],DB_Month,tblBilling[Area],$A30)) | F30: =IF($A30="","",SUMIFS(tblBilling[Amount Paid],tblBilling[Month],DB_Month,tblBilling[Area],$A30)) | G30: =IF($A30="","",SUMIFS(tblBilling[Balance],tblBilling[Month],DB_Month,tblBilling[Area],$A30)) | H30: =IF($A30="","",COUNTIFS(tblBilling[Month],DB_Month,tblBilling[Area],$A30,tblBilling[Payment Status],"PAID")) | I30: =IF($A30="","",COUNTIFS(tblBilling[Month],DB_Month,tblBilling[Area],$A30,tblBilling[Payment Status],"PARTIAL")) | J30: =IF($A30="","",COUNTIFS(tblBilling[Month],DB_Month,tblBilling[Area],$A30,tblBilling[Payment Status],"PENDING")) | K30: =IF(OR($A30="",N(E30)=0),"",F30/E30)
A31: =IFERROR(INDEX(tblAreas[Area Name],12)&"","") | B31: =IF($A31="","",COUNTIF(tblCustomers[Area],$A31)) | C31: =IF($A31="","",COUNTIFS(tblCustomers[Area],$A31,tblCustomers[Customer Status],"Active")) | D31: =IF($A31="","",COUNTIFS(tblBilling[Month],DB_Month,tblBilling[Area],$A31)) | E31: =IF($A31="","",SUMIFS(tblBilling[Monthly Fee],tblBilling[Month],DB_Month,tblBilling[Area],$A31)) | F31: =IF($A31="","",SUMIFS(tblBilling[Amount Paid],tblBilling[Month],DB_Month,tblBilling[Area],$A31)) | G31: =IF($A31="","",SUMIFS(tblBilling[Balance],tblBilling[Month],DB_Month,tblBilling[Area],$A31)) | H31: =IF($A31="","",COUNTIFS(tblBilling[Month],DB_Month,tblBilling[Area],$A31,tblBilling[Payment Status],"PAID")) | I31: =IF($A31="","",COUNTIFS(tblBilling[Month],DB_Month,tblBilling[Area],$A31,tblBilling[Payment Status],"PARTIAL")) | J31: =IF($A31="","",COUNTIFS(tblBilling[Month],DB_Month,tblBilling[Area],$A31,tblBilling[Payment Status],"PENDING")) | K31: =IF(OR($A31="",N(E31)=0),"",F31/E31)
A32: =IFERROR(INDEX(tblAreas[Area Name],13)&"","") | B32: =IF($A32="","",COUNTIF(tblCustomers[Area],$A32)) | C32: =IF($A32="","",COUNTIFS(tblCustomers[Area],$A32,tblCustomers[Customer Status],"Active")) | D32: =IF($A32="","",COUNTIFS(tblBilling[Month],DB_Month,tblBilling[Area],$A32)) | E32: =IF($A32="","",SUMIFS(tblBilling[Monthly Fee],tblBilling[Month],DB_Month,tblBilling[Area],$A32)) | F32: =IF($A32="","",SUMIFS(tblBilling[Amount Paid],tblBilling[Month],DB_Month,tblBilling[Area],$A32)) | G32: =IF($A32="","",SUMIFS(tblBilling[Balance],tblBilling[Month],DB_Month,tblBilling[Area],$A32)) | H32: =IF($A32="","",COUNTIFS(tblBilling[Month],DB_Month,tblBilling[Area],$A32,tblBilling[Payment Status],"PAID")) | I32: =IF($A32="","",COUNTIFS(tblBilling[Month],DB_Month,tblBilling[Area],$A32,tblBilling[Payment Status],"PARTIAL")) | J32: =IF($A32="","",COUNTIFS(tblBilling[Month],DB_Month,tblBilling[Area],$A32,tblBilling[Payment Status],"PENDING")) | K32: =IF(OR($A32="",N(E32)=0),"",F32/E32)
A33: =IFERROR(INDEX(tblAreas[Area Name],14)&"","") | B33: =IF($A33="","",COUNTIF(tblCustomers[Area],$A33)) | C33: =IF($A33="","",COUNTIFS(tblCustomers[Area],$A33,tblCustomers[Customer Status],"Active")) | D33: =IF($A33="","",COUNTIFS(tblBilling[Month],DB_Month,tblBilling[Area],$A33)) | E33: =IF($A33="","",SUMIFS(tblBilling[Monthly Fee],tblBilling[Month],DB_Month,tblBilling[Area],$A33)) | F33: =IF($A33="","",SUMIFS(tblBilling[Amount Paid],tblBilling[Month],DB_Month,tblBilling[Area],$A33)) | G33: =IF($A33="","",SUMIFS(tblBilling[Balance],tblBilling[Month],DB_Month,tblBilling[Area],$A33)) | H33: =IF($A33="","",COUNTIFS(tblBilling[Month],DB_Month,tblBilling[Area],$A33,tblBilling[Payment Status],"PAID")) | I33: =IF($A33="","",COUNTIFS(tblBilling[Month],DB_Month,tblBilling[Area],$A33,tblBilling[Payment Status],"PARTIAL")) | J33: =IF($A33="","",COUNTIFS(tblBilling[Month],DB_Month,tblBilling[Area],$A33,tblBilling[Payment Status],"PENDING")) | K33: =IF(OR($A33="",N(E33)=0),"",F33/E33)
A34: =IFERROR(INDEX(tblAreas[Area Name],15)&"","") | B34: =IF($A34="","",COUNTIF(tblCustomers[Area],$A34)) | C34: =IF($A34="","",COUNTIFS(tblCustomers[Area],$A34,tblCustomers[Customer Status],"Active")) | D34: =IF($A34="","",COUNTIFS(tblBilling[Month],DB_Month,tblBilling[Area],$A34)) | E34: =IF($A34="","",SUMIFS(tblBilling[Monthly Fee],tblBilling[Month],DB_Month,tblBilling[Area],$A34)) | F34: =IF($A34="","",SUMIFS(tblBilling[Amount Paid],tblBilling[Month],DB_Month,tblBilling[Area],$A34)) | G34: =IF($A34="","",SUMIFS(tblBilling[Balance],tblBilling[Month],DB_Month,tblBilling[Area],$A34)) | H34: =IF($A34="","",COUNTIFS(tblBilling[Month],DB_Month,tblBilling[Area],$A34,tblBilling[Payment Status],"PAID")) | I34: =IF($A34="","",COUNTIFS(tblBilling[Month],DB_Month,tblBilling[Area],$A34,tblBilling[Payment Status],"PARTIAL")) | J34: =IF($A34="","",COUNTIFS(tblBilling[Month],DB_Month,tblBilling[Area],$A34,tblBilling[Payment Status],"PENDING")) | K34: =IF(OR($A34="",N(E34)=0),"",F34/E34)
A35: =IFERROR(INDEX(tblAreas[Area Name],16)&"","") | B35: =IF($A35="","",COUNTIF(tblCustomers[Area],$A35)) | C35: =IF($A35="","",COUNTIFS(tblCustomers[Area],$A35,tblCustomers[Customer Status],"Active")) | D35: =IF($A35="","",COUNTIFS(tblBilling[Month],DB_Month,tblBilling[Area],$A35)) | E35: =IF($A35="","",SUMIFS(tblBilling[Monthly Fee],tblBilling[Month],DB_Month,tblBilling[Area],$A35)) | F35: =IF($A35="","",SUMIFS(tblBilling[Amount Paid],tblBilling[Month],DB_Month,tblBilling[Area],$A35)) | G35: =IF($A35="","",SUMIFS(tblBilling[Balance],tblBilling[Month],DB_Month,tblBilling[Area],$A35)) | H35: =IF($A35="","",COUNTIFS(tblBilling[Month],DB_Month,tblBilling[Area],$A35,tblBilling[Payment Status],"PAID")) | I35: =IF($A35="","",COUNTIFS(tblBilling[Month],DB_Month,tblBilling[Area],$A35,tblBilling[Payment Status],"PARTIAL")) | J35: =IF($A35="","",COUNTIFS(tblBilling[Month],DB_Month,tblBilling[Area],$A35,tblBilling[Payment Status],"PENDING")) | K35: =IF(OR($A35="",N(E35)=0),"",F35/E35)
A36: =IFERROR(INDEX(tblAreas[Area Name],17)&"","") | B36: =IF($A36="","",COUNTIF(tblCustomers[Area],$A36)) | C36: =IF($A36="","",COUNTIFS(tblCustomers[Area],$A36,tblCustomers[Customer Status],"Active")) | D36: =IF($A36="","",COUNTIFS(tblBilling[Month],DB_Month,tblBilling[Area],$A36)) | E36: =IF($A36="","",SUMIFS(tblBilling[Monthly Fee],tblBilling[Month],DB_Month,tblBilling[Area],$A36)) | F36: =IF($A36="","",SUMIFS(tblBilling[Amount Paid],tblBilling[Month],DB_Month,tblBilling[Area],$A36)) | G36: =IF($A36="","",SUMIFS(tblBilling[Balance],tblBilling[Month],DB_Month,tblBilling[Area],$A36)) | H36: =IF($A36="","",COUNTIFS(tblBilling[Month],DB_Month,tblBilling[Area],$A36,tblBilling[Payment Status],"PAID")) | I36: =IF($A36="","",COUNTIFS(tblBilling[Month],DB_Month,tblBilling[Area],$A36,tblBilling[Payment Status],"PARTIAL")) | J36: =IF($A36="","",COUNTIFS(tblBilling[Month],DB_Month,tblBilling[Area],$A36,tblBilling[Payment Status],"PENDING")) | K36: =IF(OR($A36="",N(E36)=0),"",F36/E36)
A37: =IFERROR(INDEX(tblAreas[Area Name],18)&"","") | B37: =IF($A37="","",COUNTIF(tblCustomers[Area],$A37)) | C37: =IF($A37="","",COUNTIFS(tblCustomers[Area],$A37,tblCustomers[Customer Status],"Active")) | D37: =IF($A37="","",COUNTIFS(tblBilling[Month],DB_Month,tblBilling[Area],$A37)) | E37: =IF($A37="","",SUMIFS(tblBilling[Monthly Fee],tblBilling[Month],DB_Month,tblBilling[Area],$A37)) | F37: =IF($A37="","",SUMIFS(tblBilling[Amount Paid],tblBilling[Month],DB_Month,tblBilling[Area],$A37)) | G37: =IF($A37="","",SUMIFS(tblBilling[Balance],tblBilling[Month],DB_Month,tblBilling[Area],$A37)) | H37: =IF($A37="","",COUNTIFS(tblBilling[Month],DB_Month,tblBilling[Area],$A37,tblBilling[Payment Status],"PAID")) | I37: =IF($A37="","",COUNTIFS(tblBilling[Month],DB_Month,tblBilling[Area],$A37,tblBilling[Payment Status],"PARTIAL")) | J37: =IF($A37="","",COUNTIFS(tblBilling[Month],DB_Month,tblBilling[Area],$A37,tblBilling[Payment Status],"PENDING")) | K37: =IF(OR($A37="",N(E37)=0),"",F37/E37)
A38: =IFERROR(INDEX(tblAreas[Area Name],19)&"","") | B38: =IF($A38="","",COUNTIF(tblCustomers[Area],$A38)) | C38: =IF($A38="","",COUNTIFS(tblCustomers[Area],$A38,tblCustomers[Customer Status],"Active")) | D38: =IF($A38="","",COUNTIFS(tblBilling[Month],DB_Month,tblBilling[Area],$A38)) | E38: =IF($A38="","",SUMIFS(tblBilling[Monthly Fee],tblBilling[Month],DB_Month,tblBilling[Area],$A38)) | F38: =IF($A38="","",SUMIFS(tblBilling[Amount Paid],tblBilling[Month],DB_Month,tblBilling[Area],$A38)) | G38: =IF($A38="","",SUMIFS(tblBilling[Balance],tblBilling[Month],DB_Month,tblBilling[Area],$A38)) | H38: =IF($A38="","",COUNTIFS(tblBilling[Month],DB_Month,tblBilling[Area],$A38,tblBilling[Payment Status],"PAID")) | I38: =IF($A38="","",COUNTIFS(tblBilling[Month],DB_Month,tblBilling[Area],$A38,tblBilling[Payment Status],"PARTIAL")) | J38: =IF($A38="","",COUNTIFS(tblBilling[Month],DB_Month,tblBilling[Area],$A38,tblBilling[Payment Status],"PENDING")) | K38: =IF(OR($A38="",N(E38)=0),"",F38/E38)
A39: =IFERROR(INDEX(tblAreas[Area Name],20)&"","") | B39: =IF($A39="","",COUNTIF(tblCustomers[Area],$A39)) | C39: =IF($A39="","",COUNTIFS(tblCustomers[Area],$A39,tblCustomers[Customer Status],"Active")) | D39: =IF($A39="","",COUNTIFS(tblBilling[Month],DB_Month,tblBilling[Area],$A39)) | E39: =IF($A39="","",SUMIFS(tblBilling[Monthly Fee],tblBilling[Month],DB_Month,tblBilling[Area],$A39)) | F39: =IF($A39="","",SUMIFS(tblBilling[Amount Paid],tblBilling[Month],DB_Month,tblBilling[Area],$A39)) | G39: =IF($A39="","",SUMIFS(tblBilling[Balance],tblBilling[Month],DB_Month,tblBilling[Area],$A39)) | H39: =IF($A39="","",COUNTIFS(tblBilling[Month],DB_Month,tblBilling[Area],$A39,tblBilling[Payment Status],"PAID")) | I39: =IF($A39="","",COUNTIFS(tblBilling[Month],DB_Month,tblBilling[Area],$A39,tblBilling[Payment Status],"PARTIAL")) | J39: =IF($A39="","",COUNTIFS(tblBilling[Month],DB_Month,tblBilling[Area],$A39,tblBilling[Payment Status],"PENDING")) | K39: =IF(OR($A39="",N(E39)=0),"",F39/E39)
A40: =IFERROR(INDEX(tblAreas[Area Name],21)&"","") | B40: =IF($A40="","",COUNTIF(tblCustomers[Area],$A40)) | C40: =IF($A40="","",COUNTIFS(tblCustomers[Area],$A40,tblCustomers[Customer Status],"Active")) | D40: =IF($A40="","",COUNTIFS(tblBilling[Month],DB_Month,tblBilling[Area],$A40)) | E40: =IF($A40="","",SUMIFS(tblBilling[Monthly Fee],tblBilling[Month],DB_Month,tblBilling[Area],$A40)) | F40: =IF($A40="","",SUMIFS(tblBilling[Amount Paid],tblBilling[Month],DB_Month,tblBilling[Area],$A40)) | G40: =IF($A40="","",SUMIFS(tblBilling[Balance],tblBilling[Month],DB_Month,tblBilling[Area],$A40)) | H40: =IF($A40="","",COUNTIFS(tblBilling[Month],DB_Month,tblBilling[Area],$A40,tblBilling[Payment Status],"PAID")) | I40: =IF($A40="","",COUNTIFS(tblBilling[Month],DB_Month,tblBilling[Area],$A40,tblBilling[Payment Status],"PARTIAL")) | J40: =IF($A40="","",COUNTIFS(tblBilling[Month],DB_Month,tblBilling[Area],$A40,tblBilling[Payment Status],"PENDING")) | K40: =IF(OR($A40="",N(E40)=0),"",F40/E40)
A41: =IFERROR(INDEX(tblAreas[Area Name],22)&"","") | B41: =IF($A41="","",COUNTIF(tblCustomers[Area],$A41)) | C41: =IF($A41="","",COUNTIFS(tblCustomers[Area],$A41,tblCustomers[Customer Status],"Active")) | D41: =IF($A41="","",COUNTIFS(tblBilling[Month],DB_Month,tblBilling[Area],$A41)) | E41: =IF($A41="","",SUMIFS(tblBilling[Monthly Fee],tblBilling[Month],DB_Month,tblBilling[Area],$A41)) | F41: =IF($A41="","",SUMIFS(tblBilling[Amount Paid],tblBilling[Month],DB_Month,tblBilling[Area],$A41)) | G41: =IF($A41="","",SUMIFS(tblBilling[Balance],tblBilling[Month],DB_Month,tblBilling[Area],$A41)) | H41: =IF($A41="","",COUNTIFS(tblBilling[Month],DB_Month,tblBilling[Area],$A41,tblBilling[Payment Status],"PAID")) | I41: =IF($A41="","",COUNTIFS(tblBilling[Month],DB_Month,tblBilling[Area],$A41,tblBilling[Payment Status],"PARTIAL")) | J41: =IF($A41="","",COUNTIFS(tblBilling[Month],DB_Month,tblBilling[Area],$A41,tblBilling[Payment Status],"PENDING")) | K41: =IF(OR($A41="",N(E41)=0),"",F41/E41)
A42: =IFERROR(INDEX(tblAreas[Area Name],23)&"","") | B42: =IF($A42="","",COUNTIF(tblCustomers[Area],$A42)) | C42: =IF($A42="","",COUNTIFS(tblCustomers[Area],$A42,tblCustomers[Customer Status],"Active")) | D42: =IF($A42="","",COUNTIFS(tblBilling[Month],DB_Month,tblBilling[Area],$A42)) | E42: =IF($A42="","",SUMIFS(tblBilling[Monthly Fee],tblBilling[Month],DB_Month,tblBilling[Area],$A42)) | F42: =IF($A42="","",SUMIFS(tblBilling[Amount Paid],tblBilling[Month],DB_Month,tblBilling[Area],$A42)) | G42: =IF($A42="","",SUMIFS(tblBilling[Balance],tblBilling[Month],DB_Month,tblBilling[Area],$A42)) | H42: =IF($A42="","",COUNTIFS(tblBilling[Month],DB_Month,tblBilling[Area],$A42,tblBilling[Payment Status],"PAID")) | I42: =IF($A42="","",COUNTIFS(tblBilling[Month],DB_Month,tblBilling[Area],$A42,tblBilling[Payment Status],"PARTIAL")) | J42: =IF($A42="","",COUNTIFS(tblBilling[Month],DB_Month,tblBilling[Area],$A42,tblBilling[Payment Status],"PENDING")) | K42: =IF(OR($A42="",N(E42)=0),"",F42/E42)
A43: =IFERROR(INDEX(tblAreas[Area Name],24)&"","") | B43: =IF($A43="","",COUNTIF(tblCustomers[Area],$A43)) | C43: =IF($A43="","",COUNTIFS(tblCustomers[Area],$A43,tblCustomers[Customer Status],"Active")) | D43: =IF($A43="","",COUNTIFS(tblBilling[Month],DB_Month,tblBilling[Area],$A43)) | E43: =IF($A43="","",SUMIFS(tblBilling[Monthly Fee],tblBilling[Month],DB_Month,tblBilling[Area],$A43)) | F43: =IF($A43="","",SUMIFS(tblBilling[Amount Paid],tblBilling[Month],DB_Month,tblBilling[Area],$A43)) | G43: =IF($A43="","",SUMIFS(tblBilling[Balance],tblBilling[Month],DB_Month,tblBilling[Area],$A43)) | H43: =IF($A43="","",COUNTIFS(tblBilling[Month],DB_Month,tblBilling[Area],$A43,tblBilling[Payment Status],"PAID")) | I43: =IF($A43="","",COUNTIFS(tblBilling[Month],DB_Month,tblBilling[Area],$A43,tblBilling[Payment Status],"PARTIAL")) | J43: =IF($A43="","",COUNTIFS(tblBilling[Month],DB_Month,tblBilling[Area],$A43,tblBilling[Payment Status],"PENDING")) | K43: =IF(OR($A43="",N(E43)=0),"",F43/E43)
A44: =IFERROR(INDEX(tblAreas[Area Name],25)&"","") | B44: =IF($A44="","",COUNTIF(tblCustomers[Area],$A44)) | C44: =IF($A44="","",COUNTIFS(tblCustomers[Area],$A44,tblCustomers[Customer Status],"Active")) | D44: =IF($A44="","",COUNTIFS(tblBilling[Month],DB_Month,tblBilling[Area],$A44)) | E44: =IF($A44="","",SUMIFS(tblBilling[Monthly Fee],tblBilling[Month],DB_Month,tblBilling[Area],$A44)) | F44: =IF($A44="","",SUMIFS(tblBilling[Amount Paid],tblBilling[Month],DB_Month,tblBilling[Area],$A44)) | G44: =IF($A44="","",SUMIFS(tblBilling[Balance],tblBilling[Month],DB_Month,tblBilling[Area],$A44)) | H44: =IF($A44="","",COUNTIFS(tblBilling[Month],DB_Month,tblBilling[Area],$A44,tblBilling[Payment Status],"PAID")) | I44: =IF($A44="","",COUNTIFS(tblBilling[Month],DB_Month,tblBilling[Area],$A44,tblBilling[Payment Status],"PARTIAL")) | J44: =IF($A44="","",COUNTIFS(tblBilling[Month],DB_Month,tblBilling[Area],$A44,tblBilling[Payment Status],"PENDING")) | K44: =IF(OR($A44="",N(E44)=0),"",F44/E44)
A47: COLLECTOR-WISE RECOVERY & CASH (selected month)
A48: Collector ID | B48: Collector | C48: Assigned Customers | D48: Assigned Billing | E48: Recovered | F48: Pending (Balance) | G48: Paid | H48: Partial | I48: Pending | J48: Recovery % | K48: Expected Cash | L48: Actual Cash | M48: Difference | N48: Status
A49: =IFERROR(INDEX(tblCollectors[Collector ID],1)&"","") | B49: =IF($A49="","",INDEX(tblCollectors[Collector Name],1)) | C49: =IF($B49="","",COUNTIFS(tblBilling[Month],DB_Month,tblBilling[Collector ID],$A49)) | D49: =IF($B49="","",SUMIFS(tblBilling[Monthly Fee],tblBilling[Month],DB_Month,tblBilling[Collector ID],$A49)) | E49: =IF($B49="","",SUMIFS(tblBilling[Amount Paid],tblBilling[Month],DB_Month,tblBilling[Collector ID],$A49)) | F49: =IF($B49="","",SUMIFS(tblBilling[Balance],tblBilling[Month],DB_Month,tblBilling[Collector ID],$A49)) | G49: =IF($B49="","",COUNTIFS(tblBilling[Month],DB_Month,tblBilling[Collector ID],$A49,tblBilling[Payment Status],"PAID")) | H49: =IF($B49="","",COUNTIFS(tblBilling[Month],DB_Month,tblBilling[Collector ID],$A49,tblBilling[Payment Status],"PARTIAL")) | I49: =IF($B49="","",COUNTIFS(tblBilling[Month],DB_Month,tblBilling[Collector ID],$A49,tblBilling[Payment Status],"PENDING")) | J49: =IF(OR($B49="",N(D49)=0),"",E49/D49) | K49: =IF($A49="","",SUMIFS(tblPayments[Amount],tblPayments[Collector ID],$A49,tblPayments[Month],DB_Month,tblPayments[Payment Method],"Cash",tblPayments[Voided],"<>Yes")) | L49: =IF($A49="","",IF(COUNTIFS(tblCash[Month],DB_Month,tblCash[Collector ID],$A49,tblCash[Actual Cash Submitted],"<>")=0,"",SUMIFS(tblCash[Actual Cash Submitted],tblCash[Month],DB_Month,tblCash[Collector ID],$A49))) | M49: =IF(OR($A49="",L49=""),"",L49-K49) | N49: =IF($A49="","",IF(L49="","NOT SUBMITTED",IF(M49=0,"MATCHED","CASH DIFFERENCE")))
A50: =IFERROR(INDEX(tblCollectors[Collector ID],2)&"","") | B50: =IF($A50="","",INDEX(tblCollectors[Collector Name],2)) | C50: =IF($B50="","",COUNTIFS(tblBilling[Month],DB_Month,tblBilling[Collector ID],$A50)) | D50: =IF($B50="","",SUMIFS(tblBilling[Monthly Fee],tblBilling[Month],DB_Month,tblBilling[Collector ID],$A50)) | E50: =IF($B50="","",SUMIFS(tblBilling[Amount Paid],tblBilling[Month],DB_Month,tblBilling[Collector ID],$A50)) | F50: =IF($B50="","",SUMIFS(tblBilling[Balance],tblBilling[Month],DB_Month,tblBilling[Collector ID],$A50)) | G50: =IF($B50="","",COUNTIFS(tblBilling[Month],DB_Month,tblBilling[Collector ID],$A50,tblBilling[Payment Status],"PAID")) | H50: =IF($B50="","",COUNTIFS(tblBilling[Month],DB_Month,tblBilling[Collector ID],$A50,tblBilling[Payment Status],"PARTIAL")) | I50: =IF($B50="","",COUNTIFS(tblBilling[Month],DB_Month,tblBilling[Collector ID],$A50,tblBilling[Payment Status],"PENDING")) | J50: =IF(OR($B50="",N(D50)=0),"",E50/D50) | K50: =IF($A50="","",SUMIFS(tblPayments[Amount],tblPayments[Collector ID],$A50,tblPayments[Month],DB_Month,tblPayments[Payment Method],"Cash",tblPayments[Voided],"<>Yes")) | L50: =IF($A50="","",IF(COUNTIFS(tblCash[Month],DB_Month,tblCash[Collector ID],$A50,tblCash[Actual Cash Submitted],"<>")=0,"",SUMIFS(tblCash[Actual Cash Submitted],tblCash[Month],DB_Month,tblCash[Collector ID],$A50))) | M50: =IF(OR($A50="",L50=""),"",L50-K50) | N50: =IF($A50="","",IF(L50="","NOT SUBMITTED",IF(M50=0,"MATCHED","CASH DIFFERENCE")))
A51: =IFERROR(INDEX(tblCollectors[Collector ID],3)&"","") | B51: =IF($A51="","",INDEX(tblCollectors[Collector Name],3)) | C51: =IF($B51="","",COUNTIFS(tblBilling[Month],DB_Month,tblBilling[Collector ID],$A51)) | D51: =IF($B51="","",SUMIFS(tblBilling[Monthly Fee],tblBilling[Month],DB_Month,tblBilling[Collector ID],$A51)) | E51: =IF($B51="","",SUMIFS(tblBilling[Amount Paid],tblBilling[Month],DB_Month,tblBilling[Collector ID],$A51)) | F51: =IF($B51="","",SUMIFS(tblBilling[Balance],tblBilling[Month],DB_Month,tblBilling[Collector ID],$A51)) | G51: =IF($B51="","",COUNTIFS(tblBilling[Month],DB_Month,tblBilling[Collector ID],$A51,tblBilling[Payment Status],"PAID")) | H51: =IF($B51="","",COUNTIFS(tblBilling[Month],DB_Month,tblBilling[Collector ID],$A51,tblBilling[Payment Status],"PARTIAL")) | I51: =IF($B51="","",COUNTIFS(tblBilling[Month],DB_Month,tblBilling[Collector ID],$A51,tblBilling[Payment Status],"PENDING")) | J51: =IF(OR($B51="",N(D51)=0),"",E51/D51) | K51: =IF($A51="","",SUMIFS(tblPayments[Amount],tblPayments[Collector ID],$A51,tblPayments[Month],DB_Month,tblPayments[Payment Method],"Cash",tblPayments[Voided],"<>Yes")) | L51: =IF($A51="","",IF(COUNTIFS(tblCash[Month],DB_Month,tblCash[Collector ID],$A51,tblCash[Actual Cash Submitted],"<>")=0,"",SUMIFS(tblCash[Actual Cash Submitted],tblCash[Month],DB_Month,tblCash[Collector ID],$A51))) | M51: =IF(OR($A51="",L51=""),"",L51-K51) | N51: =IF($A51="","",IF(L51="","NOT SUBMITTED",IF(M51=0,"MATCHED","CASH DIFFERENCE")))
A52: =IFERROR(INDEX(tblCollectors[Collector ID],4)&"","") | B52: =IF($A52="","",INDEX(tblCollectors[Collector Name],4)) | C52: =IF($B52="","",COUNTIFS(tblBilling[Month],DB_Month,tblBilling[Collector ID],$A52)) | D52: =IF($B52="","",SUMIFS(tblBilling[Monthly Fee],tblBilling[Month],DB_Month,tblBilling[Collector ID],$A52)) | E52: =IF($B52="","",SUMIFS(tblBilling[Amount Paid],tblBilling[Month],DB_Month,tblBilling[Collector ID],$A52)) | F52: =IF($B52="","",SUMIFS(tblBilling[Balance],tblBilling[Month],DB_Month,tblBilling[Collector ID],$A52)) | G52: =IF($B52="","",COUNTIFS(tblBilling[Month],DB_Month,tblBilling[Collector ID],$A52,tblBilling[Payment Status],"PAID")) | H52: =IF($B52="","",COUNTIFS(tblBilling[Month],DB_Month,tblBilling[Collector ID],$A52,tblBilling[Payment Status],"PARTIAL")) | I52: =IF($B52="","",COUNTIFS(tblBilling[Month],DB_Month,tblBilling[Collector ID],$A52,tblBilling[Payment Status],"PENDING")) | J52: =IF(OR($B52="",N(D52)=0),"",E52/D52) | K52: =IF($A52="","",SUMIFS(tblPayments[Amount],tblPayments[Collector ID],$A52,tblPayments[Month],DB_Month,tblPayments[Payment Method],"Cash",tblPayments[Voided],"<>Yes")) | L52: =IF($A52="","",IF(COUNTIFS(tblCash[Month],DB_Month,tblCash[Collector ID],$A52,tblCash[Actual Cash Submitted],"<>")=0,"",SUMIFS(tblCash[Actual Cash Submitted],tblCash[Month],DB_Month,tblCash[Collector ID],$A52))) | M52: =IF(OR($A52="",L52=""),"",L52-K52) | N52: =IF($A52="","",IF(L52="","NOT SUBMITTED",IF(M52=0,"MATCHED","CASH DIFFERENCE")))
A53: =IFERROR(INDEX(tblCollectors[Collector ID],5)&"","") | B53: =IF($A53="","",INDEX(tblCollectors[Collector Name],5)) | C53: =IF($B53="","",COUNTIFS(tblBilling[Month],DB_Month,tblBilling[Collector ID],$A53)) | D53: =IF($B53="","",SUMIFS(tblBilling[Monthly Fee],tblBilling[Month],DB_Month,tblBilling[Collector ID],$A53)) | E53: =IF($B53="","",SUMIFS(tblBilling[Amount Paid],tblBilling[Month],DB_Month,tblBilling[Collector ID],$A53)) | F53: =IF($B53="","",SUMIFS(tblBilling[Balance],tblBilling[Month],DB_Month,tblBilling[Collector ID],$A53)) | G53: =IF($B53="","",COUNTIFS(tblBilling[Month],DB_Month,tblBilling[Collector ID],$A53,tblBilling[Payment Status],"PAID")) | H53: =IF($B53="","",COUNTIFS(tblBilling[Month],DB_Month,tblBilling[Collector ID],$A53,tblBilling[Payment Status],"PARTIAL")) | I53: =IF($B53="","",COUNTIFS(tblBilling[Month],DB_Month,tblBilling[Collector ID],$A53,tblBilling[Payment Status],"PENDING")) | J53: =IF(OR($B53="",N(D53)=0),"",E53/D53) | K53: =IF($A53="","",SUMIFS(tblPayments[Amount],tblPayments[Collector ID],$A53,tblPayments[Month],DB_Month,tblPayments[Payment Method],"Cash",tblPayments[Voided],"<>Yes")) | L53: =IF($A53="","",IF(COUNTIFS(tblCash[Month],DB_Month,tblCash[Collector ID],$A53,tblCash[Actual Cash Submitted],"<>")=0,"",SUMIFS(tblCash[Actual Cash Submitted],tblCash[Month],DB_Month,tblCash[Collector ID],$A53))) | M53: =IF(OR($A53="",L53=""),"",L53-K53) | N53: =IF($A53="","",IF(L53="","NOT SUBMITTED",IF(M53=0,"MATCHED","CASH DIFFERENCE")))
A54: =IFERROR(INDEX(tblCollectors[Collector ID],6)&"","") | B54: =IF($A54="","",INDEX(tblCollectors[Collector Name],6)) | C54: =IF($B54="","",COUNTIFS(tblBilling[Month],DB_Month,tblBilling[Collector ID],$A54)) | D54: =IF($B54="","",SUMIFS(tblBilling[Monthly Fee],tblBilling[Month],DB_Month,tblBilling[Collector ID],$A54)) | E54: =IF($B54="","",SUMIFS(tblBilling[Amount Paid],tblBilling[Month],DB_Month,tblBilling[Collector ID],$A54)) | F54: =IF($B54="","",SUMIFS(tblBilling[Balance],tblBilling[Month],DB_Month,tblBilling[Collector ID],$A54)) | G54: =IF($B54="","",COUNTIFS(tblBilling[Month],DB_Month,tblBilling[Collector ID],$A54,tblBilling[Payment Status],"PAID")) | H54: =IF($B54="","",COUNTIFS(tblBilling[Month],DB_Month,tblBilling[Collector ID],$A54,tblBilling[Payment Status],"PARTIAL")) | I54: =IF($B54="","",COUNTIFS(tblBilling[Month],DB_Month,tblBilling[Collector ID],$A54,tblBilling[Payment Status],"PENDING")) | J54: =IF(OR($B54="",N(D54)=0),"",E54/D54) | K54: =IF($A54="","",SUMIFS(tblPayments[Amount],tblPayments[Collector ID],$A54,tblPayments[Month],DB_Month,tblPayments[Payment Method],"Cash",tblPayments[Voided],"<>Yes")) | L54: =IF($A54="","",IF(COUNTIFS(tblCash[Month],DB_Month,tblCash[Collector ID],$A54,tblCash[Actual Cash Submitted],"<>")=0,"",SUMIFS(tblCash[Actual Cash Submitted],tblCash[Month],DB_Month,tblCash[Collector ID],$A54))) | M54: =IF(OR($A54="",L54=""),"",L54-K54) | N54: =IF($A54="","",IF(L54="","NOT SUBMITTED",IF(M54=0,"MATCHED","CASH DIFFERENCE")))
A55: =IFERROR(INDEX(tblCollectors[Collector ID],7)&"","") | B55: =IF($A55="","",INDEX(tblCollectors[Collector Name],7)) | C55: =IF($B55="","",COUNTIFS(tblBilling[Month],DB_Month,tblBilling[Collector ID],$A55)) | D55: =IF($B55="","",SUMIFS(tblBilling[Monthly Fee],tblBilling[Month],DB_Month,tblBilling[Collector ID],$A55)) | E55: =IF($B55="","",SUMIFS(tblBilling[Amount Paid],tblBilling[Month],DB_Month,tblBilling[Collector ID],$A55)) | F55: =IF($B55="","",SUMIFS(tblBilling[Balance],tblBilling[Month],DB_Month,tblBilling[Collector ID],$A55)) | G55: =IF($B55="","",COUNTIFS(tblBilling[Month],DB_Month,tblBilling[Collector ID],$A55,tblBilling[Payment Status],"PAID")) | H55: =IF($B55="","",COUNTIFS(tblBilling[Month],DB_Month,tblBilling[Collector ID],$A55,tblBilling[Payment Status],"PARTIAL")) | I55: =IF($B55="","",COUNTIFS(tblBilling[Month],DB_Month,tblBilling[Collector ID],$A55,tblBilling[Payment Status],"PENDING")) | J55: =IF(OR($B55="",N(D55)=0),"",E55/D55) | K55: =IF($A55="","",SUMIFS(tblPayments[Amount],tblPayments[Collector ID],$A55,tblPayments[Month],DB_Month,tblPayments[Payment Method],"Cash",tblPayments[Voided],"<>Yes")) | L55: =IF($A55="","",IF(COUNTIFS(tblCash[Month],DB_Month,tblCash[Collector ID],$A55,tblCash[Actual Cash Submitted],"<>")=0,"",SUMIFS(tblCash[Actual Cash Submitted],tblCash[Month],DB_Month,tblCash[Collector ID],$A55))) | M55: =IF(OR($A55="",L55=""),"",L55-K55) | N55: =IF($A55="","",IF(L55="","NOT SUBMITTED",IF(M55=0,"MATCHED","CASH DIFFERENCE")))
A56: =IFERROR(INDEX(tblCollectors[Collector ID],8)&"","") | B56: =IF($A56="","",INDEX(tblCollectors[Collector Name],8)) | C56: =IF($B56="","",COUNTIFS(tblBilling[Month],DB_Month,tblBilling[Collector ID],$A56)) | D56: =IF($B56="","",SUMIFS(tblBilling[Monthly Fee],tblBilling[Month],DB_Month,tblBilling[Collector ID],$A56)) | E56: =IF($B56="","",SUMIFS(tblBilling[Amount Paid],tblBilling[Month],DB_Month,tblBilling[Collector ID],$A56)) | F56: =IF($B56="","",SUMIFS(tblBilling[Balance],tblBilling[Month],DB_Month,tblBilling[Collector ID],$A56)) | G56: =IF($B56="","",COUNTIFS(tblBilling[Month],DB_Month,tblBilling[Collector ID],$A56,tblBilling[Payment Status],"PAID")) | H56: =IF($B56="","",COUNTIFS(tblBilling[Month],DB_Month,tblBilling[Collector ID],$A56,tblBilling[Payment Status],"PARTIAL")) | I56: =IF($B56="","",COUNTIFS(tblBilling[Month],DB_Month,tblBilling[Collector ID],$A56,tblBilling[Payment Status],"PENDING")) | J56: =IF(OR($B56="",N(D56)=0),"",E56/D56) | K56: =IF($A56="","",SUMIFS(tblPayments[Amount],tblPayments[Collector ID],$A56,tblPayments[Month],DB_Month,tblPayments[Payment Method],"Cash",tblPayments[Voided],"<>Yes")) | L56: =IF($A56="","",IF(COUNTIFS(tblCash[Month],DB_Month,tblCash[Collector ID],$A56,tblCash[Actual Cash Submitted],"<>")=0,"",SUMIFS(tblCash[Actual Cash Submitted],tblCash[Month],DB_Month,tblCash[Collector ID],$A56))) | M56: =IF(OR($A56="",L56=""),"",L56-K56) | N56: =IF($A56="","",IF(L56="","NOT SUBMITTED",IF(M56=0,"MATCHED","CASH DIFFERENCE")))
A57: =IFERROR(INDEX(tblCollectors[Collector ID],9)&"","") | B57: =IF($A57="","",INDEX(tblCollectors[Collector Name],9)) | C57: =IF($B57="","",COUNTIFS(tblBilling[Month],DB_Month,tblBilling[Collector ID],$A57)) | D57: =IF($B57="","",SUMIFS(tblBilling[Monthly Fee],tblBilling[Month],DB_Month,tblBilling[Collector ID],$A57)) | E57: =IF($B57="","",SUMIFS(tblBilling[Amount Paid],tblBilling[Month],DB_Month,tblBilling[Collector ID],$A57)) | F57: =IF($B57="","",SUMIFS(tblBilling[Balance],tblBilling[Month],DB_Month,tblBilling[Collector ID],$A57)) | G57: =IF($B57="","",COUNTIFS(tblBilling[Month],DB_Month,tblBilling[Collector ID],$A57,tblBilling[Payment Status],"PAID")) | H57: =IF($B57="","",COUNTIFS(tblBilling[Month],DB_Month,tblBilling[Collector ID],$A57,tblBilling[Payment Status],"PARTIAL")) | I57: =IF($B57="","",COUNTIFS(tblBilling[Month],DB_Month,tblBilling[Collector ID],$A57,tblBilling[Payment Status],"PENDING")) | J57: =IF(OR($B57="",N(D57)=0),"",E57/D57) | K57: =IF($A57="","",SUMIFS(tblPayments[Amount],tblPayments[Collector ID],$A57,tblPayments[Month],DB_Month,tblPayments[Payment Method],"Cash",tblPayments[Voided],"<>Yes")) | L57: =IF($A57="","",IF(COUNTIFS(tblCash[Month],DB_Month,tblCash[Collector ID],$A57,tblCash[Actual Cash Submitted],"<>")=0,"",SUMIFS(tblCash[Actual Cash Submitted],tblCash[Month],DB_Month,tblCash[Collector ID],$A57))) | M57: =IF(OR($A57="",L57=""),"",L57-K57) | N57: =IF($A57="","",IF(L57="","NOT SUBMITTED",IF(M57=0,"MATCHED","CASH DIFFERENCE")))
A58: =IFERROR(INDEX(tblCollectors[Collector ID],10)&"","") | B58: =IF($A58="","",INDEX(tblCollectors[Collector Name],10)) | C58: =IF($B58="","",COUNTIFS(tblBilling[Month],DB_Month,tblBilling[Collector ID],$A58)) | D58: =IF($B58="","",SUMIFS(tblBilling[Monthly Fee],tblBilling[Month],DB_Month,tblBilling[Collector ID],$A58)) | E58: =IF($B58="","",SUMIFS(tblBilling[Amount Paid],tblBilling[Month],DB_Month,tblBilling[Collector ID],$A58)) | F58: =IF($B58="","",SUMIFS(tblBilling[Balance],tblBilling[Month],DB_Month,tblBilling[Collector ID],$A58)) | G58: =IF($B58="","",COUNTIFS(tblBilling[Month],DB_Month,tblBilling[Collector ID],$A58,tblBilling[Payment Status],"PAID")) | H58: =IF($B58="","",COUNTIFS(tblBilling[Month],DB_Month,tblBilling[Collector ID],$A58,tblBilling[Payment Status],"PARTIAL")) | I58: =IF($B58="","",COUNTIFS(tblBilling[Month],DB_Month,tblBilling[Collector ID],$A58,tblBilling[Payment Status],"PENDING")) | J58: =IF(OR($B58="",N(D58)=0),"",E58/D58) | K58: =IF($A58="","",SUMIFS(tblPayments[Amount],tblPayments[Collector ID],$A58,tblPayments[Month],DB_Month,tblPayments[Payment Method],"Cash",tblPayments[Voided],"<>Yes")) | L58: =IF($A58="","",IF(COUNTIFS(tblCash[Month],DB_Month,tblCash[Collector ID],$A58,tblCash[Actual Cash Submitted],"<>")=0,"",SUMIFS(tblCash[Actual Cash Submitted],tblCash[Month],DB_Month,tblCash[Collector ID],$A58))) | M58: =IF(OR($A58="",L58=""),"",L58-K58) | N58: =IF($A58="","",IF(L58="","NOT SUBMITTED",IF(M58=0,"MATCHED","CASH DIFFERENCE")))
A59: =IFERROR(INDEX(tblCollectors[Collector ID],11)&"","") | B59: =IF($A59="","",INDEX(tblCollectors[Collector Name],11)) | C59: =IF($B59="","",COUNTIFS(tblBilling[Month],DB_Month,tblBilling[Collector ID],$A59)) | D59: =IF($B59="","",SUMIFS(tblBilling[Monthly Fee],tblBilling[Month],DB_Month,tblBilling[Collector ID],$A59)) | E59: =IF($B59="","",SUMIFS(tblBilling[Amount Paid],tblBilling[Month],DB_Month,tblBilling[Collector ID],$A59)) | F59: =IF($B59="","",SUMIFS(tblBilling[Balance],tblBilling[Month],DB_Month,tblBilling[Collector ID],$A59)) | G59: =IF($B59="","",COUNTIFS(tblBilling[Month],DB_Month,tblBilling[Collector ID],$A59,tblBilling[Payment Status],"PAID")) | H59: =IF($B59="","",COUNTIFS(tblBilling[Month],DB_Month,tblBilling[Collector ID],$A59,tblBilling[Payment Status],"PARTIAL")) | I59: =IF($B59="","",COUNTIFS(tblBilling[Month],DB_Month,tblBilling[Collector ID],$A59,tblBilling[Payment Status],"PENDING")) | J59: =IF(OR($B59="",N(D59)=0),"",E59/D59) | K59: =IF($A59="","",SUMIFS(tblPayments[Amount],tblPayments[Collector ID],$A59,tblPayments[Month],DB_Month,tblPayments[Payment Method],"Cash",tblPayments[Voided],"<>Yes")) | L59: =IF($A59="","",IF(COUNTIFS(tblCash[Month],DB_Month,tblCash[Collector ID],$A59,tblCash[Actual Cash Submitted],"<>")=0,"",SUMIFS(tblCash[Actual Cash Submitted],tblCash[Month],DB_Month,tblCash[Collector ID],$A59))) | M59: =IF(OR($A59="",L59=""),"",L59-K59) | N59: =IF($A59="","",IF(L59="","NOT SUBMITTED",IF(M59=0,"MATCHED","CASH DIFFERENCE")))
A60: =IFERROR(INDEX(tblCollectors[Collector ID],12)&"","") | B60: =IF($A60="","",INDEX(tblCollectors[Collector Name],12)) | C60: =IF($B60="","",COUNTIFS(tblBilling[Month],DB_Month,tblBilling[Collector ID],$A60)) | D60: =IF($B60="","",SUMIFS(tblBilling[Monthly Fee],tblBilling[Month],DB_Month,tblBilling[Collector ID],$A60)) | E60: =IF($B60="","",SUMIFS(tblBilling[Amount Paid],tblBilling[Month],DB_Month,tblBilling[Collector ID],$A60)) | F60: =IF($B60="","",SUMIFS(tblBilling[Balance],tblBilling[Month],DB_Month,tblBilling[Collector ID],$A60)) | G60: =IF($B60="","",COUNTIFS(tblBilling[Month],DB_Month,tblBilling[Collector ID],$A60,tblBilling[Payment Status],"PAID")) | H60: =IF($B60="","",COUNTIFS(tblBilling[Month],DB_Month,tblBilling[Collector ID],$A60,tblBilling[Payment Status],"PARTIAL")) | I60: =IF($B60="","",COUNTIFS(tblBilling[Month],DB_Month,tblBilling[Collector ID],$A60,tblBilling[Payment Status],"PENDING")) | J60: =IF(OR($B60="",N(D60)=0),"",E60/D60) | K60: =IF($A60="","",SUMIFS(tblPayments[Amount],tblPayments[Collector ID],$A60,tblPayments[Month],DB_Month,tblPayments[Payment Method],"Cash",tblPayments[Voided],"<>Yes")) | L60: =IF($A60="","",IF(COUNTIFS(tblCash[Month],DB_Month,tblCash[Collector ID],$A60,tblCash[Actual Cash Submitted],"<>")=0,"",SUMIFS(tblCash[Actual Cash Submitted],tblCash[Month],DB_Month,tblCash[Collector ID],$A60))) | M60: =IF(OR($A60="",L60=""),"",L60-K60) | N60: =IF($A60="","",IF(L60="","NOT SUBMITTED",IF(M60=0,"MATCHED","CASH DIFFERENCE")))
A61: =IFERROR(INDEX(tblCollectors[Collector ID],13)&"","") | B61: =IF($A61="","",INDEX(tblCollectors[Collector Name],13)) | C61: =IF($B61="","",COUNTIFS(tblBilling[Month],DB_Month,tblBilling[Collector ID],$A61)) | D61: =IF($B61="","",SUMIFS(tblBilling[Monthly Fee],tblBilling[Month],DB_Month,tblBilling[Collector ID],$A61)) | E61: =IF($B61="","",SUMIFS(tblBilling[Amount Paid],tblBilling[Month],DB_Month,tblBilling[Collector ID],$A61)) | F61: =IF($B61="","",SUMIFS(tblBilling[Balance],tblBilling[Month],DB_Month,tblBilling[Collector ID],$A61)) | G61: =IF($B61="","",COUNTIFS(tblBilling[Month],DB_Month,tblBilling[Collector ID],$A61,tblBilling[Payment Status],"PAID")) | H61: =IF($B61="","",COUNTIFS(tblBilling[Month],DB_Month,tblBilling[Collector ID],$A61,tblBilling[Payment Status],"PARTIAL")) | I61: =IF($B61="","",COUNTIFS(tblBilling[Month],DB_Month,tblBilling[Collector ID],$A61,tblBilling[Payment Status],"PENDING")) | J61: =IF(OR($B61="",N(D61)=0),"",E61/D61) | K61: =IF($A61="","",SUMIFS(tblPayments[Amount],tblPayments[Collector ID],$A61,tblPayments[Month],DB_Month,tblPayments[Payment Method],"Cash",tblPayments[Voided],"<>Yes")) | L61: =IF($A61="","",IF(COUNTIFS(tblCash[Month],DB_Month,tblCash[Collector ID],$A61,tblCash[Actual Cash Submitted],"<>")=0,"",SUMIFS(tblCash[Actual Cash Submitted],tblCash[Month],DB_Month,tblCash[Collector ID],$A61))) | M61: =IF(OR($A61="",L61=""),"",L61-K61) | N61: =IF($A61="","",IF(L61="","NOT SUBMITTED",IF(M61=0,"MATCHED","CASH DIFFERENCE")))
A62: =IFERROR(INDEX(tblCollectors[Collector ID],14)&"","") | B62: =IF($A62="","",INDEX(tblCollectors[Collector Name],14)) | C62: =IF($B62="","",COUNTIFS(tblBilling[Month],DB_Month,tblBilling[Collector ID],$A62)) | D62: =IF($B62="","",SUMIFS(tblBilling[Monthly Fee],tblBilling[Month],DB_Month,tblBilling[Collector ID],$A62)) | E62: =IF($B62="","",SUMIFS(tblBilling[Amount Paid],tblBilling[Month],DB_Month,tblBilling[Collector ID],$A62)) | F62: =IF($B62="","",SUMIFS(tblBilling[Balance],tblBilling[Month],DB_Month,tblBilling[Collector ID],$A62)) | G62: =IF($B62="","",COUNTIFS(tblBilling[Month],DB_Month,tblBilling[Collector ID],$A62,tblBilling[Payment Status],"PAID")) | H62: =IF($B62="","",COUNTIFS(tblBilling[Month],DB_Month,tblBilling[Collector ID],$A62,tblBilling[Payment Status],"PARTIAL")) | I62: =IF($B62="","",COUNTIFS(tblBilling[Month],DB_Month,tblBilling[Collector ID],$A62,tblBilling[Payment Status],"PENDING")) | J62: =IF(OR($B62="",N(D62)=0),"",E62/D62) | K62: =IF($A62="","",SUMIFS(tblPayments[Amount],tblPayments[Collector ID],$A62,tblPayments[Month],DB_Month,tblPayments[Payment Method],"Cash",tblPayments[Voided],"<>Yes")) | L62: =IF($A62="","",IF(COUNTIFS(tblCash[Month],DB_Month,tblCash[Collector ID],$A62,tblCash[Actual Cash Submitted],"<>")=0,"",SUMIFS(tblCash[Actual Cash Submitted],tblCash[Month],DB_Month,tblCash[Collector ID],$A62))) | M62: =IF(OR($A62="",L62=""),"",L62-K62) | N62: =IF($A62="","",IF(L62="","NOT SUBMITTED",IF(M62=0,"MATCHED","CASH DIFFERENCE")))
A63: =IFERROR(INDEX(tblCollectors[Collector ID],15)&"","") | B63: =IF($A63="","",INDEX(tblCollectors[Collector Name],15)) | C63: =IF($B63="","",COUNTIFS(tblBilling[Month],DB_Month,tblBilling[Collector ID],$A63)) | D63: =IF($B63="","",SUMIFS(tblBilling[Monthly Fee],tblBilling[Month],DB_Month,tblBilling[Collector ID],$A63)) | E63: =IF($B63="","",SUMIFS(tblBilling[Amount Paid],tblBilling[Month],DB_Month,tblBilling[Collector ID],$A63)) | F63: =IF($B63="","",SUMIFS(tblBilling[Balance],tblBilling[Month],DB_Month,tblBilling[Collector ID],$A63)) | G63: =IF($B63="","",COUNTIFS(tblBilling[Month],DB_Month,tblBilling[Collector ID],$A63,tblBilling[Payment Status],"PAID")) | H63: =IF($B63="","",COUNTIFS(tblBilling[Month],DB_Month,tblBilling[Collector ID],$A63,tblBilling[Payment Status],"PARTIAL")) | I63: =IF($B63="","",COUNTIFS(tblBilling[Month],DB_Month,tblBilling[Collector ID],$A63,tblBilling[Payment Status],"PENDING")) | J63: =IF(OR($B63="",N(D63)=0),"",E63/D63) | K63: =IF($A63="","",SUMIFS(tblPayments[Amount],tblPayments[Collector ID],$A63,tblPayments[Month],DB_Month,tblPayments[Payment Method],"Cash",tblPayments[Voided],"<>Yes")) | L63: =IF($A63="","",IF(COUNTIFS(tblCash[Month],DB_Month,tblCash[Collector ID],$A63,tblCash[Actual Cash Submitted],"<>")=0,"",SUMIFS(tblCash[Actual Cash Submitted],tblCash[Month],DB_Month,tblCash[Collector ID],$A63))) | M63: =IF(OR($A63="",L63=""),"",L63-K63) | N63: =IF($A63="","",IF(L63="","NOT SUBMITTED",IF(M63=0,"MATCHED","CASH DIFFERENCE")))
A64: =IFERROR(INDEX(tblCollectors[Collector ID],16)&"","") | B64: =IF($A64="","",INDEX(tblCollectors[Collector Name],16)) | C64: =IF($B64="","",COUNTIFS(tblBilling[Month],DB_Month,tblBilling[Collector ID],$A64)) | D64: =IF($B64="","",SUMIFS(tblBilling[Monthly Fee],tblBilling[Month],DB_Month,tblBilling[Collector ID],$A64)) | E64: =IF($B64="","",SUMIFS(tblBilling[Amount Paid],tblBilling[Month],DB_Month,tblBilling[Collector ID],$A64)) | F64: =IF($B64="","",SUMIFS(tblBilling[Balance],tblBilling[Month],DB_Month,tblBilling[Collector ID],$A64)) | G64: =IF($B64="","",COUNTIFS(tblBilling[Month],DB_Month,tblBilling[Collector ID],$A64,tblBilling[Payment Status],"PAID")) | H64: =IF($B64="","",COUNTIFS(tblBilling[Month],DB_Month,tblBilling[Collector ID],$A64,tblBilling[Payment Status],"PARTIAL")) | I64: =IF($B64="","",COUNTIFS(tblBilling[Month],DB_Month,tblBilling[Collector ID],$A64,tblBilling[Payment Status],"PENDING")) | J64: =IF(OR($B64="",N(D64)=0),"",E64/D64) | K64: =IF($A64="","",SUMIFS(tblPayments[Amount],tblPayments[Collector ID],$A64,tblPayments[Month],DB_Month,tblPayments[Payment Method],"Cash",tblPayments[Voided],"<>Yes")) | L64: =IF($A64="","",IF(COUNTIFS(tblCash[Month],DB_Month,tblCash[Collector ID],$A64,tblCash[Actual Cash Submitted],"<>")=0,"",SUMIFS(tblCash[Actual Cash Submitted],tblCash[Month],DB_Month,tblCash[Collector ID],$A64))) | M64: =IF(OR($A64="",L64=""),"",L64-K64) | N64: =IF($A64="","",IF(L64="","NOT SUBMITTED",IF(M64=0,"MATCHED","CASH DIFFERENCE")))
A65: =IFERROR(INDEX(tblCollectors[Collector ID],17)&"","") | B65: =IF($A65="","",INDEX(tblCollectors[Collector Name],17)) | C65: =IF($B65="","",COUNTIFS(tblBilling[Month],DB_Month,tblBilling[Collector ID],$A65)) | D65: =IF($B65="","",SUMIFS(tblBilling[Monthly Fee],tblBilling[Month],DB_Month,tblBilling[Collector ID],$A65)) | E65: =IF($B65="","",SUMIFS(tblBilling[Amount Paid],tblBilling[Month],DB_Month,tblBilling[Collector ID],$A65)) | F65: =IF($B65="","",SUMIFS(tblBilling[Balance],tblBilling[Month],DB_Month,tblBilling[Collector ID],$A65)) | G65: =IF($B65="","",COUNTIFS(tblBilling[Month],DB_Month,tblBilling[Collector ID],$A65,tblBilling[Payment Status],"PAID")) | H65: =IF($B65="","",COUNTIFS(tblBilling[Month],DB_Month,tblBilling[Collector ID],$A65,tblBilling[Payment Status],"PARTIAL")) | I65: =IF($B65="","",COUNTIFS(tblBilling[Month],DB_Month,tblBilling[Collector ID],$A65,tblBilling[Payment Status],"PENDING")) | J65: =IF(OR($B65="",N(D65)=0),"",E65/D65) | K65: =IF($A65="","",SUMIFS(tblPayments[Amount],tblPayments[Collector ID],$A65,tblPayments[Month],DB_Month,tblPayments[Payment Method],"Cash",tblPayments[Voided],"<>Yes")) | L65: =IF($A65="","",IF(COUNTIFS(tblCash[Month],DB_Month,tblCash[Collector ID],$A65,tblCash[Actual Cash Submitted],"<>")=0,"",SUMIFS(tblCash[Actual Cash Submitted],tblCash[Month],DB_Month,tblCash[Collector ID],$A65))) | M65: =IF(OR($A65="",L65=""),"",L65-K65) | N65: =IF($A65="","",IF(L65="","NOT SUBMITTED",IF(M65=0,"MATCHED","CASH DIFFERENCE")))
A66: =IFERROR(INDEX(tblCollectors[Collector ID],18)&"","") | B66: =IF($A66="","",INDEX(tblCollectors[Collector Name],18)) | C66: =IF($B66="","",COUNTIFS(tblBilling[Month],DB_Month,tblBilling[Collector ID],$A66)) | D66: =IF($B66="","",SUMIFS(tblBilling[Monthly Fee],tblBilling[Month],DB_Month,tblBilling[Collector ID],$A66)) | E66: =IF($B66="","",SUMIFS(tblBilling[Amount Paid],tblBilling[Month],DB_Month,tblBilling[Collector ID],$A66)) | F66: =IF($B66="","",SUMIFS(tblBilling[Balance],tblBilling[Month],DB_Month,tblBilling[Collector ID],$A66)) | G66: =IF($B66="","",COUNTIFS(tblBilling[Month],DB_Month,tblBilling[Collector ID],$A66,tblBilling[Payment Status],"PAID")) | H66: =IF($B66="","",COUNTIFS(tblBilling[Month],DB_Month,tblBilling[Collector ID],$A66,tblBilling[Payment Status],"PARTIAL")) | I66: =IF($B66="","",COUNTIFS(tblBilling[Month],DB_Month,tblBilling[Collector ID],$A66,tblBilling[Payment Status],"PENDING")) | J66: =IF(OR($B66="",N(D66)=0),"",E66/D66) | K66: =IF($A66="","",SUMIFS(tblPayments[Amount],tblPayments[Collector ID],$A66,tblPayments[Month],DB_Month,tblPayments[Payment Method],"Cash",tblPayments[Voided],"<>Yes")) | L66: =IF($A66="","",IF(COUNTIFS(tblCash[Month],DB_Month,tblCash[Collector ID],$A66,tblCash[Actual Cash Submitted],"<>")=0,"",SUMIFS(tblCash[Actual Cash Submitted],tblCash[Month],DB_Month,tblCash[Collector ID],$A66))) | M66: =IF(OR($A66="",L66=""),"",L66-K66) | N66: =IF($A66="","",IF(L66="","NOT SUBMITTED",IF(M66=0,"MATCHED","CASH DIFFERENCE")))
A67: =IFERROR(INDEX(tblCollectors[Collector ID],19)&"","") | B67: =IF($A67="","",INDEX(tblCollectors[Collector Name],19)) | C67: =IF($B67="","",COUNTIFS(tblBilling[Month],DB_Month,tblBilling[Collector ID],$A67)) | D67: =IF($B67="","",SUMIFS(tblBilling[Monthly Fee],tblBilling[Month],DB_Month,tblBilling[Collector ID],$A67)) | E67: =IF($B67="","",SUMIFS(tblBilling[Amount Paid],tblBilling[Month],DB_Month,tblBilling[Collector ID],$A67)) | F67: =IF($B67="","",SUMIFS(tblBilling[Balance],tblBilling[Month],DB_Month,tblBilling[Collector ID],$A67)) | G67: =IF($B67="","",COUNTIFS(tblBilling[Month],DB_Month,tblBilling[Collector ID],$A67,tblBilling[Payment Status],"PAID")) | H67: =IF($B67="","",COUNTIFS(tblBilling[Month],DB_Month,tblBilling[Collector ID],$A67,tblBilling[Payment Status],"PARTIAL")) | I67: =IF($B67="","",COUNTIFS(tblBilling[Month],DB_Month,tblBilling[Collector ID],$A67,tblBilling[Payment Status],"PENDING")) | J67: =IF(OR($B67="",N(D67)=0),"",E67/D67) | K67: =IF($A67="","",SUMIFS(tblPayments[Amount],tblPayments[Collector ID],$A67,tblPayments[Month],DB_Month,tblPayments[Payment Method],"Cash",tblPayments[Voided],"<>Yes")) | L67: =IF($A67="","",IF(COUNTIFS(tblCash[Month],DB_Month,tblCash[Collector ID],$A67,tblCash[Actual Cash Submitted],"<>")=0,"",SUMIFS(tblCash[Actual Cash Submitted],tblCash[Month],DB_Month,tblCash[Collector ID],$A67))) | M67: =IF(OR($A67="",L67=""),"",L67-K67) | N67: =IF($A67="","",IF(L67="","NOT SUBMITTED",IF(M67=0,"MATCHED","CASH DIFFERENCE")))
A68: =IFERROR(INDEX(tblCollectors[Collector ID],20)&"","") | B68: =IF($A68="","",INDEX(tblCollectors[Collector Name],20)) | C68: =IF($B68="","",COUNTIFS(tblBilling[Month],DB_Month,tblBilling[Collector ID],$A68)) | D68: =IF($B68="","",SUMIFS(tblBilling[Monthly Fee],tblBilling[Month],DB_Month,tblBilling[Collector ID],$A68)) | E68: =IF($B68="","",SUMIFS(tblBilling[Amount Paid],tblBilling[Month],DB_Month,tblBilling[Collector ID],$A68)) | F68: =IF($B68="","",SUMIFS(tblBilling[Balance],tblBilling[Month],DB_Month,tblBilling[Collector ID],$A68)) | G68: =IF($B68="","",COUNTIFS(tblBilling[Month],DB_Month,tblBilling[Collector ID],$A68,tblBilling[Payment Status],"PAID")) | H68: =IF($B68="","",COUNTIFS(tblBilling[Month],DB_Month,tblBilling[Collector ID],$A68,tblBilling[Payment Status],"PARTIAL")) | I68: =IF($B68="","",COUNTIFS(tblBilling[Month],DB_Month,tblBilling[Collector ID],$A68,tblBilling[Payment Status],"PENDING")) | J68: =IF(OR($B68="",N(D68)=0),"",E68/D68) | K68: =IF($A68="","",SUMIFS(tblPayments[Amount],tblPayments[Collector ID],$A68,tblPayments[Month],DB_Month,tblPayments[Payment Method],"Cash",tblPayments[Voided],"<>Yes")) | L68: =IF($A68="","",IF(COUNTIFS(tblCash[Month],DB_Month,tblCash[Collector ID],$A68,tblCash[Actual Cash Submitted],"<>")=0,"",SUMIFS(tblCash[Actual Cash Submitted],tblCash[Month],DB_Month,tblCash[Collector ID],$A68))) | M68: =IF(OR($A68="",L68=""),"",L68-K68) | N68: =IF($A68="","",IF(L68="","NOT SUBMITTED",IF(M68=0,"MATCHED","CASH DIFFERENCE")))
B69: Unassigned | C69: =IF($B69="","",COUNTIFS(tblBilling[Month],DB_Month,tblBilling[Collector ID],"")) | D69: =IF($B69="","",SUMIFS(tblBilling[Monthly Fee],tblBilling[Month],DB_Month,tblBilling[Collector ID],"")) | E69: =IF($B69="","",SUMIFS(tblBilling[Amount Paid],tblBilling[Month],DB_Month,tblBilling[Collector ID],"")) | F69: =IF($B69="","",SUMIFS(tblBilling[Balance],tblBilling[Month],DB_Month,tblBilling[Collector ID],"")) | G69: =IF($B69="","",COUNTIFS(tblBilling[Month],DB_Month,tblBilling[Collector ID],"",tblBilling[Payment Status],"PAID")) | H69: =IF($B69="","",COUNTIFS(tblBilling[Month],DB_Month,tblBilling[Collector ID],"",tblBilling[Payment Status],"PARTIAL")) | I69: =IF($B69="","",COUNTIFS(tblBilling[Month],DB_Month,tblBilling[Collector ID],"",tblBilling[Payment Status],"PENDING")) | J69: =IF(OR($B69="",N(D69)=0),"",E69/D69)
A71: Expected Cash = cash payments recorded under that collector for the month. Actual Cash = amount entered in CASH_RECONCILIATION. A difference is only shown as a number - please add an explanation in CASH_RECONCILIATION > Remarks.
A72: Open Cash Reconciliation ► | D72: Print recovery lists ► | G72: Reports & monthly comparison ►

Sheet CUSTOMERS
A1: CUSTOMER MASTER | M1: ◄ HOME
A2: One row per customer. Grey columns are calculated. Area / Street / Address come from Location Code.
A3: Header colours: dark blue = you type | mid blue = system generated (do not edit) | grey = calculated formula (never type)
A4: Customer ID | B4: Customer Name | C4: Location Code | D4: Area | E4: Street | F4: Address Detail | G4: Full Address | H4: VLAN ID | I4: Package | J4: Package Fee | K4: Fee Override | L4: Monthly Fee | M4: Due Date | N4: Mobile Number | O4: Default Collector ID | P4: Connection Date | Q4: Customer Status | R4: Notes | S4: Created Date | T4: Last Updated | U4: Data Check | V4: Search Match
D5: =IFERROR(INDEX(tblLocations[Area Name],MATCH(tblCustomers[[#This Row],[Location Code]],tblLocations[Location Code],0)),"") | E5: =IFERROR(INDEX(tblLocations[Street Name],MATCH(tblCustomers[[#This Row],[Location Code]],tblLocations[Location Code],0))&"","") | G5: =IFERROR(INDEX(tblLocations[Full Address],MATCH(tblCustomers[[#This Row],[Location Code]],tblLocations[Location Code],0)),"")&IF(tblCustomers[[#This Row],[Address Detail]]="","",", "&tblCustomers[[#This Row],[Address Detail]]) | J5: =IFERROR(INDEX(tblPackages[Default Monthly Fee],MATCH(tblCustomers[[#This Row],[Package]],tblPackages[Package Name],0)),"") | L5: =IF(tblCustomers[[#This Row],[Fee Override]]<>"",tblCustomers[[#This Row],[Fee Override]],tblCustomers[[#This Row],[Package Fee]]) | U5: =TRIM(IF(COUNTIF(tblCustomers[Customer ID],tblCustomers[[#This Row],[Customer ID]])>1,"DUPLICATE CUSTOMER ID. ","")&IF(tblCustomers[[#This Row],[Customer Name]]="","NAME MISSING. ","")&IF(tblCustomers[[#This Row],[Location Code]]="","LOCATION CODE MISSING. ",IF(ISNA(MATCH(tblCustomers[[#This Row],[Location Code]],tblLocations[Location Code],0)),"LOCATION CODE "&tblCustomers[[#This Row],[Location Code]]&" DOES NOT EXIST. ",""))&IF(tblCustomers[[#This Row],[VLAN ID]]="","VLAN ID MISSING. ","")&IF(tblCustomers[[#This Row],[Monthly Fee]]="","MONTHLY FEE MISSING. ","")&IF(tblCustomers[[#This Row],[Due Date]]="","DUE DATE MISSING. ","")&IF(tblCustomers[[#This Row],[Customer Status]]="","STATUS MISSING. ","")&IF(AND(tblCustomers[[#This Row],[Mobile Number]]<>"",COUNTIF(tblCustomers[Mobile Number],tblCustomers[[#This Row],[Mobile Number]])>1),"POSSIBLE DUPLICATE: SAME MOBILE. ","")&IF(AND(tblCustomers[[#This Row],[Customer Name]]<>"",COUNTIFS(tblCustomers[Customer Name],tblCustomers[[#This Row],[Customer Name]],tblCustomers[Location Code],tblCustomers[[#This Row],[Location Code]])>1),"POSSIBLE DUPLICATE: SAME NAME + LOCATION. ","")&IF(AND(tblCustomers[[#This Row],[VLAN ID]]<>"",tblCustomers[[#This Row],[Customer Status]]="Active",COUNTIFS(tblCustomers[VLAN ID],tblCustomers[[#This Row],[VLAN ID]],tblCustomers[Customer Status],"Active")>1),"VLAN USED BY ANOTHER ACTIVE CUSTOMER. ","")) | V5: =IF(CH_SearchText="",0,IF(ISNUMBER(SEARCH(CH_SearchText,CHOOSE(MATCH(CH_SearchType,L_SearchTypes,0),tblCustomers[[#This Row],[Customer ID]],tblCustomers[[#This Row],[Customer Name]],SUBSTITUTE(SUBSTITUTE(tblCustomers[[#This Row],[Mobile Number]],"-","")," ",""),tblCustomers[[#This Row],[VLAN ID]]&"",tblCustomers[[#This Row],[Location Code]],tblCustomers[[#This Row],[Area]],tblCustomers[[#This Row],[Customer ID]]&"|"&tblCustomers[[#This Row],[Customer Name]]&"|"&SUBSTITUTE(tblCustomers[[#This Row],[Mobile Number]],"-","")&"|"&tblCustomers[[#This Row],[VLAN ID]]&"|"&tblCustomers[[#This Row],[Location Code]]&"|"&tblCustomers[[#This Row],[Area]]))),1,0))

Sheet MONTHLY_BILLING
A1: MONTHLY BILLING (ALL MONTHS - HISTORY) | M1: ◄ HOME
A2: One row per customer per month, created by GENERATE NEW MONTH. Never overwritten. Paid / Balance / Status are calculated from PAYMENTS.
A3: Header colours: dark blue = you type | mid blue = system generated (do not edit) | grey = calculated formula (never type)
A4: Billing ID | B4: Month | C4: Month Name | D4: Customer ID | E4: Customer Name | F4: Location Code | G4: Area | H4: Street | I4: Full Address | J4: VLAN ID | K4: Package | L4: Due Date | M4: Monthly Fee | N4: Collector ID | O4: Collector Name | P4: Amount Paid | Q4: Balance | R4: Excess Paid | S4: Payment Status | T4: Overdue | U4: Payments Count | V4: Last Payment Date | W4: Remarks | X4: Created At | Y4: Print Match | Z4: Stmt Match
N5: =IFERROR(INDEX(tblAssignments[Collector ID],MATCH(tblBilling[[#This Row],[Month]]&"|"&tblBilling[[#This Row],[Customer ID]],tblAssignments[Key],0))&"","") | O5: =IF(tblBilling[[#This Row],[Collector ID]]="","Unassigned",IFERROR(INDEX(tblCollectors[Collector Name],MATCH(tblBilling[[#This Row],[Collector ID]],tblCollectors[Collector ID],0)),tblBilling[[#This Row],[Collector ID]])) | P5: =SUMIFS(tblPayments[Amount],tblPayments[Billing ID],tblBilling[[#This Row],[Billing ID]],tblPayments[Voided],"<>Yes") | Q5: =IF(CFG_AllowNegativeBalance="Yes",tblBilling[[#This Row],[Monthly Fee]]-tblBilling[[#This Row],[Amount Paid]],MAX(0,tblBilling[[#This Row],[Monthly Fee]]-tblBilling[[#This Row],[Amount Paid]])) | R5: =MAX(0,tblBilling[[#This Row],[Amount Paid]]-tblBilling[[#This Row],[Monthly Fee]]) | S5: =IF(tblBilling[[#This Row],[Amount Paid]]>=tblBilling[[#This Row],[Monthly Fee]],"PAID",IF(tblBilling[[#This Row],[Amount Paid]]>0,"PARTIAL","PENDING")) | T5: =IF(OR(tblBilling[[#This Row],[Balance]]<=0,tblBilling[[#This Row],[Due Date]]=""),"",IF(TODAY()>DATE(LEFT(tblBilling[[#This Row],[Month]],4),MID(tblBilling[[#This Row],[Month]],6,2),MIN(tblBilling[[#This Row],[Due Date]],DAY(EOMONTH(DATE(LEFT(tblBilling[[#This Row],[Month]],4),MID(tblBilling[[#This Row],[Month]],6,2),1),0))))+CFG_OverdueGraceDays,"OVERDUE","")) | U5: =COUNTIFS(tblPayments[Billing ID],tblBilling[[#This Row],[Billing ID]],tblPayments[Voided],"<>Yes") | V5: =IF(tblBilling[[#This Row],[Payments Count]]=0,"",IFERROR(_xlfn.MAXIFS(tblPayments[Payment Date],tblPayments[Billing ID],tblBilling[[#This Row],[Billing ID]],tblPayments[Voided],"<>Yes"),"")) | Y5: =IF(AND(tblBilling[[#This Row],[Month]]=PC_Month,OR(PC_Area="All",tblBilling[[#This Row],[Area]]=PC_Area),OR(PC_Location="All",tblBilling[[#This Row],[Location Code]]=PC_Location),OR(PC_Collector="All",tblBilling[[#This Row],[Collector Name]]=PC_Collector),OR(PC_DueDate="All",tblBilling[[#This Row],[Due Date]]=PC_DueDate),OR(PC_StatusEff="All",AND(PC_StatusEff="UNPAID",tblBilling[[#This Row],[Balance]]>0),tblBilling[[#This Row],[Payment Status]]=PC_StatusEff,AND(PC_StatusEff="OVERDUE",tblBilling[[#This Row],[Overdue]]="OVERDUE")),OR(PC_Mode<>"Custom Filtered Recovery",PC_CustomCount=0,COUNTIF(PC_CustomIDs,tblBilling[[#This Row],[Customer ID]])>0)),1,0) | Z5: =IF(AND(tblBilling[[#This Row],[Customer ID]]=ST_CustomerID,OR(ST_From="All",tblBilling[[#This Row],[Month]]>=ST_From),OR(ST_To="All",tblBilling[[#This Row],[Month]]<=ST_To)),1,0)

Sheet PAYMENTS
A1: PAYMENT TRANSACTIONS | M1: ◄ HOME
A2: Every payment is a separate row (multiple partial payments allowed). Never delete - set Voided = Yes.
A3: Header colours: dark blue = you type | mid blue = system generated (do not edit) | grey = calculated formula (never type)
A4: Payment ID | B4: Customer ID | C4: Customer Name | D4: Month | E4: Billing ID | F4: Payment Date | G4: Amount | H4: Payment Method | I4: Collector ID | J4: Reference | K4: Remarks | L4: Voided | M4: Void Reason | N4: Created At | O4: Data Check
C5: =IFERROR(INDEX(tblCustomers[Customer Name],MATCH(tblPayments[[#This Row],[Customer ID]],tblCustomers[Customer ID],0)),"CUSTOMER NOT FOUND") | E5: =IF(OR(tblPayments[[#This Row],[Month]]="",tblPayments[[#This Row],[Customer ID]]=""),"",tblPayments[[#This Row],[Month]]&"-"&tblPayments[[#This Row],[Customer ID]]) | O5: =TRIM(IF(AND(tblPayments[[#This Row],[Billing ID]]<>"",ISNA(MATCH(tblPayments[[#This Row],[Billing ID]],tblBilling[Billing ID],0))),"NO BILL FOR THIS CUSTOMER/MONTH. ","")&IF(N(tblPayments[[#This Row],[Amount]])<=0,"AMOUNT MUST BE MORE THAN 0. ","")&IF(COUNTIF(tblPayments[Payment ID],tblPayments[[#This Row],[Payment ID]])>1,"DUPLICATE PAYMENT ID. ","")&IF(tblPayments[[#This Row],[Payment Date]]="","PAYMENT DATE MISSING. ",""))

Sheet PAYMENT_ENTRY
A1: PAYMENT ENTRY | H1: ◄ HOME
A2: Type a Customer ID to see the bill. Recommended: record payments with the menu program (option 'Record payment') - it saves and checks everything automatically.
B4: Customer ID
B5: Month | C5: =CFG_CurrentMonth
B7: Customer Name | C7: =IF(PE_CustomerID="","",IFERROR(INDEX(tblCustomers[Customer Name],MATCH(PE_CustomerID,tblCustomers[Customer ID],0)),"Customer "&PE_CustomerID&" was not found."))
B8: Full Address | C8: =IF(PE_CustomerID="","",IFERROR(INDEX(tblCustomers[Full Address],MATCH(PE_CustomerID,tblCustomers[Customer ID],0)),"Customer "&PE_CustomerID&" was not found."))
B9: VLAN ID | C9: =IF(PE_CustomerID="","",IFERROR(INDEX(tblCustomers[VLAN ID],MATCH(PE_CustomerID,tblCustomers[Customer ID],0)),"Customer "&PE_CustomerID&" was not found."))
B10: Mobile | C10: =IF(PE_CustomerID="","",IFERROR(INDEX(tblCustomers[Mobile Number],MATCH(PE_CustomerID,tblCustomers[Customer ID],0)),"Customer "&PE_CustomerID&" was not found."))
B11: Customer Status | C11: =IF(PE_CustomerID="","",IFERROR(INDEX(tblCustomers[Customer Status],MATCH(PE_CustomerID,tblCustomers[Customer ID],0)),"Customer "&PE_CustomerID&" was not found."))
B12: Bill (this month) | C12: =IF(PE_CustomerID="","",IFERROR(INDEX(tblBilling[Monthly Fee],MATCH(PE_Month&"-"&PE_CustomerID,tblBilling[Billing ID],0)),"No bill for this month"))
B13: Already Paid | C13: =IF(PE_CustomerID="","",IFERROR(INDEX(tblBilling[Amount Paid],MATCH(PE_Month&"-"&PE_CustomerID,tblBilling[Billing ID],0)),"No bill for this month"))
B14: Remaining | C14: =IF(PE_CustomerID="","",IFERROR(INDEX(tblBilling[Balance],MATCH(PE_Month&"-"&PE_CustomerID,tblBilling[Billing ID],0)),"No bill for this month"))
B15: Payment Status | C15: =IF(PE_CustomerID="","",IFERROR(INDEX(tblBilling[Payment Status],MATCH(PE_Month&"-"&PE_CustomerID,tblBilling[Billing ID],0)),"No bill for this month"))
B16: Assigned Collector | C16: =IF(PE_CustomerID="","",IFERROR(INDEX(tblBilling[Collector Name],MATCH(PE_Month&"-"&PE_CustomerID,tblBilling[Billing ID],0)),"No bill for this month"))
B17: Outstanding (all months) | C17: =IF(PE_CustomerID="","",SUMIFS(tblBilling[Balance],tblBilling[Customer ID],PE_CustomerID))
B18: Next Payment ID | C18: ="PAY-"&TEXT(IFERROR(AGGREGATE(14,6,--MID(tblPayments[Payment ID],5,10),1),0)+1,"000000")
B20: HOW TO SAVE A PAYMENT WITHOUT THE MENU PROGRAM
B21: 1. Go to PAYMENTS and type in the first empty row below the table: Payment ID (shown above), Customer ID, Month,
B22: Payment Date, Amount, Payment Method, Collector ID. Set Voided = No.
B23: 2. Amount Paid, Balance and Status in MONTHLY_BILLING update automatically. Several partial payments are allowed.
B24: 3. Never delete a wrong payment - set Voided = Yes and write the reason.
B26: ► Open PAYMENTS
B28: THIS CUSTOMER'S PAYMENTS (latest 20 shown in order entered)
B29: Payment ID | C29: Month | D29: Payment Date | E29: Amount | F29: Method | G29: Collector | H29: Reference | I29: Voided
B30: =IF($K30="","",INDEX(tblPayments[Payment ID],$K30)&"") | C30: =IF($K30="","",INDEX(tblPayments[Month],$K30)&"") | D30: =IF($K30="","",INDEX(tblPayments[Payment Date],$K30)) | E30: =IF($K30="","",INDEX(tblPayments[Amount],$K30)) | F30: =IF($K30="","",INDEX(tblPayments[Payment Method],$K30)&"") | G30: =IF($K30="","",INDEX(tblPayments[Collector ID],$K30)&"") | H30: =IF($K30="","",INDEX(tblPayments[Reference],$K30)&"") | I30: =IF($K30="","",INDEX(tblPayments[Voided],$K30)&"") | K30: =IF(PE_CustomerID="","",IFERROR(MATCH(PE_CustomerID,tblPayments[Customer ID],0),""))
B31: =IF($K31="","",INDEX(tblPayments[Payment ID],$K31)&"") | C31: =IF($K31="","",INDEX(tblPayments[Month],$K31)&"") | D31: =IF($K31="","",INDEX(tblPayments[Payment Date],$K31)) | E31: =IF($K31="","",INDEX(tblPayments[Amount],$K31)) | F31: =IF($K31="","",INDEX(tblPayments[Payment Method],$K31)&"") | G31: =IF($K31="","",INDEX(tblPayments[Collector ID],$K31)&"") | H31: =IF($K31="","",INDEX(tblPayments[Reference],$K31)&"") | I31: =IF($K31="","",INDEX(tblPayments[Voided],$K31)&"") | K31: =IF(K30="","",IFERROR(K30+MATCH(PE_CustomerID,INDEX(tblPayments[Customer ID],K30+1):INDEX(tblPayments[Customer ID],ROWS(tblPayments[Customer ID])),0),""))
B32: =IF($K32="","",INDEX(tblPayments[Payment ID],$K32)&"") | C32: =IF($K32="","",INDEX(tblPayments[Month],$K32)&"") | D32: =IF($K32="","",INDEX(tblPayments[Payment Date],$K32)) | E32: =IF($K32="","",INDEX(tblPayments[Amount],$K32)) | F32: =IF($K32="","",INDEX(tblPayments[Payment Method],$K32)&"") | G32: =IF($K32="","",INDEX(tblPayments[Collector ID],$K32)&"") | H32: =IF($K32="","",INDEX(tblPayments[Reference],$K32)&"") | I32: =IF($K32="","",INDEX(tblPayments[Voided],$K32)&"") | K32: =IF(K31="","",IFERROR(K31+MATCH(PE_CustomerID,INDEX(tblPayments[Customer ID],K31+1):INDEX(tblPayments[Customer ID],ROWS(tblPayments[Customer ID])),0),""))
B33: =IF($K33="","",INDEX(tblPayments[Payment ID],$K33)&"") | C33: =IF($K33="","",INDEX(tblPayments[Month],$K33)&"") | D33: =IF($K33="","",INDEX(tblPayments[Payment Date],$K33)) | E33: =IF($K33="","",INDEX(tblPayments[Amount],$K33)) | F33: =IF($K33="","",INDEX(tblPayments[Payment Method],$K33)&"") | G33: =IF($K33="","",INDEX(tblPayments[Collector ID],$K33)&"") | H33: =IF($K33="","",INDEX(tblPayments[Reference],$K33)&"") | I33: =IF($K33="","",INDEX(tblPayments[Voided],$K33)&"") | K33: =IF(K32="","",IFERROR(K32+MATCH(PE_CustomerID,INDEX(tblPayments[Customer ID],K32+1):INDEX(tblPayments[Customer ID],ROWS(tblPayments[Customer ID])),0),""))
B34: =IF($K34="","",INDEX(tblPayments[Payment ID],$K34)&"") | C34: =IF($K34="","",INDEX(tblPayments[Month],$K34)&"") | D34: =IF($K34="","",INDEX(tblPayments[Payment Date],$K34)) | E34: =IF($K34="","",INDEX(tblPayments[Amount],$K34)) | F34: =IF($K34="","",INDEX(tblPayments[Payment Method],$K34)&"") | G34: =IF($K34="","",INDEX(tblPayments[Collector ID],$K34)&"") | H34: =IF($K34="","",INDEX(tblPayments[Reference],$K34)&"") | I34: =IF($K34="","",INDEX(tblPayments[Voided],$K34)&"") | K34: =IF(K33="","",IFERROR(K33+MATCH(PE_CustomerID,INDEX(tblPayments[Customer ID],K33+1):INDEX(tblPayments[Customer ID],ROWS(tblPayments[Customer ID])),0),""))
B35: =IF($K35="","",INDEX(tblPayments[Payment ID],$K35)&"") | C35: =IF($K35="","",INDEX(tblPayments[Month],$K35)&"") | D35: =IF($K35="","",INDEX(tblPayments[Payment Date],$K35)) | E35: =IF($K35="","",INDEX(tblPayments[Amount],$K35)) | F35: =IF($K35="","",INDEX(tblPayments[Payment Method],$K35)&"") | G35: =IF($K35="","",INDEX(tblPayments[Collector ID],$K35)&"") | H35: =IF($K35="","",INDEX(tblPayments[Reference],$K35)&"") | I35: =IF($K35="","",INDEX(tblPayments[Voided],$K35)&"") | K35: =IF(K34="","",IFERROR(K34+MATCH(PE_CustomerID,INDEX(tblPayments[Customer ID],K34+1):INDEX(tblPayments[Customer ID],ROWS(tblPayments[Customer ID])),0),""))
B36: =IF($K36="","",INDEX(tblPayments[Payment ID],$K36)&"") | C36: =IF($K36="","",INDEX(tblPayments[Month],$K36)&"") | D36: =IF($K36="","",INDEX(tblPayments[Payment Date],$K36)) | E36: =IF($K36="","",INDEX(tblPayments[Amount],$K36)) | F36: =IF($K36="","",INDEX(tblPayments[Payment Method],$K36)&"") | G36: =IF($K36="","",INDEX(tblPayments[Collector ID],$K36)&"") | H36: =IF($K36="","",INDEX(tblPayments[Reference],$K36)&"") | I36: =IF($K36="","",INDEX(tblPayments[Voided],$K36)&"") | K36: =IF(K35="","",IFERROR(K35+MATCH(PE_CustomerID,INDEX(tblPayments[Customer ID],K35+1):INDEX(tblPayments[Customer ID],ROWS(tblPayments[Customer ID])),0),""))
B37: =IF($K37="","",INDEX(tblPayments[Payment ID],$K37)&"") | C37: =IF($K37="","",INDEX(tblPayments[Month],$K37)&"") | D37: =IF($K37="","",INDEX(tblPayments[Payment Date],$K37)) | E37: =IF($K37="","",INDEX(tblPayments[Amount],$K37)) | F37: =IF($K37="","",INDEX(tblPayments[Payment Method],$K37)&"") | G37: =IF($K37="","",INDEX(tblPayments[Collector ID],$K37)&"") | H37: =IF($K37="","",INDEX(tblPayments[Reference],$K37)&"") | I37: =IF($K37="","",INDEX(tblPayments[Voided],$K37)&"") | K37: =IF(K36="","",IFERROR(K36+MATCH(PE_CustomerID,INDEX(tblPayments[Customer ID],K36+1):INDEX(tblPayments[Customer ID],ROWS(tblPayments[Customer ID])),0),""))
B38: =IF($K38="","",INDEX(tblPayments[Payment ID],$K38)&"") | C38: =IF($K38="","",INDEX(tblPayments[Month],$K38)&"") | D38: =IF($K38="","",INDEX(tblPayments[Payment Date],$K38)) | E38: =IF($K38="","",INDEX(tblPayments[Amount],$K38)) | F38: =IF($K38="","",INDEX(tblPayments[Payment Method],$K38)&"") | G38: =IF($K38="","",INDEX(tblPayments[Collector ID],$K38)&"") | H38: =IF($K38="","",INDEX(tblPayments[Reference],$K38)&"") | I38: =IF($K38="","",INDEX(tblPayments[Voided],$K38)&"") | K38: =IF(K37="","",IFERROR(K37+MATCH(PE_CustomerID,INDEX(tblPayments[Customer ID],K37+1):INDEX(tblPayments[Customer ID],ROWS(tblPayments[Customer ID])),0),""))
B39: =IF($K39="","",INDEX(tblPayments[Payment ID],$K39)&"") | C39: =IF($K39="","",INDEX(tblPayments[Month],$K39)&"") | D39: =IF($K39="","",INDEX(tblPayments[Payment Date],$K39)) | E39: =IF($K39="","",INDEX(tblPayments[Amount],$K39)) | F39: =IF($K39="","",INDEX(tblPayments[Payment Method],$K39)&"") | G39: =IF($K39="","",INDEX(tblPayments[Collector ID],$K39)&"") | H39: =IF($K39="","",INDEX(tblPayments[Reference],$K39)&"") | I39: =IF($K39="","",INDEX(tblPayments[Voided],$K39)&"") | K39: =IF(K38="","",IFERROR(K38+MATCH(PE_CustomerID,INDEX(tblPayments[Customer ID],K38+1):INDEX(tblPayments[Customer ID],ROWS(tblPayments[Customer ID])),0),""))
B40: =IF($K40="","",INDEX(tblPayments[Payment ID],$K40)&"") | C40: =IF($K40="","",INDEX(tblPayments[Month],$K40)&"") | D40: =IF($K40="","",INDEX(tblPayments[Payment Date],$K40)) | E40: =IF($K40="","",INDEX(tblPayments[Amount],$K40)) | F40: =IF($K40="","",INDEX(tblPayments[Payment Method],$K40)&"") | G40: =IF($K40="","",INDEX(tblPayments[Collector ID],$K40)&"") | H40: =IF($K40="","",INDEX(tblPayments[Reference],$K40)&"") | I40: =IF($K40="","",INDEX(tblPayments[Voided],$K40)&"") | K40: =IF(K39="","",IFERROR(K39+MATCH(PE_CustomerID,INDEX(tblPayments[Customer ID],K39+1):INDEX(tblPayments[Customer ID],ROWS(tblPayments[Customer ID])),0),""))
B41: =IF($K41="","",INDEX(tblPayments[Payment ID],$K41)&"") | C41: =IF($K41="","",INDEX(tblPayments[Month],$K41)&"") | D41: =IF($K41="","",INDEX(tblPayments[Payment Date],$K41)) | E41: =IF($K41="","",INDEX(tblPayments[Amount],$K41)) | F41: =IF($K41="","",INDEX(tblPayments[Payment Method],$K41)&"") | G41: =IF($K41="","",INDEX(tblPayments[Collector ID],$K41)&"") | H41: =IF($K41="","",INDEX(tblPayments[Reference],$K41)&"") | I41: =IF($K41="","",INDEX(tblPayments[Voided],$K41)&"") | K41: =IF(K40="","",IFERROR(K40+MATCH(PE_CustomerID,INDEX(tblPayments[Customer ID],K40+1):INDEX(tblPayments[Customer ID],ROWS(tblPayments[Customer ID])),0),""))
B42: =IF($K42="","",INDEX(tblPayments[Payment ID],$K42)&"") | C42: =IF($K42="","",INDEX(tblPayments[Month],$K42)&"") | D42: =IF($K42="","",INDEX(tblPayments[Payment Date],$K42)) | E42: =IF($K42="","",INDEX(tblPayments[Amount],$K42)) | F42: =IF($K42="","",INDEX(tblPayments[Payment Method],$K42)&"") | G42: =IF($K42="","",INDEX(tblPayments[Collector ID],$K42)&"") | H42: =IF($K42="","",INDEX(tblPayments[Reference],$K42)&"") | I42: =IF($K42="","",INDEX(tblPayments[Voided],$K42)&"") | K42: =IF(K41="","",IFERROR(K41+MATCH(PE_CustomerID,INDEX(tblPayments[Customer ID],K41+1):INDEX(tblPayments[Customer ID],ROWS(tblPayments[Customer ID])),0),""))
... B49: =IF($K49="","",INDEX(tblPayments[Payment ID],$K49)&"") | C49: =IF($K49="","",INDEX(tblPayments[Month],$K49)&"") | D49: =IF($K49="","",INDEX(tblPayments[Payment Date],$K49)) | E49: =IF($K49="","",INDEX(tblPayments[Amount],$K49)) | F49: =IF($K49="","",INDEX(tblPayments[Payment Method],$K49)&"") | G49: =IF($K49="","",INDEX(tblPayments[Collector ID],$K49)&"") | H49: =IF($K49="","",INDEX(tblPayments[Reference],$K49)&"") | I49: =IF($K49="","",INDEX(tblPayments[Voided],$K49)&"") | K49: =IF(K48="","",IFERROR(K48+MATCH(PE_CustomerID,INDEX(tblPayments[Customer ID],K48+1):INDEX(tblPayments[Customer ID],ROWS(tblPayments[Customer ID])),0),""))

Sheet PRINT_CENTER
A1: PRINT CENTER - RECOVERY LISTS | H1: ◄ HOME
A2: 1) Choose filters in the yellow cells 2) Check the preview count 3) Open PRINT SHEET and print (Ctrl+P).
F3: Custom Customer IDs | G3: Count
B4: Print Mode | C4: Area-wise Recovery | G4: =COUNTIF(PC_CustomIDs,"?*")
B5: Month | C5: =CFG_CurrentMonth | D5: =IFERROR(TEXT(DATE(LEFT(PC_Month,4),MID(PC_Month,6,2),1),"mmmm yyyy"),"")
B6: Area | C6: All
B7: Location Code / Street | C7: All | D7: =IF(PC_Location="All","",IFERROR(INDEX(tblLocations[Full Address],MATCH(PC_Location,tblLocations[Location Code],0)),"Location Code does not exist"))
B8: Collector | C8: All
B9: Payment Status | C9: All | D9: UNPAID = Pending + Partial (everyone who still owes money)
B10: Due Date (day) | C10: All
B12: Effective Status Filter | C12: =IF(AND(PC_Mode="Pending Recovery",PC_Status="All"),"UNPAID",IF(AND(PC_Mode="Partial Payment Recovery",PC_Status="All"),"PARTIAL",PC_Status))
B13: Customers in this list | C13: =SUM(tblBilling[Print Match])
B14: List Title | C14: =TRIM(IF(PC_Location<>"All",IFERROR(INDEX(tblLocations[Full Address],MATCH(PC_Location,tblLocations[Location Code],0)),PC_Location),IF(PC_Area<>"All",PC_Area,"All Areas"))&" "&IFERROR(INDEX(L_PrintStatusLabels,MATCH(PC_StatusEff,L_PrintStatuses,0)),"")&" Recovery List"&IF(PC_Collector<>"All"," - "&PC_Collector,"")&IF(PC_DueDate<>"All"," - Due "&PC_DueDate,""))
B15: Total Billing | C15: =SUMIFS(tblBilling[Monthly Fee],tblBilling[Print Match],1)
B16: Total Recovered | C16: =SUMIFS(tblBilling[Amount Paid],tblBilling[Print Match],1)
B17: Total Pending | C17: =SUMIFS(tblBilling[Balance],tblBilling[Print Match],1)
B18: Message | C18: =IF(COUNTIF(tblBilling[Month],PC_Month)=0,"No billing exists for "&PC_Month&". Generate the month first.",IF(PC_Count>500,"More than 500 customers - narrow the filters or use the menu program (Print recovery list PDF).",IF(PC_Count=0,"No customers match these filters.","Ready to print.")))
C20: ► OPEN PRINT SHEET (English)
C21: ► OPEN PRINT SHEET (Urdu / RTL)
C22: ="Print Language in SETTINGS: "&CFG_PrintLanguage
B24: PRINT MODES (presets)
B25: Area-wise Recovery | C25: Choose Area, keep Location = All.
B26: Street-wise Recovery | C26: Choose Location Code e.g. A1 (Arif Town, Gali 1).
B27: Collector-wise Recovery | C27: Choose Collector (uses RECOVERY_ASSIGNMENTS).
B28: Due-Date-wise Recovery | C28: Choose Due Date (day of month).
B29: Pending Recovery | C29: Status All is treated as UNPAID (pending + partial).
B30: Partial Payment Recovery | C30: Status All is treated as PARTIAL.
B31: Custom Filtered Recovery | C31: Type Customer IDs in column F; only those customers are listed (other filters still apply).

Sheet PRINT_SHEET
A1: =CFG_CompanyName | Z1: =MIN(PC_Count,500)+9+7
A2: =CFG_Tagline
A3: MONTHLY RECOVERY SHEET
A4: =PC_Title
A5: Area: | C5: =PC_Area | D5: Location/Street: | E5: =IF(PC_Location="All","All",PC_Location&" - "&IFERROR(INDEX(tblLocations[Full Address],MATCH(PC_Location,tblLocations[Location Code],0)),"")) | H5: Month: | I5: =IFERROR(TEXT(DATE(LEFT(PC_Month,4),MID(PC_Month,6,2),1),"mmmm yyyy"),PC_Month) | J5: Collector: | K5: =PC_Collector
A6: Total Customers: | C6: =PC_Count | D6: Total Billing: | E6: =CFG_CurrencySymbol&" "&TEXT(PC_TotalFee,"#,##0") | H6: Recovered: | I6: =CFG_CurrencySymbol&" "&TEXT(PC_TotalPaid,"#,##0") | J6: Pending: | K6: =CFG_CurrencySymbol&" "&TEXT(PC_TotalBalance,"#,##0")
A7: Status: | C7: =PC_StatusEff | D7: Printed: | E7: =TODAY()
A9: # | B9: Customer ID | C9: Customer Name | D9: Address | E9: VLAN ID | F9: Due Date | G9: Monthly Fee | H9: Amount Paid | I9: Balance | J9: Status | K9: Collection Date | L9: Collector
A10: =IF($N10="","",ROW()-9) | B10: =IF($N10<>"",INDEX(tblBilling[Customer ID],$N10),"") | C10: =IF($N10<>"",INDEX(tblBilling[Customer Name],$N10),CHOOSE(MIN(MAX($O10,0),7)+1,"","TOTAL","","Total Customers: "&PC_Count,"Total Recovered: "&CFG_CurrencySymbol&" "&TEXT(PC_TotalPaid,"#,##0"),"","Collector Signature: ____________","")) | D10: =IF($N10<>"",INDEX(tblBilling[Full Address],$N10),CHOOSE(MIN(MAX($O10,0),7)+1,"","","","Total Billing: "&CFG_CurrencySymbol&" "&TEXT(PC_TotalFee,"#,##0"),"Total Pending: "&CFG_CurrencySymbol&" "&TEXT(PC_TotalBalance,"#,##0"),"","Office Verification: ____________","")) | E10: =IF($N10<>"",INDEX(tblBilling[VLAN ID],$N10),"") | F10: =IF($N10<>"",INDEX(tblBilling[Due Date],$N10),"") | G10: =IF($N10<>"",INDEX(tblBilling[Monthly Fee],$N10),IF($O10=1,PC_TotalFee,"")) | H10: =IF($N10<>"",INDEX(tblBilling[Amount Paid],$N10),IF($O10=1,PC_TotalPaid,"")) | I10: =IF($N10<>"",INDEX(tblBilling[Balance],$N10),IF($O10=1,PC_TotalBalance,"")) | J10: =IF($N10<>"",INDEX(tblBilling[Payment Status],$N10),"") | K10: =IF($N10<>"",IF(INDEX(tblBilling[Last Payment Date],$N10)="","",INDEX(tblBilling[Last Payment Date],$N10)),"") | L10: =IF($N10<>"",INDEX(tblBilling[Collector Name],$N10),"") | N10: =IFERROR(MATCH(1,tblBilling[Print Match],0),"") | O10: =ROW()-9-MIN(PC_Count,500)
A11: =IF($N11="","",ROW()-9) | B11: =IF($N11<>"",INDEX(tblBilling[Customer ID],$N11),"") | C11: =IF($N11<>"",INDEX(tblBilling[Customer Name],$N11),CHOOSE(MIN(MAX($O11,0),7)+1,"","TOTAL","","Total Customers: "&PC_Count,"Total Recovered: "&CFG_CurrencySymbol&" "&TEXT(PC_TotalPaid,"#,##0"),"","Collector Signature: ____________","")) | D11: =IF($N11<>"",INDEX(tblBilling[Full Address],$N11),CHOOSE(MIN(MAX($O11,0),7)+1,"","","","Total Billing: "&CFG_CurrencySymbol&" "&TEXT(PC_TotalFee,"#,##0"),"Total Pending: "&CFG_CurrencySymbol&" "&TEXT(PC_TotalBalance,"#,##0"),"","Office Verification: ____________","")) | E11: =IF($N11<>"",INDEX(tblBilling[VLAN ID],$N11),"") | F11: =IF($N11<>"",INDEX(tblBilling[Due Date],$N11),"") | G11: =IF($N11<>"",INDEX(tblBilling[Monthly Fee],$N11),IF($O11=1,PC_TotalFee,"")) | H11: =IF($N11<>"",INDEX(tblBilling[Amount Paid],$N11),IF($O11=1,PC_TotalPaid,"")) | I11: =IF($N11<>"",INDEX(tblBilling[Balance],$N11),IF($O11=1,PC_TotalBalance,"")) | J11: =IF($N11<>"",INDEX(tblBilling[Payment Status],$N11),"") | K11: =IF($N11<>"",IF(INDEX(tblBilling[Last Payment Date],$N11)="","",INDEX(tblBilling[Last Payment Date],$N11)),"") | L11: =IF($N11<>"",INDEX(tblBilling[Collector Name],$N11),"") | N11: =IF(N10="","",IFERROR(N10+MATCH(1,INDEX(tblBilling[Print Match],N10+1):INDEX(tblBilling[Print Match],ROWS(tblBilling[Print Match])),0),"")) | O11: =ROW()-9-MIN(PC_Count,500)
A12: =IF($N12="","",ROW()-9) | B12: =IF($N12<>"",INDEX(tblBilling[Customer ID],$N12),"") | C12: =IF($N12<>"",INDEX(tblBilling[Customer Name],$N12),CHOOSE(MIN(MAX($O12,0),7)+1,"","TOTAL","","Total Customers: "&PC_Count,"Total Recovered: "&CFG_CurrencySymbol&" "&TEXT(PC_TotalPaid,"#,##0"),"","Collector Signature: ____________","")) | D12: =IF($N12<>"",INDEX(tblBilling[Full Address],$N12),CHOOSE(MIN(MAX($O12,0),7)+1,"","","","Total Billing: "&CFG_CurrencySymbol&" "&TEXT(PC_TotalFee,"#,##0"),"Total Pending: "&CFG_CurrencySymbol&" "&TEXT(PC_TotalBalance,"#,##0"),"","Office Verification: ____________","")) | E12: =IF($N12<>"",INDEX(tblBilling[VLAN ID],$N12),"") | F12: =IF($N12<>"",INDEX(tblBilling[Due Date],$N12),"") | G12: =IF($N12<>"",INDEX(tblBilling[Monthly Fee],$N12),IF($O12=1,PC_TotalFee,"")) | H12: =IF($N12<>"",INDEX(tblBilling[Amount Paid],$N12),IF($O12=1,PC_TotalPaid,"")) | I12: =IF($N12<>"",INDEX(tblBilling[Balance],$N12),IF($O12=1,PC_TotalBalance,"")) | J12: =IF($N12<>"",INDEX(tblBilling[Payment Status],$N12),"") | K12: =IF($N12<>"",IF(INDEX(tblBilling[Last Payment Date],$N12)="","",INDEX(tblBilling[Last Payment Date],$N12)),"") | L12: =IF($N12<>"",INDEX(tblBilling[Collector Name],$N12),"") | N12: =IF(N11="","",IFERROR(N11+MATCH(1,INDEX(tblBilling[Print Match],N11+1):INDEX(tblBilling[Print Match],ROWS(tblBilling[Print Match])),0),"")) | O12: =ROW()-9-MIN(PC_Count,500)
A13: =IF($N13="","",ROW()-9) | B13: =IF($N13<>"",INDEX(tblBilling[Customer ID],$N13),"") | C13: =IF($N13<>"",INDEX(tblBilling[Customer Name],$N13),CHOOSE(MIN(MAX($O13,0),7)+1,"","TOTAL","","Total Customers: "&PC_Count,"Total Recovered: "&CFG_CurrencySymbol&" "&TEXT(PC_TotalPaid,"#,##0"),"","Collector Signature: ____________","")) | D13: =IF($N13<>"",INDEX(tblBilling[Full Address],$N13),CHOOSE(MIN(MAX($O13,0),7)+1,"","","","Total Billing: "&CFG_CurrencySymbol&" "&TEXT(PC_TotalFee,"#,##0"),"Total Pending: "&CFG_CurrencySymbol&" "&TEXT(PC_TotalBalance,"#,##0"),"","Office Verification: ____________","")) | E13: =IF($N13<>"",INDEX(tblBilling[VLAN ID],$N13),"") | F13: =IF($N13<>"",INDEX(tblBilling[Due Date],$N13),"") | G13: =IF($N13<>"",INDEX(tblBilling[Monthly Fee],$N13),IF($O13=1,PC_TotalFee,"")) | H13: =IF($N13<>"",INDEX(tblBilling[Amount Paid],$N13),IF($O13=1,PC_TotalPaid,"")) | I13: =IF($N13<>"",INDEX(tblBilling[Balance],$N13),IF($O13=1,PC_TotalBalance,"")) | J13: =IF($N13<>"",INDEX(tblBilling[Payment Status],$N13),"") | K13: =IF($N13<>"",IF(INDEX(tblBilling[Last Payment Date],$N13)="","",INDEX(tblBilling[Last Payment Date],$N13)),"") | L13: =IF($N13<>"",INDEX(tblBilling[Collector Name],$N13),"") | N13: =IF(N12="","",IFERROR(N12+MATCH(1,INDEX(tblBilling[Print Match],N12+1):INDEX(tblBilling[Print Match],ROWS(tblBilling[Print Match])),0),"")) | O13: =ROW()-9-MIN(PC_Count,500)
A14: =IF($N14="","",ROW()-9) | B14: =IF($N14<>"",INDEX(tblBilling[Customer ID],$N14),"") | C14: =IF($N14<>"",INDEX(tblBilling[Customer Name],$N14),CHOOSE(MIN(MAX($O14,0),7)+1,"","TOTAL","","Total Customers: "&PC_Count,"Total Recovered: "&CFG_CurrencySymbol&" "&TEXT(PC_TotalPaid,"#,##0"),"","Collector Signature: ____________","")) | D14: =IF($N14<>"",INDEX(tblBilling[Full Address],$N14),CHOOSE(MIN(MAX($O14,0),7)+1,"","","","Total Billing: "&CFG_CurrencySymbol&" "&TEXT(PC_TotalFee,"#,##0"),"Total Pending: "&CFG_CurrencySymbol&" "&TEXT(PC_TotalBalance,"#,##0"),"","Office Verification: ____________","")) | E14: =IF($N14<>"",INDEX(tblBilling[VLAN ID],$N14),"") | F14: =IF($N14<>"",INDEX(tblBilling[Due Date],$N14),"") | G14: =IF($N14<>"",INDEX(tblBilling[Monthly Fee],$N14),IF($O14=1,PC_TotalFee,"")) | H14: =IF($N14<>"",INDEX(tblBilling[Amount Paid],$N14),IF($O14=1,PC_TotalPaid,"")) | I14: =IF($N14<>"",INDEX(tblBilling[Balance],$N14),IF($O14=1,PC_TotalBalance,"")) | J14: =IF($N14<>"",INDEX(tblBilling[Payment Status],$N14),"") | K14: =IF($N14<>"",IF(INDEX(tblBilling[Last Payment Date],$N14)="","",INDEX(tblBilling[Last Payment Date],$N14)),"") | L14: =IF($N14<>"",INDEX(tblBilling[Collector Name],$N14),"") | N14: =IF(N13="","",IFERROR(N13+MATCH(1,INDEX(tblBilling[Print Match],N13+1):INDEX(tblBilling[Print Match],ROWS(tblBilling[Print Match])),0),"")) | O14: =ROW()-9-MIN(PC_Count,500)
A15: =IF($N15="","",ROW()-9) | B15: =IF($N15<>"",INDEX(tblBilling[Customer ID],$N15),"") | C15: =IF($N15<>"",INDEX(tblBilling[Customer Name],$N15),CHOOSE(MIN(MAX($O15,0),7)+1,"","TOTAL","","Total Customers: "&PC_Count,"Total Recovered: "&CFG_CurrencySymbol&" "&TEXT(PC_TotalPaid,"#,##0"),"","Collector Signature: ____________","")) | D15: =IF($N15<>"",INDEX(tblBilling[Full Address],$N15),CHOOSE(MIN(MAX($O15,0),7)+1,"","","","Total Billing: "&CFG_CurrencySymbol&" "&TEXT(PC_TotalFee,"#,##0"),"Total Pending: "&CFG_CurrencySymbol&" "&TEXT(PC_TotalBalance,"#,##0"),"","Office Verification: ____________","")) | E15: =IF($N15<>"",INDEX(tblBilling[VLAN ID],$N15),"") | F15: =IF($N15<>"",INDEX(tblBilling[Due Date],$N15),"") | G15: =IF($N15<>"",INDEX(tblBilling[Monthly Fee],$N15),IF($O15=1,PC_TotalFee,"")) | H15: =IF($N15<>"",INDEX(tblBilling[Amount Paid],$N15),IF($O15=1,PC_TotalPaid,"")) | I15: =IF($N15<>"",INDEX(tblBilling[Balance],$N15),IF($O15=1,PC_TotalBalance,"")) | J15: =IF($N15<>"",INDEX(tblBilling[Payment Status],$N15),"") | K15: =IF($N15<>"",IF(INDEX(tblBilling[Last Payment Date],$N15)="","",INDEX(tblBilling[Last Payment Date],$N15)),"") | L15: =IF($N15<>"",INDEX(tblBilling[Collector Name],$N15),"") | N15: =IF(N14="","",IFERROR(N14+MATCH(1,INDEX(tblBilling[Print Match],N14+1):INDEX(tblBilling[Print Match],ROWS(tblBilling[Print Match])),0),"")) | O15: =ROW()-9-MIN(PC_Count,500)
A16: =IF($N16="","",ROW()-9) | B16: =IF($N16<>"",INDEX(tblBilling[Customer ID],$N16),"") | C16: =IF($N16<>"",INDEX(tblBilling[Customer Name],$N16),CHOOSE(MIN(MAX($O16,0),7)+1,"","TOTAL","","Total Customers: "&PC_Count,"Total Recovered: "&CFG_CurrencySymbol&" "&TEXT(PC_TotalPaid,"#,##0"),"","Collector Signature: ____________","")) | D16: =IF($N16<>"",INDEX(tblBilling[Full Address],$N16),CHOOSE(MIN(MAX($O16,0),7)+1,"","","","Total Billing: "&CFG_CurrencySymbol&" "&TEXT(PC_TotalFee,"#,##0"),"Total Pending: "&CFG_CurrencySymbol&" "&TEXT(PC_TotalBalance,"#,##0"),"","Office Verification: ____________","")) | E16: =IF($N16<>"",INDEX(tblBilling[VLAN ID],$N16),"") | F16: =IF($N16<>"",INDEX(tblBilling[Due Date],$N16),"") | G16: =IF($N16<>"",INDEX(tblBilling[Monthly Fee],$N16),IF($O16=1,PC_TotalFee,"")) | H16: =IF($N16<>"",INDEX(tblBilling[Amount Paid],$N16),IF($O16=1,PC_TotalPaid,"")) | I16: =IF($N16<>"",INDEX(tblBilling[Balance],$N16),IF($O16=1,PC_TotalBalance,"")) | J16: =IF($N16<>"",INDEX(tblBilling[Payment Status],$N16),"") | K16: =IF($N16<>"",IF(INDEX(tblBilling[Last Payment Date],$N16)="","",INDEX(tblBilling[Last Payment Date],$N16)),"") | L16: =IF($N16<>"",INDEX(tblBilling[Collector Name],$N16),"") | N16: =IF(N15="","",IFERROR(N15+MATCH(1,INDEX(tblBilling[Print Match],N15+1):INDEX(tblBilling[Print Match],ROWS(tblBilling[Print Match])),0),"")) | O16: =ROW()-9-MIN(PC_Count,500)
A17: =IF($N17="","",ROW()-9) | B17: =IF($N17<>"",INDEX(tblBilling[Customer ID],$N17),"") | C17: =IF($N17<>"",INDEX(tblBilling[Customer Name],$N17),CHOOSE(MIN(MAX($O17,0),7)+1,"","TOTAL","","Total Customers: "&PC_Count,"Total Recovered: "&CFG_CurrencySymbol&" "&TEXT(PC_TotalPaid,"#,##0"),"","Collector Signature: ____________","")) | D17: =IF($N17<>"",INDEX(tblBilling[Full Address],$N17),CHOOSE(MIN(MAX($O17,0),7)+1,"","","","Total Billing: "&CFG_CurrencySymbol&" "&TEXT(PC_TotalFee,"#,##0"),"Total Pending: "&CFG_CurrencySymbol&" "&TEXT(PC_TotalBalance,"#,##0"),"","Office Verification: ____________","")) | E17: =IF($N17<>"",INDEX(tblBilling[VLAN ID],$N17),"") | F17: =IF($N17<>"",INDEX(tblBilling[Due Date],$N17),"") | G17: =IF($N17<>"",INDEX(tblBilling[Monthly Fee],$N17),IF($O17=1,PC_TotalFee,"")) | H17: =IF($N17<>"",INDEX(tblBilling[Amount Paid],$N17),IF($O17=1,PC_TotalPaid,"")) | I17: =IF($N17<>"",INDEX(tblBilling[Balance],$N17),IF($O17=1,PC_TotalBalance,"")) | J17: =IF($N17<>"",INDEX(tblBilling[Payment Status],$N17),"") | K17: =IF($N17<>"",IF(INDEX(tblBilling[Last Payment Date],$N17)="","",INDEX(tblBilling[Last Payment Date],$N17)),"") | L17: =IF($N17<>"",INDEX(tblBilling[Collector Name],$N17),"") | N17: =IF(N16="","",IFERROR(N16+MATCH(1,INDEX(tblBilling[Print Match],N16+1):INDEX(tblBilling[Print Match],ROWS(tblBilling[Print Match])),0),"")) | O17: =ROW()-9-MIN(PC_Count,500)
A18: =IF($N18="","",ROW()-9) | B18: =IF($N18<>"",INDEX(tblBilling[Customer ID],$N18),"") | C18: =IF($N18<>"",INDEX(tblBilling[Customer Name],$N18),CHOOSE(MIN(MAX($O18,0),7)+1,"","TOTAL","","Total Customers: "&PC_Count,"Total Recovered: "&CFG_CurrencySymbol&" "&TEXT(PC_TotalPaid,"#,##0"),"","Collector Signature: ____________","")) | D18: =IF($N18<>"",INDEX(tblBilling[Full Address],$N18),CHOOSE(MIN(MAX($O18,0),7)+1,"","","","Total Billing: "&CFG_CurrencySymbol&" "&TEXT(PC_TotalFee,"#,##0"),"Total Pending: "&CFG_CurrencySymbol&" "&TEXT(PC_TotalBalance,"#,##0"),"","Office Verification: ____________","")) | E18: =IF($N18<>"",INDEX(tblBilling[VLAN ID],$N18),"") | F18: =IF($N18<>"",INDEX(tblBilling[Due Date],$N18),"") | G18: =IF($N18<>"",INDEX(tblBilling[Monthly Fee],$N18),IF($O18=1,PC_TotalFee,"")) | H18: =IF($N18<>"",INDEX(tblBilling[Amount Paid],$N18),IF($O18=1,PC_TotalPaid,"")) | I18: =IF($N18<>"",INDEX(tblBilling[Balance],$N18),IF($O18=1,PC_TotalBalance,"")) | J18: =IF($N18<>"",INDEX(tblBilling[Payment Status],$N18),"") | K18: =IF($N18<>"",IF(INDEX(tblBilling[Last Payment Date],$N18)="","",INDEX(tblBilling[Last Payment Date],$N18)),"") | L18: =IF($N18<>"",INDEX(tblBilling[Collector Name],$N18),"") | N18: =IF(N17="","",IFERROR(N17+MATCH(1,INDEX(tblBilling[Print Match],N17+1):INDEX(tblBilling[Print Match],ROWS(tblBilling[Print Match])),0),"")) | O18: =ROW()-9-MIN(PC_Count,500)
A19: =IF($N19="","",ROW()-9) | B19: =IF($N19<>"",INDEX(tblBilling[Customer ID],$N19),"") | C19: =IF($N19<>"",INDEX(tblBilling[Customer Name],$N19),CHOOSE(MIN(MAX($O19,0),7)+1,"","TOTAL","","Total Customers: "&PC_Count,"Total Recovered: "&CFG_CurrencySymbol&" "&TEXT(PC_TotalPaid,"#,##0"),"","Collector Signature: ____________","")) | D19: =IF($N19<>"",INDEX(tblBilling[Full Address],$N19),CHOOSE(MIN(MAX($O19,0),7)+1,"","","","Total Billing: "&CFG_CurrencySymbol&" "&TEXT(PC_TotalFee,"#,##0"),"Total Pending: "&CFG_CurrencySymbol&" "&TEXT(PC_TotalBalance,"#,##0"),"","Office Verification: ____________","")) | E19: =IF($N19<>"",INDEX(tblBilling[VLAN ID],$N19),"") | F19: =IF($N19<>"",INDEX(tblBilling[Due Date],$N19),"") | G19: =IF($N19<>"",INDEX(tblBilling[Monthly Fee],$N19),IF($O19=1,PC_TotalFee,"")) | H19: =IF($N19<>"",INDEX(tblBilling[Amount Paid],$N19),IF($O19=1,PC_TotalPaid,"")) | I19: =IF($N19<>"",INDEX(tblBilling[Balance],$N19),IF($O19=1,PC_TotalBalance,"")) | J19: =IF($N19<>"",INDEX(tblBilling[Payment Status],$N19),"") | K19: =IF($N19<>"",IF(INDEX(tblBilling[Last Payment Date],$N19)="","",INDEX(tblBilling[Last Payment Date],$N19)),"") | L19: =IF($N19<>"",INDEX(tblBilling[Collector Name],$N19),"") | N19: =IF(N18="","",IFERROR(N18+MATCH(1,INDEX(tblBilling[Print Match],N18+1):INDEX(tblBilling[Print Match],ROWS(tblBilling[Print Match])),0),"")) | O19: =ROW()-9-MIN(PC_Count,500)
A20: =IF($N20="","",ROW()-9) | B20: =IF($N20<>"",INDEX(tblBilling[Customer ID],$N20),"") | C20: =IF($N20<>"",INDEX(tblBilling[Customer Name],$N20),CHOOSE(MIN(MAX($O20,0),7)+1,"","TOTAL","","Total Customers: "&PC_Count,"Total Recovered: "&CFG_CurrencySymbol&" "&TEXT(PC_TotalPaid,"#,##0"),"","Collector Signature: ____________","")) | D20: =IF($N20<>"",INDEX(tblBilling[Full Address],$N20),CHOOSE(MIN(MAX($O20,0),7)+1,"","","","Total Billing: "&CFG_CurrencySymbol&" "&TEXT(PC_TotalFee,"#,##0"),"Total Pending: "&CFG_CurrencySymbol&" "&TEXT(PC_TotalBalance,"#,##0"),"","Office Verification: ____________","")) | E20: =IF($N20<>"",INDEX(tblBilling[VLAN ID],$N20),"") | F20: =IF($N20<>"",INDEX(tblBilling[Due Date],$N20),"") | G20: =IF($N20<>"",INDEX(tblBilling[Monthly Fee],$N20),IF($O20=1,PC_TotalFee,"")) | H20: =IF($N20<>"",INDEX(tblBilling[Amount Paid],$N20),IF($O20=1,PC_TotalPaid,"")) | I20: =IF($N20<>"",INDEX(tblBilling[Balance],$N20),IF($O20=1,PC_TotalBalance,"")) | J20: =IF($N20<>"",INDEX(tblBilling[Payment Status],$N20),"") | K20: =IF($N20<>"",IF(INDEX(tblBilling[Last Payment Date],$N20)="","",INDEX(tblBilling[Last Payment Date],$N20)),"") | L20: =IF($N20<>"",INDEX(tblBilling[Collector Name],$N20),"") | N20: =IF(N19="","",IFERROR(N19+MATCH(1,INDEX(tblBilling[Print Match],N19+1):INDEX(tblBilling[Print Match],ROWS(tblBilling[Print Match])),0),"")) | O20: =ROW()-9-MIN(PC_Count,500)
A21: =IF($N21="","",ROW()-9) | B21: =IF($N21<>"",INDEX(tblBilling[Customer ID],$N21),"") | C21: =IF($N21<>"",INDEX(tblBilling[Customer Name],$N21),CHOOSE(MIN(MAX($O21,0),7)+1,"","TOTAL","","Total Customers: "&PC_Count,"Total Recovered: "&CFG_CurrencySymbol&" "&TEXT(PC_TotalPaid,"#,##0"),"","Collector Signature: ____________","")) | D21: =IF($N21<>"",INDEX(tblBilling[Full Address],$N21),CHOOSE(MIN(MAX($O21,0),7)+1,"","","","Total Billing: "&CFG_CurrencySymbol&" "&TEXT(PC_TotalFee,"#,##0"),"Total Pending: "&CFG_CurrencySymbol&" "&TEXT(PC_TotalBalance,"#,##0"),"","Office Verification: ____________","")) | E21: =IF($N21<>"",INDEX(tblBilling[VLAN ID],$N21),"") | F21: =IF($N21<>"",INDEX(tblBilling[Due Date],$N21),"") | G21: =IF($N21<>"",INDEX(tblBilling[Monthly Fee],$N21),IF($O21=1,PC_TotalFee,"")) | H21: =IF($N21<>"",INDEX(tblBilling[Amount Paid],$N21),IF($O21=1,PC_TotalPaid,"")) | I21: =IF($N21<>"",INDEX(tblBilling[Balance],$N21),IF($O21=1,PC_TotalBalance,"")) | J21: =IF($N21<>"",INDEX(tblBilling[Payment Status],$N21),"") | K21: =IF($N21<>"",IF(INDEX(tblBilling[Last Payment Date],$N21)="","",INDEX(tblBilling[Last Payment Date],$N21)),"") | L21: =IF($N21<>"",INDEX(tblBilling[Collector Name],$N21),"") | N21: =IF(N20="","",IFERROR(N20+MATCH(1,INDEX(tblBilling[Print Match],N20+1):INDEX(tblBilling[Print Match],ROWS(tblBilling[Print Match])),0),"")) | O21: =ROW()-9-MIN(PC_Count,500)
A22: =IF($N22="","",ROW()-9) | B22: =IF($N22<>"",INDEX(tblBilling[Customer ID],$N22),"") | C22: =IF($N22<>"",INDEX(tblBilling[Customer Name],$N22),CHOOSE(MIN(MAX($O22,0),7)+1,"","TOTAL","","Total Customers: "&PC_Count,"Total Recovered: "&CFG_CurrencySymbol&" "&TEXT(PC_TotalPaid,"#,##0"),"","Collector Signature: ____________","")) | D22: =IF($N22<>"",INDEX(tblBilling[Full Address],$N22),CHOOSE(MIN(MAX($O22,0),7)+1,"","","","Total Billing: "&CFG_CurrencySymbol&" "&TEXT(PC_TotalFee,"#,##0"),"Total Pending: "&CFG_CurrencySymbol&" "&TEXT(PC_TotalBalance,"#,##0"),"","Office Verification: ____________","")) | E22: =IF($N22<>"",INDEX(tblBilling[VLAN ID],$N22),"") | F22: =IF($N22<>"",INDEX(tblBilling[Due Date],$N22),"") | G22: =IF($N22<>"",INDEX(tblBilling[Monthly Fee],$N22),IF($O22=1,PC_TotalFee,"")) | H22: =IF($N22<>"",INDEX(tblBilling[Amount Paid],$N22),IF($O22=1,PC_TotalPaid,"")) | I22: =IF($N22<>"",INDEX(tblBilling[Balance],$N22),IF($O22=1,PC_TotalBalance,"")) | J22: =IF($N22<>"",INDEX(tblBilling[Payment Status],$N22),"") | K22: =IF($N22<>"",IF(INDEX(tblBilling[Last Payment Date],$N22)="","",INDEX(tblBilling[Last Payment Date],$N22)),"") | L22: =IF($N22<>"",INDEX(tblBilling[Collector Name],$N22),"") | N22: =IF(N21="","",IFERROR(N21+MATCH(1,INDEX(tblBilling[Print Match],N21+1):INDEX(tblBilling[Print Match],ROWS(tblBilling[Print Match])),0),"")) | O22: =ROW()-9-MIN(PC_Count,500)
... A509: =IF($N509="","",ROW()-9) | B509: =IF($N509<>"",INDEX(tblBilling[Customer ID],$N509),"") | C509: =IF($N509<>"",INDEX(tblBilling[Customer Name],$N509),CHOOSE(MIN(MAX($O509,0),7)+1,"","TOTAL","","Total Customers: "&PC_Count,"Total Recovered: "&CFG_CurrencySymbol&" "&TEXT(PC_TotalPaid,"#,##0"),"","Collector Signature: ____________","")) | D509: =IF($N509<>"",INDEX(tblBilling[Full Address],$N509),CHOOSE(MIN(MAX($O509,0),7)+1,"","","","Total Billing: "&CFG_CurrencySymbol&" "&TEXT(PC_TotalFee,"#,##0"),"Total Pending: "&CFG_CurrencySymbol&" "&TEXT(PC_TotalBalance,"#,##0"),"","Office Verification: ____________","")) | E509: =IF($N509<>"",INDEX(tblBilling[VLAN ID],$N509),"") | F509: =IF($N509<>"",INDEX(tblBilling[Due Date],$N509),"") | G509: =IF($N509<>"",INDEX(tblBilling[Monthly Fee],$N509),IF($O509=1,PC_TotalFee,"")) | H509: =IF($N509<>"",INDEX(tblBilling[Amount Paid],$N509),IF($O509=1,PC_TotalPaid,"")) | I509: =IF($N509<>"",INDEX(tblBilling[Balance],$N509),IF($O509=1,PC_TotalBalance,"")) | J509: =IF($N509<>"",INDEX(tblBilling[Payment Status],$N509),"") | K509: =IF($N509<>"",IF(INDEX(tblBilling[Last Payment Date],$N509)="","",INDEX(tblBilling[Last Payment Date],$N509)),"") | L509: =IF($N509<>"",INDEX(tblBilling[Collector Name],$N509),"") | N509: =IF(N508="","",IFERROR(N508+MATCH(1,INDEX(tblBilling[Print Match],N508+1):INDEX(tblBilling[Print Match],ROWS(tblBilling[Print Match])),0),"")) | O509: =ROW()-9-MIN(PC_Count,500)

Sheet PRINT_SHEET_UR
A1: =CFG_CompanyName | Z1: =MIN(PC_Count,500)+9+7
A2: =CFG_Tagline
A3: ماہانہ ریکوری شیٹ
A4: =PC_Title
A5: علاقہ: | C5: =PC_Area | D5: گلی / لوکیشن: | E5: =IF(PC_Location="All","All",PC_Location&" - "&IFERROR(INDEX(tblLocations[Full Address],MATCH(PC_Location,tblLocations[Location Code],0)),"")) | H5: مہینہ: | I5: =IFERROR(TEXT(DATE(LEFT(PC_Month,4),MID(PC_Month,6,2),1),"mmmm yyyy"),PC_Month) | J5: ریکوری: | K5: =PC_Collector
A6: کل کسٹمر: | C6: =PC_Count | D6: کل بل: | E6: =CFG_CurrencySymbol&" "&TEXT(PC_TotalFee,"#,##0") | H6: وصول شدہ: | I6: =CFG_CurrencySymbol&" "&TEXT(PC_TotalPaid,"#,##0") | J6: بقایا: | K6: =CFG_CurrencySymbol&" "&TEXT(PC_TotalBalance,"#,##0")
A7: اسٹیٹس: | C7: =PC_StatusEff | D7: پرنٹ تاریخ: | E7: =TODAY()
A9: # | B9: کسٹمر آئی ڈی | C9: نام | D9: پتہ | E9: VLAN | F9: تاریخ | G9: ماہانہ فیس | H9: وصول شدہ | I9: بقایا | J9: اسٹیٹس | K9: تاریخ وصولی | L9: ریکوری
A10: =IF(PRINT_SHEET!A10="","",PRINT_SHEET!A10) | B10: =IF(PRINT_SHEET!B10="","",PRINT_SHEET!B10) | C10: =IF(PRINT_SHEET!C10="","",PRINT_SHEET!C10) | D10: =IF(PRINT_SHEET!D10="","",PRINT_SHEET!D10) | E10: =IF(PRINT_SHEET!E10="","",PRINT_SHEET!E10) | F10: =IF(PRINT_SHEET!F10="","",PRINT_SHEET!F10) | G10: =IF(PRINT_SHEET!G10="","",PRINT_SHEET!G10) | H10: =IF(PRINT_SHEET!H10="","",PRINT_SHEET!H10) | I10: =IF(PRINT_SHEET!I10="","",PRINT_SHEET!I10) | J10: =IFERROR(INDEX({"ادا شدہ","جزوی","بقایا"},MATCH(PRINT_SHEET!J10,{"PAID","PARTIAL","PENDING"},0)),PRINT_SHEET!J10) | K10: =IF(PRINT_SHEET!K10="","",PRINT_SHEET!K10) | L10: =IF(PRINT_SHEET!L10="","",PRINT_SHEET!L10)
A11: =IF(PRINT_SHEET!A11="","",PRINT_SHEET!A11) | B11: =IF(PRINT_SHEET!B11="","",PRINT_SHEET!B11) | C11: =IF(PRINT_SHEET!C11="","",PRINT_SHEET!C11) | D11: =IF(PRINT_SHEET!D11="","",PRINT_SHEET!D11) | E11: =IF(PRINT_SHEET!E11="","",PRINT_SHEET!E11) | F11: =IF(PRINT_SHEET!F11="","",PRINT_SHEET!F11) | G11: =IF(PRINT_SHEET!G11="","",PRINT_SHEET!G11) | H11: =IF(PRINT_SHEET!H11="","",PRINT_SHEET!H11) | I11: =IF(PRINT_SHEET!I11="","",PRINT_SHEET!I11) | J11: =IFERROR(INDEX({"ادا شدہ","جزوی","بقایا"},MATCH(PRINT_SHEET!J11,{"PAID","PARTIAL","PENDING"},0)),PRINT_SHEET!J11) | K11: =IF(PRINT_SHEET!K11="","",PRINT_SHEET!K11) | L11: =IF(PRINT_SHEET!L11="","",PRINT_SHEET!L11)
A12: =IF(PRINT_SHEET!A12="","",PRINT_SHEET!A12) | B12: =IF(PRINT_SHEET!B12="","",PRINT_SHEET!B12) | C12: =IF(PRINT_SHEET!C12="","",PRINT_SHEET!C12) | D12: =IF(PRINT_SHEET!D12="","",PRINT_SHEET!D12) | E12: =IF(PRINT_SHEET!E12="","",PRINT_SHEET!E12) | F12: =IF(PRINT_SHEET!F12="","",PRINT_SHEET!F12) | G12: =IF(PRINT_SHEET!G12="","",PRINT_SHEET!G12) | H12: =IF(PRINT_SHEET!H12="","",PRINT_SHEET!H12) | I12: =IF(PRINT_SHEET!I12="","",PRINT_SHEET!I12) | J12: =IFERROR(INDEX({"ادا شدہ","جزوی","بقایا"},MATCH(PRINT_SHEET!J12,{"PAID","PARTIAL","PENDING"},0)),PRINT_SHEET!J12) | K12: =IF(PRINT_SHEET!K12="","",PRINT_SHEET!K12) | L12: =IF(PRINT_SHEET!L12="","",PRINT_SHEET!L12)
A13: =IF(PRINT_SHEET!A13="","",PRINT_SHEET!A13) | B13: =IF(PRINT_SHEET!B13="","",PRINT_SHEET!B13) | C13: =IF(PRINT_SHEET!C13="","",PRINT_SHEET!C13) | D13: =IF(PRINT_SHEET!D13="","",PRINT_SHEET!D13) | E13: =IF(PRINT_SHEET!E13="","",PRINT_SHEET!E13) | F13: =IF(PRINT_SHEET!F13="","",PRINT_SHEET!F13) | G13: =IF(PRINT_SHEET!G13="","",PRINT_SHEET!G13) | H13: =IF(PRINT_SHEET!H13="","",PRINT_SHEET!H13) | I13: =IF(PRINT_SHEET!I13="","",PRINT_SHEET!I13) | J13: =IFERROR(INDEX({"ادا شدہ","جزوی","بقایا"},MATCH(PRINT_SHEET!J13,{"PAID","PARTIAL","PENDING"},0)),PRINT_SHEET!J13) | K13: =IF(PRINT_SHEET!K13="","",PRINT_SHEET!K13) | L13: =IF(PRINT_SHEET!L13="","",PRINT_SHEET!L13)
A14: =IF(PRINT_SHEET!A14="","",PRINT_SHEET!A14) | B14: =IF(PRINT_SHEET!B14="","",PRINT_SHEET!B14) | C14: =IF(PRINT_SHEET!C14="","",PRINT_SHEET!C14) | D14: =IF(PRINT_SHEET!D14="","",PRINT_SHEET!D14) | E14: =IF(PRINT_SHEET!E14="","",PRINT_SHEET!E14) | F14: =IF(PRINT_SHEET!F14="","",PRINT_SHEET!F14) | G14: =IF(PRINT_SHEET!G14="","",PRINT_SHEET!G14) | H14: =IF(PRINT_SHEET!H14="","",PRINT_SHEET!H14) | I14: =IF(PRINT_SHEET!I14="","",PRINT_SHEET!I14) | J14: =IFERROR(INDEX({"ادا شدہ","جزوی","بقایا"},MATCH(PRINT_SHEET!J14,{"PAID","PARTIAL","PENDING"},0)),PRINT_SHEET!J14) | K14: =IF(PRINT_SHEET!K14="","",PRINT_SHEET!K14) | L14: =IF(PRINT_SHEET!L14="","",PRINT_SHEET!L14)
A15: =IF(PRINT_SHEET!A15="","",PRINT_SHEET!A15) | B15: =IF(PRINT_SHEET!B15="","",PRINT_SHEET!B15) | C15: =IF(PRINT_SHEET!C15="","",PRINT_SHEET!C15) | D15: =IF(PRINT_SHEET!D15="","",PRINT_SHEET!D15) | E15: =IF(PRINT_SHEET!E15="","",PRINT_SHEET!E15) | F15: =IF(PRINT_SHEET!F15="","",PRINT_SHEET!F15) | G15: =IF(PRINT_SHEET!G15="","",PRINT_SHEET!G15) | H15: =IF(PRINT_SHEET!H15="","",PRINT_SHEET!H15) | I15: =IF(PRINT_SHEET!I15="","",PRINT_SHEET!I15) | J15: =IFERROR(INDEX({"ادا شدہ","جزوی","بقایا"},MATCH(PRINT_SHEET!J15,{"PAID","PARTIAL","PENDING"},0)),PRINT_SHEET!J15) | K15: =IF(PRINT_SHEET!K15="","",PRINT_SHEET!K15) | L15: =IF(PRINT_SHEET!L15="","",PRINT_SHEET!L15)
A16: =IF(PRINT_SHEET!A16="","",PRINT_SHEET!A16) | B16: =IF(PRINT_SHEET!B16="","",PRINT_SHEET!B16) | C16: =IF(PRINT_SHEET!C16="","",PRINT_SHEET!C16) | D16: =IF(PRINT_SHEET!D16="","",PRINT_SHEET!D16) | E16: =IF(PRINT_SHEET!E16="","",PRINT_SHEET!E16) | F16: =IF(PRINT_SHEET!F16="","",PRINT_SHEET!F16) | G16: =IF(PRINT_SHEET!G16="","",PRINT_SHEET!G16) | H16: =IF(PRINT_SHEET!H16="","",PRINT_SHEET!H16) | I16: =IF(PRINT_SHEET!I16="","",PRINT_SHEET!I16) | J16: =IFERROR(INDEX({"ادا شدہ","جزوی","بقایا"},MATCH(PRINT_SHEET!J16,{"PAID","PARTIAL","PENDING"},0)),PRINT_SHEET!J16) | K16: =IF(PRINT_SHEET!K16="","",PRINT_SHEET!K16) | L16: =IF(PRINT_SHEET!L16="","",PRINT_SHEET!L16)
A17: =IF(PRINT_SHEET!A17="","",PRINT_SHEET!A17) | B17: =IF(PRINT_SHEET!B17="","",PRINT_SHEET!B17) | C17: =IF(PRINT_SHEET!C17="","",PRINT_SHEET!C17) | D17: =IF(PRINT_SHEET!D17="","",PRINT_SHEET!D17) | E17: =IF(PRINT_SHEET!E17="","",PRINT_SHEET!E17) | F17: =IF(PRINT_SHEET!F17="","",PRINT_SHEET!F17) | G17: =IF(PRINT_SHEET!G17="","",PRINT_SHEET!G17) | H17: =IF(PRINT_SHEET!H17="","",PRINT_SHEET!H17) | I17: =IF(PRINT_SHEET!I17="","",PRINT_SHEET!I17) | J17: =IFERROR(INDEX({"ادا شدہ","جزوی","بقایا"},MATCH(PRINT_SHEET!J17,{"PAID","PARTIAL","PENDING"},0)),PRINT_SHEET!J17) | K17: =IF(PRINT_SHEET!K17="","",PRINT_SHEET!K17) | L17: =IF(PRINT_SHEET!L17="","",PRINT_SHEET!L17)
A18: =IF(PRINT_SHEET!A18="","",PRINT_SHEET!A18) | B18: =IF(PRINT_SHEET!B18="","",PRINT_SHEET!B18) | C18: =IF(PRINT_SHEET!C18="","",PRINT_SHEET!C18) | D18: =IF(PRINT_SHEET!D18="","",PRINT_SHEET!D18) | E18: =IF(PRINT_SHEET!E18="","",PRINT_SHEET!E18) | F18: =IF(PRINT_SHEET!F18="","",PRINT_SHEET!F18) | G18: =IF(PRINT_SHEET!G18="","",PRINT_SHEET!G18) | H18: =IF(PRINT_SHEET!H18="","",PRINT_SHEET!H18) | I18: =IF(PRINT_SHEET!I18="","",PRINT_SHEET!I18) | J18: =IFERROR(INDEX({"ادا شدہ","جزوی","بقایا"},MATCH(PRINT_SHEET!J18,{"PAID","PARTIAL","PENDING"},0)),PRINT_SHEET!J18) | K18: =IF(PRINT_SHEET!K18="","",PRINT_SHEET!K18) | L18: =IF(PRINT_SHEET!L18="","",PRINT_SHEET!L18)
A19: =IF(PRINT_SHEET!A19="","",PRINT_SHEET!A19) | B19: =IF(PRINT_SHEET!B19="","",PRINT_SHEET!B19) | C19: =IF(PRINT_SHEET!C19="","",PRINT_SHEET!C19) | D19: =IF(PRINT_SHEET!D19="","",PRINT_SHEET!D19) | E19: =IF(PRINT_SHEET!E19="","",PRINT_SHEET!E19) | F19: =IF(PRINT_SHEET!F19="","",PRINT_SHEET!F19) | G19: =IF(PRINT_SHEET!G19="","",PRINT_SHEET!G19) | H19: =IF(PRINT_SHEET!H19="","",PRINT_SHEET!H19) | I19: =IF(PRINT_SHEET!I19="","",PRINT_SHEET!I19) | J19: =IFERROR(INDEX({"ادا شدہ","جزوی","بقایا"},MATCH(PRINT_SHEET!J19,{"PAID","PARTIAL","PENDING"},0)),PRINT_SHEET!J19) | K19: =IF(PRINT_SHEET!K19="","",PRINT_SHEET!K19) | L19: =IF(PRINT_SHEET!L19="","",PRINT_SHEET!L19)
A20: =IF(PRINT_SHEET!A20="","",PRINT_SHEET!A20) | B20: =IF(PRINT_SHEET!B20="","",PRINT_SHEET!B20) | C20: =IF(PRINT_SHEET!C20="","",PRINT_SHEET!C20) | D20: =IF(PRINT_SHEET!D20="","",PRINT_SHEET!D20) | E20: =IF(PRINT_SHEET!E20="","",PRINT_SHEET!E20) | F20: =IF(PRINT_SHEET!F20="","",PRINT_SHEET!F20) | G20: =IF(PRINT_SHEET!G20="","",PRINT_SHEET!G20) | H20: =IF(PRINT_SHEET!H20="","",PRINT_SHEET!H20) | I20: =IF(PRINT_SHEET!I20="","",PRINT_SHEET!I20) | J20: =IFERROR(INDEX({"ادا شدہ","جزوی","بقایا"},MATCH(PRINT_SHEET!J20,{"PAID","PARTIAL","PENDING"},0)),PRINT_SHEET!J20) | K20: =IF(PRINT_SHEET!K20="","",PRINT_SHEET!K20) | L20: =IF(PRINT_SHEET!L20="","",PRINT_SHEET!L20)
A21: =IF(PRINT_SHEET!A21="","",PRINT_SHEET!A21) | B21: =IF(PRINT_SHEET!B21="","",PRINT_SHEET!B21) | C21: =IF(PRINT_SHEET!C21="","",PRINT_SHEET!C21) | D21: =IF(PRINT_SHEET!D21="","",PRINT_SHEET!D21) | E21: =IF(PRINT_SHEET!E21="","",PRINT_SHEET!E21) | F21: =IF(PRINT_SHEET!F21="","",PRINT_SHEET!F21) | G21: =IF(PRINT_SHEET!G21="","",PRINT_SHEET!G21) | H21: =IF(PRINT_SHEET!H21="","",PRINT_SHEET!H21) | I21: =IF(PRINT_SHEET!I21="","",PRINT_SHEET!I21) | J21: =IFERROR(INDEX({"ادا شدہ","جزوی","بقایا"},MATCH(PRINT_SHEET!J21,{"PAID","PARTIAL","PENDING"},0)),PRINT_SHEET!J21) | K21: =IF(PRINT_SHEET!K21="","",PRINT_SHEET!K21) | L21: =IF(PRINT_SHEET!L21="","",PRINT_SHEET!L21)
... A509: =IF(PRINT_SHEET!A509="","",PRINT_SHEET!A509) | B509: =IF(PRINT_SHEET!B509="","",PRINT_SHEET!B509) | C509: =IF(PRINT_SHEET!C509="","",PRINT_SHEET!C509) | D509: =IF(PRINT_SHEET!D509="","",PRINT_SHEET!D509) | E509: =IF(PRINT_SHEET!E509="","",PRINT_SHEET!E509) | F509: =IF(PRINT_SHEET!F509="","",PRINT_SHEET!F509) | G509: =IF(PRINT_SHEET!G509="","",PRINT_SHEET!G509) | H509: =IF(PRINT_SHEET!H509="","",PRINT_SHEET!H509) | I509: =IF(PRINT_SHEET!I509="","",PRINT_SHEET!I509) | J509: =IFERROR(INDEX({"ادا شدہ","جزوی","بقایا"},MATCH(PRINT_SHEET!J509,{"PAID","PARTIAL","PENDING"},0)),PRINT_SHEET!J509) | K509: =IF(PRINT_SHEET!K509="","",PRINT_SHEET!K509) | L509: =IF(PRINT_SHEET!L509="","",PRINT_SHEET!L509)

Sheet CUSTOMER_HISTORY
A1: CUSTOMER HISTORY | J1: ◄ HOME
A2: Search by Customer ID (best), Name, Mobile, VLAN ID, Location Code or Area. Capital/small letters do not matter.
F3: MATCHING CUSTOMERS (first 15)
B4: Search By | C4: Customer ID | F4: Customer ID | G4: Customer Name | H4: Location | I4: VLAN | J4: Mobile | K4: Status
B5: Search Text | F5: =IF($M5="","",INDEX(tblCustomers[Customer ID],$M5)&"") | G5: =IF($M5="","",INDEX(tblCustomers[Customer Name],$M5)&"") | H5: =IF($M5="","",INDEX(tblCustomers[Location Code],$M5)&"") | I5: =IF($M5="","",INDEX(tblCustomers[VLAN ID],$M5)&"") | J5: =IF($M5="","",INDEX(tblCustomers[Mobile Number],$M5)&"") | K5: =IF($M5="","",INDEX(tblCustomers[Customer Status],$M5)&"") | M5: =IFERROR(MATCH(1,tblCustomers[Search Match],0),"")
B6: Matches found | C6: =SUM(tblCustomers[Search Match]) | F6: =IF($M6="","",INDEX(tblCustomers[Customer ID],$M6)&"") | G6: =IF($M6="","",INDEX(tblCustomers[Customer Name],$M6)&"") | H6: =IF($M6="","",INDEX(tblCustomers[Location Code],$M6)&"") | I6: =IF($M6="","",INDEX(tblCustomers[VLAN ID],$M6)&"") | J6: =IF($M6="","",INDEX(tblCustomers[Mobile Number],$M6)&"") | K6: =IF($M6="","",INDEX(tblCustomers[Customer Status],$M6)&"") | M6: =IF(M5="","",IFERROR(M5+MATCH(1,INDEX(tblCustomers[Search Match],M5+1):INDEX(tblCustomers[Search Match],ROWS(tblCustomers[Search Match])),0),""))
B7: SELECTED CUSTOMER ID | C7: =IF(CH_SearchText="","",IF(COUNTIF(tblCustomers[Customer ID],CH_SearchText)=1,INDEX(tblCustomers[Customer ID],MATCH(CH_SearchText,tblCustomers[Customer ID],0)),IF(C6=1,INDEX(tblCustomers[Customer ID],MATCH(1,tblCustomers[Search Match],0)),""))) | D7: =IF(CH_SearchText="","Type a Customer ID (e.g. CL-0025) in Search Text.",IF(C6=0,"Customer "&CH_SearchText&" was not found.",IF(C7="","Several customers match - copy the correct Customer ID from the list on the right into Search Text.",""))) | F7: =IF($M7="","",INDEX(tblCustomers[Customer ID],$M7)&"") | G7: =IF($M7="","",INDEX(tblCustomers[Customer Name],$M7)&"") | H7: =IF($M7="","",INDEX(tblCustomers[Location Code],$M7)&"") | I7: =IF($M7="","",INDEX(tblCustomers[VLAN ID],$M7)&"") | J7: =IF($M7="","",INDEX(tblCustomers[Mobile Number],$M7)&"") | K7: =IF($M7="","",INDEX(tblCustomers[Customer Status],$M7)&"") | M7: =IF(M6="","",IFERROR(M6+MATCH(1,INDEX(tblCustomers[Search Match],M6+1):INDEX(tblCustomers[Search Match],ROWS(tblCustomers[Search Match])),0),""))
F8: =IF($M8="","",INDEX(tblCustomers[Customer ID],$M8)&"") | G8: =IF($M8="","",INDEX(tblCustomers[Customer Name],$M8)&"") | H8: =IF($M8="","",INDEX(tblCustomers[Location Code],$M8)&"") | I8: =IF($M8="","",INDEX(tblCustomers[VLAN ID],$M8)&"") | J8: =IF($M8="","",INDEX(tblCustomers[Mobile Number],$M8)&"") | K8: =IF($M8="","",INDEX(tblCustomers[Customer Status],$M8)&"") | M8: =IF(M7="","",IFERROR(M7+MATCH(1,INDEX(tblCustomers[Search Match],M7+1):INDEX(tblCustomers[Search Match],ROWS(tblCustomers[Search Match])),0),""))
F9: =IF($M9="","",INDEX(tblCustomers[Customer ID],$M9)&"") | G9: =IF($M9="","",INDEX(tblCustomers[Customer Name],$M9)&"") | H9: =IF($M9="","",INDEX(tblCustomers[Location Code],$M9)&"") | I9: =IF($M9="","",INDEX(tblCustomers[VLAN ID],$M9)&"") | J9: =IF($M9="","",INDEX(tblCustomers[Mobile Number],$M9)&"") | K9: =IF($M9="","",INDEX(tblCustomers[Customer Status],$M9)&"") | M9: =IF(M8="","",IFERROR(M8+MATCH(1,INDEX(tblCustomers[Search Match],M8+1):INDEX(tblCustomers[Search Match],ROWS(tblCustomers[Search Match])),0),""))
F10: =IF($M10="","",INDEX(tblCustomers[Customer ID],$M10)&"") | G10: =IF($M10="","",INDEX(tblCustomers[Customer Name],$M10)&"") | H10: =IF($M10="","",INDEX(tblCustomers[Location Code],$M10)&"") | I10: =IF($M10="","",INDEX(tblCustomers[VLAN ID],$M10)&"") | J10: =IF($M10="","",INDEX(tblCustomers[Mobile Number],$M10)&"") | K10: =IF($M10="","",INDEX(tblCustomers[Customer Status],$M10)&"") | M10: =IF(M9="","",IFERROR(M9+MATCH(1,INDEX(tblCustomers[Search Match],M9+1):INDEX(tblCustomers[Search Match],ROWS(tblCustomers[Search Match])),0),""))
F11: =IF($M11="","",INDEX(tblCustomers[Customer ID],$M11)&"") | G11: =IF($M11="","",INDEX(tblCustomers[Customer Name],$M11)&"") | H11: =IF($M11="","",INDEX(tblCustomers[Location Code],$M11)&"") | I11: =IF($M11="","",INDEX(tblCustomers[VLAN ID],$M11)&"") | J11: =IF($M11="","",INDEX(tblCustomers[Mobile Number],$M11)&"") | K11: =IF($M11="","",INDEX(tblCustomers[Customer Status],$M11)&"") | M11: =IF(M10="","",IFERROR(M10+MATCH(1,INDEX(tblCustomers[Search Match],M10+1):INDEX(tblCustomers[Search Match],ROWS(tblCustomers[Search Match])),0),""))
F12: =IF($M12="","",INDEX(tblCustomers[Customer ID],$M12)&"") | G12: =IF($M12="","",INDEX(tblCustomers[Customer Name],$M12)&"") | H12: =IF($M12="","",INDEX(tblCustomers[Location Code],$M12)&"") | I12: =IF($M12="","",INDEX(tblCustomers[VLAN ID],$M12)&"") | J12: =IF($M12="","",INDEX(tblCustomers[Mobile Number],$M12)&"") | K12: =IF($M12="","",INDEX(tblCustomers[Customer Status],$M12)&"") | M12: =IF(M11="","",IFERROR(M11+MATCH(1,INDEX(tblCustomers[Search Match],M11+1):INDEX(tblCustomers[Search Match],ROWS(tblCustomers[Search Match])),0),""))
F13: =IF($M13="","",INDEX(tblCustomers[Customer ID],$M13)&"") | G13: =IF($M13="","",INDEX(tblCustomers[Customer Name],$M13)&"") | H13: =IF($M13="","",INDEX(tblCustomers[Location Code],$M13)&"") | I13: =IF($M13="","",INDEX(tblCustomers[VLAN ID],$M13)&"") | J13: =IF($M13="","",INDEX(tblCustomers[Mobile Number],$M13)&"") | K13: =IF($M13="","",INDEX(tblCustomers[Customer Status],$M13)&"") | M13: =IF(M12="","",IFERROR(M12+MATCH(1,INDEX(tblCustomers[Search Match],M12+1):INDEX(tblCustomers[Search Match],ROWS(tblCustomers[Search Match])),0),""))
F14: =IF($M14="","",INDEX(tblCustomers[Customer ID],$M14)&"") | G14: =IF($M14="","",INDEX(tblCustomers[Customer Name],$M14)&"") | H14: =IF($M14="","",INDEX(tblCustomers[Location Code],$M14)&"") | I14: =IF($M14="","",INDEX(tblCustomers[VLAN ID],$M14)&"") | J14: =IF($M14="","",INDEX(tblCustomers[Mobile Number],$M14)&"") | K14: =IF($M14="","",INDEX(tblCustomers[Customer Status],$M14)&"") | M14: =IF(M13="","",IFERROR(M13+MATCH(1,INDEX(tblCustomers[Search Match],M13+1):INDEX(tblCustomers[Search Match],ROWS(tblCustomers[Search Match])),0),""))
F15: =IF($M15="","",INDEX(tblCustomers[Customer ID],$M15)&"") | G15: =IF($M15="","",INDEX(tblCustomers[Customer Name],$M15)&"") | H15: =IF($M15="","",INDEX(tblCustomers[Location Code],$M15)&"") | I15: =IF($M15="","",INDEX(tblCustomers[VLAN ID],$M15)&"") | J15: =IF($M15="","",INDEX(tblCustomers[Mobile Number],$M15)&"") | K15: =IF($M15="","",INDEX(tblCustomers[Customer Status],$M15)&"") | M15: =IF(M14="","",IFERROR(M14+MATCH(1,INDEX(tblCustomers[Search Match],M14+1):INDEX(tblCustomers[Search Match],ROWS(tblCustomers[Search Match])),0),""))
F16: =IF($M16="","",INDEX(tblCustomers[Customer ID],$M16)&"") | G16: =IF($M16="","",INDEX(tblCustomers[Customer Name],$M16)&"") | H16: =IF($M16="","",INDEX(tblCustomers[Location Code],$M16)&"") | I16: =IF($M16="","",INDEX(tblCustomers[VLAN ID],$M16)&"") | J16: =IF($M16="","",INDEX(tblCustomers[Mobile Number],$M16)&"") | K16: =IF($M16="","",INDEX(tblCustomers[Customer Status],$M16)&"") | M16: =IF(M15="","",IFERROR(M15+MATCH(1,INDEX(tblCustomers[Search Match],M15+1):INDEX(tblCustomers[Search Match],ROWS(tblCustomers[Search Match])),0),""))
F17: =IF($M17="","",INDEX(tblCustomers[Customer ID],$M17)&"") | G17: =IF($M17="","",INDEX(tblCustomers[Customer Name],$M17)&"") | H17: =IF($M17="","",INDEX(tblCustomers[Location Code],$M17)&"") | I17: =IF($M17="","",INDEX(tblCustomers[VLAN ID],$M17)&"") | J17: =IF($M17="","",INDEX(tblCustomers[Mobile Number],$M17)&"") | K17: =IF($M17="","",INDEX(tblCustomers[Customer Status],$M17)&"") | M17: =IF(M16="","",IFERROR(M16+MATCH(1,INDEX(tblCustomers[Search Match],M16+1):INDEX(tblCustomers[Search Match],ROWS(tblCustomers[Search Match])),0),""))
F18: =IF($M18="","",INDEX(tblCustomers[Customer ID],$M18)&"") | G18: =IF($M18="","",INDEX(tblCustomers[Customer Name],$M18)&"") | H18: =IF($M18="","",INDEX(tblCustomers[Location Code],$M18)&"") | I18: =IF($M18="","",INDEX(tblCustomers[VLAN ID],$M18)&"") | J18: =IF($M18="","",INDEX(tblCustomers[Mobile Number],$M18)&"") | K18: =IF($M18="","",INDEX(tblCustomers[Customer Status],$M18)&"") | M18: =IF(M17="","",IFERROR(M17+MATCH(1,INDEX(tblCustomers[Search Match],M17+1):INDEX(tblCustomers[Search Match],ROWS(tblCustomers[Search Match])),0),""))
F19: =IF($M19="","",INDEX(tblCustomers[Customer ID],$M19)&"") | G19: =IF($M19="","",INDEX(tblCustomers[Customer Name],$M19)&"") | H19: =IF($M19="","",INDEX(tblCustomers[Location Code],$M19)&"") | I19: =IF($M19="","",INDEX(tblCustomers[VLAN ID],$M19)&"") | J19: =IF($M19="","",INDEX(tblCustomers[Mobile Number],$M19)&"") | K19: =IF($M19="","",INDEX(tblCustomers[Customer Status],$M19)&"") | M19: =IF(M18="","",IFERROR(M18+MATCH(1,INDEX(tblCustomers[Search Match],M18+1):INDEX(tblCustomers[Search Match],ROWS(tblCustomers[Search Match])),0),""))
B21: CUSTOMER PROFILE | F21: TOTALS
B22: Customer ID | C22: =CH_CustomerID | F22: Total Billing | H22: =IF(CH_CustomerID="","",SUMIFS(tblBilling[Monthly Fee],tblBilling[Customer ID],CH_CustomerID))
B23: Customer Name | C23: =IF(CH_CustomerID="","",INDEX(tblCustomers[Customer Name],MATCH(CH_CustomerID,tblCustomers[Customer ID],0))) | F23: Total Paid | H23: =IF(CH_CustomerID="","",SUMIFS(tblBilling[Amount Paid],tblBilling[Customer ID],CH_CustomerID))
B24: Location Code | C24: =IF(CH_CustomerID="","",INDEX(tblCustomers[Location Code],MATCH(CH_CustomerID,tblCustomers[Customer ID],0))) | F24: Total Outstanding | H24: =IF(CH_CustomerID="","",SUMIFS(tblBilling[Balance],tblBilling[Customer ID],CH_CustomerID))
B25: Area | C25: =IF(CH_CustomerID="","",INDEX(tblCustomers[Area],MATCH(CH_CustomerID,tblCustomers[Customer ID],0))) | F25: Last Payment Date | H25: =IF(CH_CustomerID="","",IF(COUNTIFS(tblPayments[Customer ID],CH_CustomerID,tblPayments[Voided],"<>Yes")=0,"No payments",IFERROR(_xlfn.MAXIFS(tblPayments[Payment Date],tblPayments[Customer ID],CH_CustomerID,tblPayments[Voided],"<>Yes"),"")))
B26: Street | C26: =IF(CH_CustomerID="","",INDEX(tblCustomers[Street],MATCH(CH_CustomerID,tblCustomers[Customer ID],0))) | F26: Last Payment Amount | H26: =IF(OR(CH_CustomerID="",NOT(ISNUMBER(H25))),"",SUMIFS(tblPayments[Amount],tblPayments[Customer ID],CH_CustomerID,tblPayments[Payment Date],H25,tblPayments[Voided],"<>Yes"))
B27: Full Address | C27: =IF(CH_CustomerID="","",INDEX(tblCustomers[Full Address],MATCH(CH_CustomerID,tblCustomers[Customer ID],0))) | F27: Months Billed | H27: =IF(CH_CustomerID="","",COUNTIF(tblBilling[Customer ID],CH_CustomerID))
B28: VLAN ID | C28: =IF(CH_CustomerID="","",INDEX(tblCustomers[VLAN ID],MATCH(CH_CustomerID,tblCustomers[Customer ID],0)))
B29: Package | C29: =IF(CH_CustomerID="","",INDEX(tblCustomers[Package],MATCH(CH_CustomerID,tblCustomers[Customer ID],0))) | F29: WhatsApp | H29: =IF(OR(CH_CustomerID="",C34=""),"",HYPERLINK("https://wa.me/"&IF(LEFT(SUBSTITUTE(SUBSTITUTE(C34,"-","")," ",""),1)="0",CFG_WhatsAppCountryCode&MID(SUBSTITUTE(SUBSTITUTE(C34,"-","")," ",""),2,20),SUBSTITUTE(SUBSTITUTE(C34,"-","")," ",""))&"?text="&_xlfn.ENCODEURL(CFG_WhatsAppMessage),"OPEN WHATSAPP"))
B30: Monthly Fee | C30: =IF(CH_CustomerID="","",INDEX(tblCustomers[Monthly Fee],MATCH(CH_CustomerID,tblCustomers[Customer ID],0))) | F30: The PDF statement must be attached manually in WhatsApp.
B31: Due Date | C31: =IF(CH_CustomerID="","",INDEX(tblCustomers[Due Date],MATCH(CH_CustomerID,tblCustomers[Customer ID],0))) | F31: ► Customer statement sheet
B32: Connection Date | C32: =IF(CH_CustomerID="","",INDEX(tblCustomers[Connection Date],MATCH(CH_CustomerID,tblCustomers[Customer ID],0)))
B33: Current Status | C33: =IF(CH_CustomerID="","",INDEX(tblCustomers[Customer Status],MATCH(CH_CustomerID,tblCustomers[Customer ID],0)))
B34: Mobile | C34: =IF(CH_CustomerID="","",INDEX(tblCustomers[Mobile Number],MATCH(CH_CustomerID,tblCustomers[Customer ID],0)))
B37: COMPLETE BILLING / PAYMENT HISTORY (never overwritten)
B38: Month | C38: Month Name | D38: Bill | E38: Paid | F38: Payment Date | G38: Balance | H38: Status | I38: Collector | J38: Payments
B39: =IF($M39="","",IF(INDEX(tblBilling[Month],$M39)="","",INDEX(tblBilling[Month],$M39))) | C39: =IF($M39="","",IF(INDEX(tblBilling[Month Name],$M39)="","",INDEX(tblBilling[Month Name],$M39))) | D39: =IF($M39="","",IF(INDEX(tblBilling[Monthly Fee],$M39)="","",INDEX(tblBilling[Monthly Fee],$M39))) | E39: =IF($M39="","",IF(INDEX(tblBilling[Amount Paid],$M39)="","",INDEX(tblBilling[Amount Paid],$M39))) | F39: =IF($M39="","",IF(INDEX(tblBilling[Last Payment Date],$M39)="","",INDEX(tblBilling[Last Payment Date],$M39))) | G39: =IF($M39="","",IF(INDEX(tblBilling[Balance],$M39)="","",INDEX(tblBilling[Balance],$M39))) | H39: =IF($M39="","",IF(INDEX(tblBilling[Payment Status],$M39)="","",INDEX(tblBilling[Payment Status],$M39))) | I39: =IF($M39="","",IF(INDEX(tblBilling[Collector Name],$M39)="","",INDEX(tblBilling[Collector Name],$M39))) | J39: =IF($M39="","",IF(INDEX(tblBilling[Payments Count],$M39)="","",INDEX(tblBilling[Payments Count],$M39))) | M39: =IF(CH_CustomerID="","",IFERROR(MATCH(CH_CustomerID,tblBilling[Customer ID],0),""))
B40: =IF($M40="","",IF(INDEX(tblBilling[Month],$M40)="","",INDEX(tblBilling[Month],$M40))) | C40: =IF($M40="","",IF(INDEX(tblBilling[Month Name],$M40)="","",INDEX(tblBilling[Month Name],$M40))) | D40: =IF($M40="","",IF(INDEX(tblBilling[Monthly Fee],$M40)="","",INDEX(tblBilling[Monthly Fee],$M40))) | E40: =IF($M40="","",IF(INDEX(tblBilling[Amount Paid],$M40)="","",INDEX(tblBilling[Amount Paid],$M40))) | F40: =IF($M40="","",IF(INDEX(tblBilling[Last Payment Date],$M40)="","",INDEX(tblBilling[Last Payment Date],$M40))) | G40: =IF($M40="","",IF(INDEX(tblBilling[Balance],$M40)="","",INDEX(tblBilling[Balance],$M40))) | H40: =IF($M40="","",IF(INDEX(tblBilling[Payment Status],$M40)="","",INDEX(tblBilling[Payment Status],$M40))) | I40: =IF($M40="","",IF(INDEX(tblBilling[Collector Name],$M40)="","",INDEX(tblBilling[Collector Name],$M40))) | J40: =IF($M40="","",IF(INDEX(tblBilling[Payments Count],$M40)="","",INDEX(tblBilling[Payments Count],$M40))) | M40: =IF(M39="","",IFERROR(M39+MATCH(CH_CustomerID,INDEX(tblBilling[Customer ID],M39+1):INDEX(tblBilling[Customer ID],ROWS(tblBilling[Customer ID])),0),""))
B41: =IF($M41="","",IF(INDEX(tblBilling[Month],$M41)="","",INDEX(tblBilling[Month],$M41))) | C41: =IF($M41="","",IF(INDEX(tblBilling[Month Name],$M41)="","",INDEX(tblBilling[Month Name],$M41))) | D41: =IF($M41="","",IF(INDEX(tblBilling[Monthly Fee],$M41)="","",INDEX(tblBilling[Monthly Fee],$M41))) | E41: =IF($M41="","",IF(INDEX(tblBilling[Amount Paid],$M41)="","",INDEX(tblBilling[Amount Paid],$M41))) | F41: =IF($M41="","",IF(INDEX(tblBilling[Last Payment Date],$M41)="","",INDEX(tblBilling[Last Payment Date],$M41))) | G41: =IF($M41="","",IF(INDEX(tblBilling[Balance],$M41)="","",INDEX(tblBilling[Balance],$M41))) | H41: =IF($M41="","",IF(INDEX(tblBilling[Payment Status],$M41)="","",INDEX(tblBilling[Payment Status],$M41))) | I41: =IF($M41="","",IF(INDEX(tblBilling[Collector Name],$M41)="","",INDEX(tblBilling[Collector Name],$M41))) | J41: =IF($M41="","",IF(INDEX(tblBilling[Payments Count],$M41)="","",INDEX(tblBilling[Payments Count],$M41))) | M41: =IF(M40="","",IFERROR(M40+MATCH(CH_CustomerID,INDEX(tblBilling[Customer ID],M40+1):INDEX(tblBilling[Customer ID],ROWS(tblBilling[Customer ID])),0),""))
B42: =IF($M42="","",IF(INDEX(tblBilling[Month],$M42)="","",INDEX(tblBilling[Month],$M42))) | C42: =IF($M42="","",IF(INDEX(tblBilling[Month Name],$M42)="","",INDEX(tblBilling[Month Name],$M42))) | D42: =IF($M42="","",IF(INDEX(tblBilling[Monthly Fee],$M42)="","",INDEX(tblBilling[Monthly Fee],$M42))) | E42: =IF($M42="","",IF(INDEX(tblBilling[Amount Paid],$M42)="","",INDEX(tblBilling[Amount Paid],$M42))) | F42: =IF($M42="","",IF(INDEX(tblBilling[Last Payment Date],$M42)="","",INDEX(tblBilling[Last Payment Date],$M42))) | G42: =IF($M42="","",IF(INDEX(tblBilling[Balance],$M42)="","",INDEX(tblBilling[Balance],$M42))) | H42: =IF($M42="","",IF(INDEX(tblBilling[Payment Status],$M42)="","",INDEX(tblBilling[Payment Status],$M42))) | I42: =IF($M42="","",IF(INDEX(tblBilling[Collector Name],$M42)="","",INDEX(tblBilling[Collector Name],$M42))) | J42: =IF($M42="","",IF(INDEX(tblBilling[Payments Count],$M42)="","",INDEX(tblBilling[Payments Count],$M42))) | M42: =IF(M41="","",IFERROR(M41+MATCH(CH_CustomerID,INDEX(tblBilling[Customer ID],M41+1):INDEX(tblBilling[Customer ID],ROWS(tblBilling[Customer ID])),0),""))
B43: =IF($M43="","",IF(INDEX(tblBilling[Month],$M43)="","",INDEX(tblBilling[Month],$M43))) | C43: =IF($M43="","",IF(INDEX(tblBilling[Month Name],$M43)="","",INDEX(tblBilling[Month Name],$M43))) | D43: =IF($M43="","",IF(INDEX(tblBilling[Monthly Fee],$M43)="","",INDEX(tblBilling[Monthly Fee],$M43))) | E43: =IF($M43="","",IF(INDEX(tblBilling[Amount Paid],$M43)="","",INDEX(tblBilling[Amount Paid],$M43))) | F43: =IF($M43="","",IF(INDEX(tblBilling[Last Payment Date],$M43)="","",INDEX(tblBilling[Last Payment Date],$M43))) | G43: =IF($M43="","",IF(INDEX(tblBilling[Balance],$M43)="","",INDEX(tblBilling[Balance],$M43))) | H43: =IF($M43="","",IF(INDEX(tblBilling[Payment Status],$M43)="","",INDEX(tblBilling[Payment Status],$M43))) | I43: =IF($M43="","",IF(INDEX(tblBilling[Collector Name],$M43)="","",INDEX(tblBilling[Collector Name],$M43))) | J43: =IF($M43="","",IF(INDEX(tblBilling[Payments Count],$M43)="","",INDEX(tblBilling[Payments Count],$M43))) | M43: =IF(M42="","",IFERROR(M42+MATCH(CH_CustomerID,INDEX(tblBilling[Customer ID],M42+1):INDEX(tblBilling[Customer ID],ROWS(tblBilling[Customer ID])),0),""))
B44: =IF($M44="","",IF(INDEX(tblBilling[Month],$M44)="","",INDEX(tblBilling[Month],$M44))) | C44: =IF($M44="","",IF(INDEX(tblBilling[Month Name],$M44)="","",INDEX(tblBilling[Month Name],$M44))) | D44: =IF($M44="","",IF(INDEX(tblBilling[Monthly Fee],$M44)="","",INDEX(tblBilling[Monthly Fee],$M44))) | E44: =IF($M44="","",IF(INDEX(tblBilling[Amount Paid],$M44)="","",INDEX(tblBilling[Amount Paid],$M44))) | F44: =IF($M44="","",IF(INDEX(tblBilling[Last Payment Date],$M44)="","",INDEX(tblBilling[Last Payment Date],$M44))) | G44: =IF($M44="","",IF(INDEX(tblBilling[Balance],$M44)="","",INDEX(tblBilling[Balance],$M44))) | H44: =IF($M44="","",IF(INDEX(tblBilling[Payment Status],$M44)="","",INDEX(tblBilling[Payment Status],$M44))) | I44: =IF($M44="","",IF(INDEX(tblBilling[Collector Name],$M44)="","",INDEX(tblBilling[Collector Name],$M44))) | J44: =IF($M44="","",IF(INDEX(tblBilling[Payments Count],$M44)="","",INDEX(tblBilling[Payments Count],$M44))) | M44: =IF(M43="","",IFERROR(M43+MATCH(CH_CustomerID,INDEX(tblBilling[Customer ID],M43+1):INDEX(tblBilling[Customer ID],ROWS(tblBilling[Customer ID])),0),""))
B45: =IF($M45="","",IF(INDEX(tblBilling[Month],$M45)="","",INDEX(tblBilling[Month],$M45))) | C45: =IF($M45="","",IF(INDEX(tblBilling[Month Name],$M45)="","",INDEX(tblBilling[Month Name],$M45))) | D45: =IF($M45="","",IF(INDEX(tblBilling[Monthly Fee],$M45)="","",INDEX(tblBilling[Monthly Fee],$M45))) | E45: =IF($M45="","",IF(INDEX(tblBilling[Amount Paid],$M45)="","",INDEX(tblBilling[Amount Paid],$M45))) | F45: =IF($M45="","",IF(INDEX(tblBilling[Last Payment Date],$M45)="","",INDEX(tblBilling[Last Payment Date],$M45))) | G45: =IF($M45="","",IF(INDEX(tblBilling[Balance],$M45)="","",INDEX(tblBilling[Balance],$M45))) | H45: =IF($M45="","",IF(INDEX(tblBilling[Payment Status],$M45)="","",INDEX(tblBilling[Payment Status],$M45))) | I45: =IF($M45="","",IF(INDEX(tblBilling[Collector Name],$M45)="","",INDEX(tblBilling[Collector Name],$M45))) | J45: =IF($M45="","",IF(INDEX(tblBilling[Payments Count],$M45)="","",INDEX(tblBilling[Payments Count],$M45))) | M45: =IF(M44="","",IFERROR(M44+MATCH(CH_CustomerID,INDEX(tblBilling[Customer ID],M44+1):INDEX(tblBilling[Customer ID],ROWS(tblBilling[Customer ID])),0),""))
B46: =IF($M46="","",IF(INDEX(tblBilling[Month],$M46)="","",INDEX(tblBilling[Month],$M46))) | C46: =IF($M46="","",IF(INDEX(tblBilling[Month Name],$M46)="","",INDEX(tblBilling[Month Name],$M46))) | D46: =IF($M46="","",IF(INDEX(tblBilling[Monthly Fee],$M46)="","",INDEX(tblBilling[Monthly Fee],$M46))) | E46: =IF($M46="","",IF(INDEX(tblBilling[Amount Paid],$M46)="","",INDEX(tblBilling[Amount Paid],$M46))) | F46: =IF($M46="","",IF(INDEX(tblBilling[Last Payment Date],$M46)="","",INDEX(tblBilling[Last Payment Date],$M46))) | G46: =IF($M46="","",IF(INDEX(tblBilling[Balance],$M46)="","",INDEX(tblBilling[Balance],$M46))) | H46: =IF($M46="","",IF(INDEX(tblBilling[Payment Status],$M46)="","",INDEX(tblBilling[Payment Status],$M46))) | I46: =IF($M46="","",IF(INDEX(tblBilling[Collector Name],$M46)="","",INDEX(tblBilling[Collector Name],$M46))) | J46: =IF($M46="","",IF(INDEX(tblBilling[Payments Count],$M46)="","",INDEX(tblBilling[Payments Count],$M46))) | M46: =IF(M45="","",IFERROR(M45+MATCH(CH_CustomerID,INDEX(tblBilling[Customer ID],M45+1):INDEX(tblBilling[Customer ID],ROWS(tblBilling[Customer ID])),0),""))
B47: =IF($M47="","",IF(INDEX(tblBilling[Month],$M47)="","",INDEX(tblBilling[Month],$M47))) | C47: =IF($M47="","",IF(INDEX(tblBilling[Month Name],$M47)="","",INDEX(tblBilling[Month Name],$M47))) | D47: =IF($M47="","",IF(INDEX(tblBilling[Monthly Fee],$M47)="","",INDEX(tblBilling[Monthly Fee],$M47))) | E47: =IF($M47="","",IF(INDEX(tblBilling[Amount Paid],$M47)="","",INDEX(tblBilling[Amount Paid],$M47))) | F47: =IF($M47="","",IF(INDEX(tblBilling[Last Payment Date],$M47)="","",INDEX(tblBilling[Last Payment Date],$M47))) | G47: =IF($M47="","",IF(INDEX(tblBilling[Balance],$M47)="","",INDEX(tblBilling[Balance],$M47))) | H47: =IF($M47="","",IF(INDEX(tblBilling[Payment Status],$M47)="","",INDEX(tblBilling[Payment Status],$M47))) | I47: =IF($M47="","",IF(INDEX(tblBilling[Collector Name],$M47)="","",INDEX(tblBilling[Collector Name],$M47))) | J47: =IF($M47="","",IF(INDEX(tblBilling[Payments Count],$M47)="","",INDEX(tblBilling[Payments Count],$M47))) | M47: =IF(M46="","",IFERROR(M46+MATCH(CH_CustomerID,INDEX(tblBilling[Customer ID],M46+1):INDEX(tblBilling[Customer ID],ROWS(tblBilling[Customer ID])),0),""))
B48: =IF($M48="","",IF(INDEX(tblBilling[Month],$M48)="","",INDEX(tblBilling[Month],$M48))) | C48: =IF($M48="","",IF(INDEX(tblBilling[Month Name],$M48)="","",INDEX(tblBilling[Month Name],$M48))) | D48: =IF($M48="","",IF(INDEX(tblBilling[Monthly Fee],$M48)="","",INDEX(tblBilling[Monthly Fee],$M48))) | E48: =IF($M48="","",IF(INDEX(tblBilling[Amount Paid],$M48)="","",INDEX(tblBilling[Amount Paid],$M48))) | F48: =IF($M48="","",IF(INDEX(tblBilling[Last Payment Date],$M48)="","",INDEX(tblBilling[Last Payment Date],$M48))) | G48: =IF($M48="","",IF(INDEX(tblBilling[Balance],$M48)="","",INDEX(tblBilling[Balance],$M48))) | H48: =IF($M48="","",IF(INDEX(tblBilling[Payment Status],$M48)="","",INDEX(tblBilling[Payment Status],$M48))) | I48: =IF($M48="","",IF(INDEX(tblBilling[Collector Name],$M48)="","",INDEX(tblBilling[Collector Name],$M48))) | J48: =IF($M48="","",IF(INDEX(tblBilling[Payments Count],$M48)="","",INDEX(tblBilling[Payments Count],$M48))) | M48: =IF(M47="","",IFERROR(M47+MATCH(CH_CustomerID,INDEX(tblBilling[Customer ID],M47+1):INDEX(tblBilling[Customer ID],ROWS(tblBilling[Customer ID])),0),""))
B49: =IF($M49="","",IF(INDEX(tblBilling[Month],$M49)="","",INDEX(tblBilling[Month],$M49))) | C49: =IF($M49="","",IF(INDEX(tblBilling[Month Name],$M49)="","",INDEX(tblBilling[Month Name],$M49))) | D49: =IF($M49="","",IF(INDEX(tblBilling[Monthly Fee],$M49)="","",INDEX(tblBilling[Monthly Fee],$M49))) | E49: =IF($M49="","",IF(INDEX(tblBilling[Amount Paid],$M49)="","",INDEX(tblBilling[Amount Paid],$M49))) | F49: =IF($M49="","",IF(INDEX(tblBilling[Last Payment Date],$M49)="","",INDEX(tblBilling[Last Payment Date],$M49))) | G49: =IF($M49="","",IF(INDEX(tblBilling[Balance],$M49)="","",INDEX(tblBilling[Balance],$M49))) | H49: =IF($M49="","",IF(INDEX(tblBilling[Payment Status],$M49)="","",INDEX(tblBilling[Payment Status],$M49))) | I49: =IF($M49="","",IF(INDEX(tblBilling[Collector Name],$M49)="","",INDEX(tblBilling[Collector Name],$M49))) | J49: =IF($M49="","",IF(INDEX(tblBilling[Payments Count],$M49)="","",INDEX(tblBilling[Payments Count],$M49))) | M49: =IF(M48="","",IFERROR(M48+MATCH(CH_CustomerID,INDEX(tblBilling[Customer ID],M48+1):INDEX(tblBilling[Customer ID],ROWS(tblBilling[Customer ID])),0),""))
B50: =IF($M50="","",IF(INDEX(tblBilling[Month],$M50)="","",INDEX(tblBilling[Month],$M50))) | C50: =IF($M50="","",IF(INDEX(tblBilling[Month Name],$M50)="","",INDEX(tblBilling[Month Name],$M50))) | D50: =IF($M50="","",IF(INDEX(tblBilling[Monthly Fee],$M50)="","",INDEX(tblBilling[Monthly Fee],$M50))) | E50: =IF($M50="","",IF(INDEX(tblBilling[Amount Paid],$M50)="","",INDEX(tblBilling[Amount Paid],$M50))) | F50: =IF($M50="","",IF(INDEX(tblBilling[Last Payment Date],$M50)="","",INDEX(tblBilling[Last Payment Date],$M50))) | G50: =IF($M50="","",IF(INDEX(tblBilling[Balance],$M50)="","",INDEX(tblBilling[Balance],$M50))) | H50: =IF($M50="","",IF(INDEX(tblBilling[Payment Status],$M50)="","",INDEX(tblBilling[Payment Status],$M50))) | I50: =IF($M50="","",IF(INDEX(tblBilling[Collector Name],$M50)="","",INDEX(tblBilling[Collector Name],$M50))) | J50: =IF($M50="","",IF(INDEX(tblBilling[Payments Count],$M50)="","",INDEX(tblBilling[Payments Count],$M50))) | M50: =IF(M49="","",IFERROR(M49+MATCH(CH_CustomerID,INDEX(tblBilling[Customer ID],M49+1):INDEX(tblBilling[Customer ID],ROWS(tblBilling[Customer ID])),0),""))
B51: =IF($M51="","",IF(INDEX(tblBilling[Month],$M51)="","",INDEX(tblBilling[Month],$M51))) | C51: =IF($M51="","",IF(INDEX(tblBilling[Month Name],$M51)="","",INDEX(tblBilling[Month Name],$M51))) | D51: =IF($M51="","",IF(INDEX(tblBilling[Monthly Fee],$M51)="","",INDEX(tblBilling[Monthly Fee],$M51))) | E51: =IF($M51="","",IF(INDEX(tblBilling[Amount Paid],$M51)="","",INDEX(tblBilling[Amount Paid],$M51))) | F51: =IF($M51="","",IF(INDEX(tblBilling[Last Payment Date],$M51)="","",INDEX(tblBilling[Last Payment Date],$M51))) | G51: =IF($M51="","",IF(INDEX(tblBilling[Balance],$M51)="","",INDEX(tblBilling[Balance],$M51))) | H51: =IF($M51="","",IF(INDEX(tblBilling[Payment Status],$M51)="","",INDEX(tblBilling[Payment Status],$M51))) | I51: =IF($M51="","",IF(INDEX(tblBilling[Collector Name],$M51)="","",INDEX(tblBilling[Collector Name],$M51))) | J51: =IF($M51="","",IF(INDEX(tblBilling[Payments Count],$M51)="","",INDEX(tblBilling[Payments Count],$M51))) | M51: =IF(M50="","",IFERROR(M50+MATCH(CH_CustomerID,INDEX(tblBilling[Customer ID],M50+1):INDEX(tblBilling[Customer ID],ROWS(tblBilling[Customer ID])),0),""))
... B158: =IF($M158="","",IF(INDEX(tblBilling[Month],$M158)="","",INDEX(tblBilling[Month],$M158))) | C158: =IF($M158="","",IF(INDEX(tblBilling[Month Name],$M158)="","",INDEX(tblBilling[Month Name],$M158))) | D158: =IF($M158="","",IF(INDEX(tblBilling[Monthly Fee],$M158)="","",INDEX(tblBilling[Monthly Fee],$M158))) | E158: =IF($M158="","",IF(INDEX(tblBilling[Amount Paid],$M158)="","",INDEX(tblBilling[Amount Paid],$M158))) | F158: =IF($M158="","",IF(INDEX(tblBilling[Last Payment Date],$M158)="","",INDEX(tblBilling[Last Payment Date],$M158))) | G158: =IF($M158="","",IF(INDEX(tblBilling[Balance],$M158)="","",INDEX(tblBilling[Balance],$M158))) | H158: =IF($M158="","",IF(INDEX(tblBilling[Payment Status],$M158)="","",INDEX(tblBilling[Payment Status],$M158))) | I158: =IF($M158="","",IF(INDEX(tblBilling[Collector Name],$M158)="","",INDEX(tblBilling[Collector Name],$M158))) | J158: =IF($M158="","",IF(INDEX(tblBilling[Payments Count],$M158)="","",INDEX(tblBilling[Payments Count],$M158))) | M158: =IF(M157="","",IFERROR(M157+MATCH(CH_CustomerID,INDEX(tblBilling[Customer ID],M157+1):INDEX(tblBilling[Customer ID],ROWS(tblBilling[Customer ID])),0),""))
B160: CONNECTION HISTORY (CUSTOMER_EVENTS)
B161: Event Date | C161: Event Type | D161: Old Value | E161: New Value | F161: Notes
B162: =IF($M162="","",IF(INDEX(tblEvents[Event Date],$M162)="","",INDEX(tblEvents[Event Date],$M162))) | C162: =IF($M162="","",IF(INDEX(tblEvents[Event Type],$M162)="","",INDEX(tblEvents[Event Type],$M162))) | D162: =IF($M162="","",IF(INDEX(tblEvents[Old Value],$M162)="","",INDEX(tblEvents[Old Value],$M162))) | E162: =IF($M162="","",IF(INDEX(tblEvents[New Value],$M162)="","",INDEX(tblEvents[New Value],$M162))) | F162: =IF($M162="","",IF(INDEX(tblEvents[Notes],$M162)="","",INDEX(tblEvents[Notes],$M162))) | M162: =IF(CH_CustomerID="","",IFERROR(MATCH(CH_CustomerID,tblEvents[Customer ID],0),""))
B163: =IF($M163="","",IF(INDEX(tblEvents[Event Date],$M163)="","",INDEX(tblEvents[Event Date],$M163))) | C163: =IF($M163="","",IF(INDEX(tblEvents[Event Type],$M163)="","",INDEX(tblEvents[Event Type],$M163))) | D163: =IF($M163="","",IF(INDEX(tblEvents[Old Value],$M163)="","",INDEX(tblEvents[Old Value],$M163))) | E163: =IF($M163="","",IF(INDEX(tblEvents[New Value],$M163)="","",INDEX(tblEvents[New Value],$M163))) | F163: =IF($M163="","",IF(INDEX(tblEvents[Notes],$M163)="","",INDEX(tblEvents[Notes],$M163))) | M163: =IF(M162="","",IFERROR(M162+MATCH(CH_CustomerID,INDEX(tblEvents[Customer ID],M162+1):INDEX(tblEvents[Customer ID],ROWS(tblEvents[Customer ID])),0),""))
B164: =IF($M164="","",IF(INDEX(tblEvents[Event Date],$M164)="","",INDEX(tblEvents[Event Date],$M164))) | C164: =IF($M164="","",IF(INDEX(tblEvents[Event Type],$M164)="","",INDEX(tblEvents[Event Type],$M164))) | D164: =IF($M164="","",IF(INDEX(tblEvents[Old Value],$M164)="","",INDEX(tblEvents[Old Value],$M164))) | E164: =IF($M164="","",IF(INDEX(tblEvents[New Value],$M164)="","",INDEX(tblEvents[New Value],$M164))) | F164: =IF($M164="","",IF(INDEX(tblEvents[Notes],$M164)="","",INDEX(tblEvents[Notes],$M164))) | M164: =IF(M163="","",IFERROR(M163+MATCH(CH_CustomerID,INDEX(tblEvents[Customer ID],M163+1):INDEX(tblEvents[Customer ID],ROWS(tblEvents[Customer ID])),0),""))
B165: =IF($M165="","",IF(INDEX(tblEvents[Event Date],$M165)="","",INDEX(tblEvents[Event Date],$M165))) | C165: =IF($M165="","",IF(INDEX(tblEvents[Event Type],$M165)="","",INDEX(tblEvents[Event Type],$M165))) | D165: =IF($M165="","",IF(INDEX(tblEvents[Old Value],$M165)="","",INDEX(tblEvents[Old Value],$M165))) | E165: =IF($M165="","",IF(INDEX(tblEvents[New Value],$M165)="","",INDEX(tblEvents[New Value],$M165))) | F165: =IF($M165="","",IF(INDEX(tblEvents[Notes],$M165)="","",INDEX(tblEvents[Notes],$M165))) | M165: =IF(M164="","",IFERROR(M164+MATCH(CH_CustomerID,INDEX(tblEvents[Customer ID],M164+1):INDEX(tblEvents[Customer ID],ROWS(tblEvents[Customer ID])),0),""))
B166: =IF($M166="","",IF(INDEX(tblEvents[Event Date],$M166)="","",INDEX(tblEvents[Event Date],$M166))) | C166: =IF($M166="","",IF(INDEX(tblEvents[Event Type],$M166)="","",INDEX(tblEvents[Event Type],$M166))) | D166: =IF($M166="","",IF(INDEX(tblEvents[Old Value],$M166)="","",INDEX(tblEvents[Old Value],$M166))) | E166: =IF($M166="","",IF(INDEX(tblEvents[New Value],$M166)="","",INDEX(tblEvents[New Value],$M166))) | F166: =IF($M166="","",IF(INDEX(tblEvents[Notes],$M166)="","",INDEX(tblEvents[Notes],$M166))) | M166: =IF(M165="","",IFERROR(M165+MATCH(CH_CustomerID,INDEX(tblEvents[Customer ID],M165+1):INDEX(tblEvents[Customer ID],ROWS(tblEvents[Customer ID])),0),""))
B167: =IF($M167="","",IF(INDEX(tblEvents[Event Date],$M167)="","",INDEX(tblEvents[Event Date],$M167))) | C167: =IF($M167="","",IF(INDEX(tblEvents[Event Type],$M167)="","",INDEX(tblEvents[Event Type],$M167))) | D167: =IF($M167="","",IF(INDEX(tblEvents[Old Value],$M167)="","",INDEX(tblEvents[Old Value],$M167))) | E167: =IF($M167="","",IF(INDEX(tblEvents[New Value],$M167)="","",INDEX(tblEvents[New Value],$M167))) | F167: =IF($M167="","",IF(INDEX(tblEvents[Notes],$M167)="","",INDEX(tblEvents[Notes],$M167))) | M167: =IF(M166="","",IFERROR(M166+MATCH(CH_CustomerID,INDEX(tblEvents[Customer ID],M166+1):INDEX(tblEvents[Customer ID],ROWS(tblEvents[Customer ID])),0),""))
B168: =IF($M168="","",IF(INDEX(tblEvents[Event Date],$M168)="","",INDEX(tblEvents[Event Date],$M168))) | C168: =IF($M168="","",IF(INDEX(tblEvents[Event Type],$M168)="","",INDEX(tblEvents[Event Type],$M168))) | D168: =IF($M168="","",IF(INDEX(tblEvents[Old Value],$M168)="","",INDEX(tblEvents[Old Value],$M168))) | E168: =IF($M168="","",IF(INDEX(tblEvents[New Value],$M168)="","",INDEX(tblEvents[New Value],$M168))) | F168: =IF($M168="","",IF(INDEX(tblEvents[Notes],$M168)="","",INDEX(tblEvents[Notes],$M168))) | M168: =IF(M167="","",IFERROR(M167+MATCH(CH_CustomerID,INDEX(tblEvents[Customer ID],M167+1):INDEX(tblEvents[Customer ID],ROWS(tblEvents[Customer ID])),0),""))
B169: =IF($M169="","",IF(INDEX(tblEvents[Event Date],$M169)="","",INDEX(tblEvents[Event Date],$M169))) | C169: =IF($M169="","",IF(INDEX(tblEvents[Event Type],$M169)="","",INDEX(tblEvents[Event Type],$M169))) | D169: =IF($M169="","",IF(INDEX(tblEvents[Old Value],$M169)="","",INDEX(tblEvents[Old Value],$M169))) | E169: =IF($M169="","",IF(INDEX(tblEvents[New Value],$M169)="","",INDEX(tblEvents[New Value],$M169))) | F169: =IF($M169="","",IF(INDEX(tblEvents[Notes],$M169)="","",INDEX(tblEvents[Notes],$M169))) | M169: =IF(M168="","",IFERROR(M168+MATCH(CH_CustomerID,INDEX(tblEvents[Customer ID],M168+1):INDEX(tblEvents[Customer ID],ROWS(tblEvents[Customer ID])),0),""))
B170: =IF($M170="","",IF(INDEX(tblEvents[Event Date],$M170)="","",INDEX(tblEvents[Event Date],$M170))) | C170: =IF($M170="","",IF(INDEX(tblEvents[Event Type],$M170)="","",INDEX(tblEvents[Event Type],$M170))) | D170: =IF($M170="","",IF(INDEX(tblEvents[Old Value],$M170)="","",INDEX(tblEvents[Old Value],$M170))) | E170: =IF($M170="","",IF(INDEX(tblEvents[New Value],$M170)="","",INDEX(tblEvents[New Value],$M170))) | F170: =IF($M170="","",IF(INDEX(tblEvents[Notes],$M170)="","",INDEX(tblEvents[Notes],$M170))) | M170: =IF(M169="","",IFERROR(M169+MATCH(CH_CustomerID,INDEX(tblEvents[Customer ID],M169+1):INDEX(tblEvents[Customer ID],ROWS(tblEvents[Customer ID])),0),""))
B171: =IF($M171="","",IF(INDEX(tblEvents[Event Date],$M171)="","",INDEX(tblEvents[Event Date],$M171))) | C171: =IF($M171="","",IF(INDEX(tblEvents[Event Type],$M171)="","",INDEX(tblEvents[Event Type],$M171))) | D171: =IF($M171="","",IF(INDEX(tblEvents[Old Value],$M171)="","",INDEX(tblEvents[Old Value],$M171))) | E171: =IF($M171="","",IF(INDEX(tblEvents[New Value],$M171)="","",INDEX(tblEvents[New Value],$M171))) | F171: =IF($M171="","",IF(INDEX(tblEvents[Notes],$M171)="","",INDEX(tblEvents[Notes],$M171))) | M171: =IF(M170="","",IFERROR(M170+MATCH(CH_CustomerID,INDEX(tblEvents[Customer ID],M170+1):INDEX(tblEvents[Customer ID],ROWS(tblEvents[Customer ID])),0),""))
B172: =IF($M172="","",IF(INDEX(tblEvents[Event Date],$M172)="","",INDEX(tblEvents[Event Date],$M172))) | C172: =IF($M172="","",IF(INDEX(tblEvents[Event Type],$M172)="","",INDEX(tblEvents[Event Type],$M172))) | D172: =IF($M172="","",IF(INDEX(tblEvents[Old Value],$M172)="","",INDEX(tblEvents[Old Value],$M172))) | E172: =IF($M172="","",IF(INDEX(tblEvents[New Value],$M172)="","",INDEX(tblEvents[New Value],$M172))) | F172: =IF($M172="","",IF(INDEX(tblEvents[Notes],$M172)="","",INDEX(tblEvents[Notes],$M172))) | M172: =IF(M171="","",IFERROR(M171+MATCH(CH_CustomerID,INDEX(tblEvents[Customer ID],M171+1):INDEX(tblEvents[Customer ID],ROWS(tblEvents[Customer ID])),0),""))
B173: =IF($M173="","",IF(INDEX(tblEvents[Event Date],$M173)="","",INDEX(tblEvents[Event Date],$M173))) | C173: =IF($M173="","",IF(INDEX(tblEvents[Event Type],$M173)="","",INDEX(tblEvents[Event Type],$M173))) | D173: =IF($M173="","",IF(INDEX(tblEvents[Old Value],$M173)="","",INDEX(tblEvents[Old Value],$M173))) | E173: =IF($M173="","",IF(INDEX(tblEvents[New Value],$M173)="","",INDEX(tblEvents[New Value],$M173))) | F173: =IF($M173="","",IF(INDEX(tblEvents[Notes],$M173)="","",INDEX(tblEvents[Notes],$M173))) | M173: =IF(M172="","",IFERROR(M172+MATCH(CH_CustomerID,INDEX(tblEvents[Customer ID],M172+1):INDEX(tblEvents[Customer ID],ROWS(tblEvents[Customer ID])),0),""))
B174: =IF($M174="","",IF(INDEX(tblEvents[Event Date],$M174)="","",INDEX(tblEvents[Event Date],$M174))) | C174: =IF($M174="","",IF(INDEX(tblEvents[Event Type],$M174)="","",INDEX(tblEvents[Event Type],$M174))) | D174: =IF($M174="","",IF(INDEX(tblEvents[Old Value],$M174)="","",INDEX(tblEvents[Old Value],$M174))) | E174: =IF($M174="","",IF(INDEX(tblEvents[New Value],$M174)="","",INDEX(tblEvents[New Value],$M174))) | F174: =IF($M174="","",IF(INDEX(tblEvents[Notes],$M174)="","",INDEX(tblEvents[Notes],$M174))) | M174: =IF(M173="","",IFERROR(M173+MATCH(CH_CustomerID,INDEX(tblEvents[Customer ID],M173+1):INDEX(tblEvents[Customer ID],ROWS(tblEvents[Customer ID])),0),""))
... B201: =IF($M201="","",IF(INDEX(tblEvents[Event Date],$M201)="","",INDEX(tblEvents[Event Date],$M201))) | C201: =IF($M201="","",IF(INDEX(tblEvents[Event Type],$M201)="","",INDEX(tblEvents[Event Type],$M201))) | D201: =IF($M201="","",IF(INDEX(tblEvents[Old Value],$M201)="","",INDEX(tblEvents[Old Value],$M201))) | E201: =IF($M201="","",IF(INDEX(tblEvents[New Value],$M201)="","",INDEX(tblEvents[New Value],$M201))) | F201: =IF($M201="","",IF(INDEX(tblEvents[Notes],$M201)="","",INDEX(tblEvents[Notes],$M201))) | M201: =IF(M200="","",IFERROR(M200+MATCH(CH_CustomerID,INDEX(tblEvents[Customer ID],M200+1):INDEX(tblEvents[Customer ID],ROWS(tblEvents[Customer ID])),0),""))

Sheet STATEMENT
A1: =CFG_CompanyName | J1: SELECT -> | Z1: =MAX(COUNTIF(tblBilling[Stmt Match],1),1)+14+6
A2: =CFG_Tagline&IF(CFG_CompanyPhone="",""," | "&CFG_CompanyPhone) | J2: Customer ID
A3: CUSTOMER PAYMENT STATEMENT | J3: From Month | K3: All
J4: To Month | K4: All
A5: Customer ID | C5: =ST_CustomerID | F5: Period: | G5: =IF(AND(ST_From="All",ST_To="All"),"Complete History",IF(ST_From="All","Up to ","")&ST_From&IF(AND(ST_From<>"All",ST_To<>"All")," to ","")&IF(ST_To="All"," onwards",ST_To)) | J5: All = complete history. Use the menu program for the PDF file (Export PDF).
A6: Customer Name | C6: =IF(ST_CustomerID="","",IFERROR(INDEX(tblCustomers[Customer Name],MATCH(ST_CustomerID,tblCustomers[Customer ID],0)),"Customer "&ST_CustomerID&" was not found.")) | F6: Generated: | G6: =TODAY() | J6: ◄ HOME
A7: Address | C7: =IF(ST_CustomerID="","",IFERROR(INDEX(tblCustomers[Full Address],MATCH(ST_CustomerID,tblCustomers[Customer ID],0)),"Customer "&ST_CustomerID&" was not found."))
A8: VLAN ID | C8: =IF(ST_CustomerID="","",IFERROR(INDEX(tblCustomers[VLAN ID],MATCH(ST_CustomerID,tblCustomers[Customer ID],0)),"Customer "&ST_CustomerID&" was not found."))
A9: Package | C9: =IF(ST_CustomerID="","",IFERROR(INDEX(tblCustomers[Package],MATCH(ST_CustomerID,tblCustomers[Customer ID],0)),"Customer "&ST_CustomerID&" was not found."))
A10: Monthly Fee | C10: =IF(ST_CustomerID="","",IFERROR(INDEX(tblCustomers[Monthly Fee],MATCH(ST_CustomerID,tblCustomers[Customer ID],0)),"Customer "&ST_CustomerID&" was not found."))
A11: Connection Date | C11: =IF(ST_CustomerID="","",IFERROR(INDEX(tblCustomers[Connection Date],MATCH(ST_CustomerID,tblCustomers[Customer ID],0)),"Customer "&ST_CustomerID&" was not found."))
A12: Current Status | C12: =IF(ST_CustomerID="","",IFERROR(INDEX(tblCustomers[Customer Status],MATCH(ST_CustomerID,tblCustomers[Customer ID],0)),"Customer "&ST_CustomerID&" was not found."))
A14: Month | B14: Bill | C14: Paid | D14: Payment Date | E14: Balance | F14: Status | G14: Payments | H14: Remarks
A15: =IF($Z15<>"",IF(INDEX(tblBilling[Month Name],$Z15)="","",INDEX(tblBilling[Month Name],$Z15)),CHOOSE(MIN(MAX($AA15,0),5)+1,"","TOTAL","","Total Billing: "&CFG_CurrencySymbol&" "&TEXT(SUMIFS(tblBilling[Monthly Fee],tblBilling[Stmt Match],1),"#,##0"),"Total Paid: "&CFG_CurrencySymbol&" "&TEXT(SUMIFS(tblBilling[Amount Paid],tblBilling[Stmt Match],1),"#,##0"),"Total Outstanding: "&CFG_CurrencySymbol&" "&TEXT(SUMIFS(tblBilling[Balance],tblBilling[Stmt Match],1),"#,##0"))) | B15: =IF($Z15<>"",IF(INDEX(tblBilling[Monthly Fee],$Z15)="","",INDEX(tblBilling[Monthly Fee],$Z15)),IF($AA15=1,SUMIFS(tblBilling[Monthly Fee],tblBilling[Stmt Match],1),"")) | C15: =IF($Z15<>"",IF(INDEX(tblBilling[Amount Paid],$Z15)="","",INDEX(tblBilling[Amount Paid],$Z15)),IF($AA15=1,SUMIFS(tblBilling[Amount Paid],tblBilling[Stmt Match],1),"")) | D15: =IF($Z15<>"",IF(INDEX(tblBilling[Last Payment Date],$Z15)="","",INDEX(tblBilling[Last Payment Date],$Z15)),"") | E15: =IF($Z15<>"",IF(INDEX(tblBilling[Balance],$Z15)="","",INDEX(tblBilling[Balance],$Z15)),IF($AA15=1,SUMIFS(tblBilling[Balance],tblBilling[Stmt Match],1),"")) | F15: =IF($Z15<>"",IF(INDEX(tblBilling[Payment Status],$Z15)="","",INDEX(tblBilling[Payment Status],$Z15)),"") | G15: =IF($Z15<>"",IF(INDEX(tblBilling[Payments Count],$Z15)="","",INDEX(tblBilling[Payments Count],$Z15)),"") | H15: =IF($Z15<>"",IF(INDEX(tblBilling[Remarks],$Z15)="","",INDEX(tblBilling[Remarks],$Z15)),"") | Z15: =IFERROR(MATCH(1,tblBilling[Stmt Match],0),"") | AA15: =ROW()-14-COUNTIF(tblBilling[Stmt Match],1)
A16: =IF($Z16<>"",IF(INDEX(tblBilling[Month Name],$Z16)="","",INDEX(tblBilling[Month Name],$Z16)),CHOOSE(MIN(MAX($AA16,0),5)+1,"","TOTAL","","Total Billing: "&CFG_CurrencySymbol&" "&TEXT(SUMIFS(tblBilling[Monthly Fee],tblBilling[Stmt Match],1),"#,##0"),"Total Paid: "&CFG_CurrencySymbol&" "&TEXT(SUMIFS(tblBilling[Amount Paid],tblBilling[Stmt Match],1),"#,##0"),"Total Outstanding: "&CFG_CurrencySymbol&" "&TEXT(SUMIFS(tblBilling[Balance],tblBilling[Stmt Match],1),"#,##0"))) | B16: =IF($Z16<>"",IF(INDEX(tblBilling[Monthly Fee],$Z16)="","",INDEX(tblBilling[Monthly Fee],$Z16)),IF($AA16=1,SUMIFS(tblBilling[Monthly Fee],tblBilling[Stmt Match],1),"")) | C16: =IF($Z16<>"",IF(INDEX(tblBilling[Amount Paid],$Z16)="","",INDEX(tblBilling[Amount Paid],$Z16)),IF($AA16=1,SUMIFS(tblBilling[Amount Paid],tblBilling[Stmt Match],1),"")) | D16: =IF($Z16<>"",IF(INDEX(tblBilling[Last Payment Date],$Z16)="","",INDEX(tblBilling[Last Payment Date],$Z16)),"") | E16: =IF($Z16<>"",IF(INDEX(tblBilling[Balance],$Z16)="","",INDEX(tblBilling[Balance],$Z16)),IF($AA16=1,SUMIFS(tblBilling[Balance],tblBilling[Stmt Match],1),"")) | F16: =IF($Z16<>"",IF(INDEX(tblBilling[Payment Status],$Z16)="","",INDEX(tblBilling[Payment Status],$Z16)),"") | G16: =IF($Z16<>"",IF(INDEX(tblBilling[Payments Count],$Z16)="","",INDEX(tblBilling[Payments Count],$Z16)),"") | H16: =IF($Z16<>"",IF(INDEX(tblBilling[Remarks],$Z16)="","",INDEX(tblBilling[Remarks],$Z16)),"") | Z16: =IF(Z15="","",IFERROR(Z15+MATCH(1,INDEX(tblBilling[Stmt Match],Z15+1):INDEX(tblBilling[Stmt Match],ROWS(tblBilling[Stmt Match])),0),"")) | AA16: =ROW()-14-COUNTIF(tblBilling[Stmt Match],1)
A17: =IF($Z17<>"",IF(INDEX(tblBilling[Month Name],$Z17)="","",INDEX(tblBilling[Month Name],$Z17)),CHOOSE(MIN(MAX($AA17,0),5)+1,"","TOTAL","","Total Billing: "&CFG_CurrencySymbol&" "&TEXT(SUMIFS(tblBilling[Monthly Fee],tblBilling[Stmt Match],1),"#,##0"),"Total Paid: "&CFG_CurrencySymbol&" "&TEXT(SUMIFS(tblBilling[Amount Paid],tblBilling[Stmt Match],1),"#,##0"),"Total Outstanding: "&CFG_CurrencySymbol&" "&TEXT(SUMIFS(tblBilling[Balance],tblBilling[Stmt Match],1),"#,##0"))) | B17: =IF($Z17<>"",IF(INDEX(tblBilling[Monthly Fee],$Z17)="","",INDEX(tblBilling[Monthly Fee],$Z17)),IF($AA17=1,SUMIFS(tblBilling[Monthly Fee],tblBilling[Stmt Match],1),"")) | C17: =IF($Z17<>"",IF(INDEX(tblBilling[Amount Paid],$Z17)="","",INDEX(tblBilling[Amount Paid],$Z17)),IF($AA17=1,SUMIFS(tblBilling[Amount Paid],tblBilling[Stmt Match],1),"")) | D17: =IF($Z17<>"",IF(INDEX(tblBilling[Last Payment Date],$Z17)="","",INDEX(tblBilling[Last Payment Date],$Z17)),"") | E17: =IF($Z17<>"",IF(INDEX(tblBilling[Balance],$Z17)="","",INDEX(tblBilling[Balance],$Z17)),IF($AA17=1,SUMIFS(tblBilling[Balance],tblBilling[Stmt Match],1),"")) | F17: =IF($Z17<>"",IF(INDEX(tblBilling[Payment Status],$Z17)="","",INDEX(tblBilling[Payment Status],$Z17)),"") | G17: =IF($Z17<>"",IF(INDEX(tblBilling[Payments Count],$Z17)="","",INDEX(tblBilling[Payments Count],$Z17)),"") | H17: =IF($Z17<>"",IF(INDEX(tblBilling[Remarks],$Z17)="","",INDEX(tblBilling[Remarks],$Z17)),"") | Z17: =IF(Z16="","",IFERROR(Z16+MATCH(1,INDEX(tblBilling[Stmt Match],Z16+1):INDEX(tblBilling[Stmt Match],ROWS(tblBilling[Stmt Match])),0),"")) | AA17: =ROW()-14-COUNTIF(tblBilling[Stmt Match],1)
A18: =IF($Z18<>"",IF(INDEX(tblBilling[Month Name],$Z18)="","",INDEX(tblBilling[Month Name],$Z18)),CHOOSE(MIN(MAX($AA18,0),5)+1,"","TOTAL","","Total Billing: "&CFG_CurrencySymbol&" "&TEXT(SUMIFS(tblBilling[Monthly Fee],tblBilling[Stmt Match],1),"#,##0"),"Total Paid: "&CFG_CurrencySymbol&" "&TEXT(SUMIFS(tblBilling[Amount Paid],tblBilling[Stmt Match],1),"#,##0"),"Total Outstanding: "&CFG_CurrencySymbol&" "&TEXT(SUMIFS(tblBilling[Balance],tblBilling[Stmt Match],1),"#,##0"))) | B18: =IF($Z18<>"",IF(INDEX(tblBilling[Monthly Fee],$Z18)="","",INDEX(tblBilling[Monthly Fee],$Z18)),IF($AA18=1,SUMIFS(tblBilling[Monthly Fee],tblBilling[Stmt Match],1),"")) | C18: =IF($Z18<>"",IF(INDEX(tblBilling[Amount Paid],$Z18)="","",INDEX(tblBilling[Amount Paid],$Z18)),IF($AA18=1,SUMIFS(tblBilling[Amount Paid],tblBilling[Stmt Match],1),"")) | D18: =IF($Z18<>"",IF(INDEX(tblBilling[Last Payment Date],$Z18)="","",INDEX(tblBilling[Last Payment Date],$Z18)),"") | E18: =IF($Z18<>"",IF(INDEX(tblBilling[Balance],$Z18)="","",INDEX(tblBilling[Balance],$Z18)),IF($AA18=1,SUMIFS(tblBilling[Balance],tblBilling[Stmt Match],1),"")) | F18: =IF($Z18<>"",IF(INDEX(tblBilling[Payment Status],$Z18)="","",INDEX(tblBilling[Payment Status],$Z18)),"") | G18: =IF($Z18<>"",IF(INDEX(tblBilling[Payments Count],$Z18)="","",INDEX(tblBilling[Payments Count],$Z18)),"") | H18: =IF($Z18<>"",IF(INDEX(tblBilling[Remarks],$Z18)="","",INDEX(tblBilling[Remarks],$Z18)),"") | Z18: =IF(Z17="","",IFERROR(Z17+MATCH(1,INDEX(tblBilling[Stmt Match],Z17+1):INDEX(tblBilling[Stmt Match],ROWS(tblBilling[Stmt Match])),0),"")) | AA18: =ROW()-14-COUNTIF(tblBilling[Stmt Match],1)
A19: =IF($Z19<>"",IF(INDEX(tblBilling[Month Name],$Z19)="","",INDEX(tblBilling[Month Name],$Z19)),CHOOSE(MIN(MAX($AA19,0),5)+1,"","TOTAL","","Total Billing: "&CFG_CurrencySymbol&" "&TEXT(SUMIFS(tblBilling[Monthly Fee],tblBilling[Stmt Match],1),"#,##0"),"Total Paid: "&CFG_CurrencySymbol&" "&TEXT(SUMIFS(tblBilling[Amount Paid],tblBilling[Stmt Match],1),"#,##0"),"Total Outstanding: "&CFG_CurrencySymbol&" "&TEXT(SUMIFS(tblBilling[Balance],tblBilling[Stmt Match],1),"#,##0"))) | B19: =IF($Z19<>"",IF(INDEX(tblBilling[Monthly Fee],$Z19)="","",INDEX(tblBilling[Monthly Fee],$Z19)),IF($AA19=1,SUMIFS(tblBilling[Monthly Fee],tblBilling[Stmt Match],1),"")) | C19: =IF($Z19<>"",IF(INDEX(tblBilling[Amount Paid],$Z19)="","",INDEX(tblBilling[Amount Paid],$Z19)),IF($AA19=1,SUMIFS(tblBilling[Amount Paid],tblBilling[Stmt Match],1),"")) | D19: =IF($Z19<>"",IF(INDEX(tblBilling[Last Payment Date],$Z19)="","",INDEX(tblBilling[Last Payment Date],$Z19)),"") | E19: =IF($Z19<>"",IF(INDEX(tblBilling[Balance],$Z19)="","",INDEX(tblBilling[Balance],$Z19)),IF($AA19=1,SUMIFS(tblBilling[Balance],tblBilling[Stmt Match],1),"")) | F19: =IF($Z19<>"",IF(INDEX(tblBilling[Payment Status],$Z19)="","",INDEX(tblBilling[Payment Status],$Z19)),"") | G19: =IF($Z19<>"",IF(INDEX(tblBilling[Payments Count],$Z19)="","",INDEX(tblBilling[Payments Count],$Z19)),"") | H19: =IF($Z19<>"",IF(INDEX(tblBilling[Remarks],$Z19)="","",INDEX(tblBilling[Remarks],$Z19)),"") | Z19: =IF(Z18="","",IFERROR(Z18+MATCH(1,INDEX(tblBilling[Stmt Match],Z18+1):INDEX(tblBilling[Stmt Match],ROWS(tblBilling[Stmt Match])),0),"")) | AA19: =ROW()-14-COUNTIF(tblBilling[Stmt Match],1)
A20: =IF($Z20<>"",IF(INDEX(tblBilling[Month Name],$Z20)="","",INDEX(tblBilling[Month Name],$Z20)),CHOOSE(MIN(MAX($AA20,0),5)+1,"","TOTAL","","Total Billing: "&CFG_CurrencySymbol&" "&TEXT(SUMIFS(tblBilling[Monthly Fee],tblBilling[Stmt Match],1),"#,##0"),"Total Paid: "&CFG_CurrencySymbol&" "&TEXT(SUMIFS(tblBilling[Amount Paid],tblBilling[Stmt Match],1),"#,##0"),"Total Outstanding: "&CFG_CurrencySymbol&" "&TEXT(SUMIFS(tblBilling[Balance],tblBilling[Stmt Match],1),"#,##0"))) | B20: =IF($Z20<>"",IF(INDEX(tblBilling[Monthly Fee],$Z20)="","",INDEX(tblBilling[Monthly Fee],$Z20)),IF($AA20=1,SUMIFS(tblBilling[Monthly Fee],tblBilling[Stmt Match],1),"")) | C20: =IF($Z20<>"",IF(INDEX(tblBilling[Amount Paid],$Z20)="","",INDEX(tblBilling[Amount Paid],$Z20)),IF($AA20=1,SUMIFS(tblBilling[Amount Paid],tblBilling[Stmt Match],1),"")) | D20: =IF($Z20<>"",IF(INDEX(tblBilling[Last Payment Date],$Z20)="","",INDEX(tblBilling[Last Payment Date],$Z20)),"") | E20: =IF($Z20<>"",IF(INDEX(tblBilling[Balance],$Z20)="","",INDEX(tblBilling[Balance],$Z20)),IF($AA20=1,SUMIFS(tblBilling[Balance],tblBilling[Stmt Match],1),"")) | F20: =IF($Z20<>"",IF(INDEX(tblBilling[Payment Status],$Z20)="","",INDEX(tblBilling[Payment Status],$Z20)),"") | G20: =IF($Z20<>"",IF(INDEX(tblBilling[Payments Count],$Z20)="","",INDEX(tblBilling[Payments Count],$Z20)),"") | H20: =IF($Z20<>"",IF(INDEX(tblBilling[Remarks],$Z20)="","",INDEX(tblBilling[Remarks],$Z20)),"") | Z20: =IF(Z19="","",IFERROR(Z19+MATCH(1,INDEX(tblBilling[Stmt Match],Z19+1):INDEX(tblBilling[Stmt Match],ROWS(tblBilling[Stmt Match])),0),"")) | AA20: =ROW()-14-COUNTIF(tblBilling[Stmt Match],1)
A21: =IF($Z21<>"",IF(INDEX(tblBilling[Month Name],$Z21)="","",INDEX(tblBilling[Month Name],$Z21)),CHOOSE(MIN(MAX($AA21,0),5)+1,"","TOTAL","","Total Billing: "&CFG_CurrencySymbol&" "&TEXT(SUMIFS(tblBilling[Monthly Fee],tblBilling[Stmt Match],1),"#,##0"),"Total Paid: "&CFG_CurrencySymbol&" "&TEXT(SUMIFS(tblBilling[Amount Paid],tblBilling[Stmt Match],1),"#,##0"),"Total Outstanding: "&CFG_CurrencySymbol&" "&TEXT(SUMIFS(tblBilling[Balance],tblBilling[Stmt Match],1),"#,##0"))) | B21: =IF($Z21<>"",IF(INDEX(tblBilling[Monthly Fee],$Z21)="","",INDEX(tblBilling[Monthly Fee],$Z21)),IF($AA21=1,SUMIFS(tblBilling[Monthly Fee],tblBilling[Stmt Match],1),"")) | C21: =IF($Z21<>"",IF(INDEX(tblBilling[Amount Paid],$Z21)="","",INDEX(tblBilling[Amount Paid],$Z21)),IF($AA21=1,SUMIFS(tblBilling[Amount Paid],tblBilling[Stmt Match],1),"")) | D21: =IF($Z21<>"",IF(INDEX(tblBilling[Last Payment Date],$Z21)="","",INDEX(tblBilling[Last Payment Date],$Z21)),"") | E21: =IF($Z21<>"",IF(INDEX(tblBilling[Balance],$Z21)="","",INDEX(tblBilling[Balance],$Z21)),IF($AA21=1,SUMIFS(tblBilling[Balance],tblBilling[Stmt Match],1),"")) | F21: =IF($Z21<>"",IF(INDEX(tblBilling[Payment Status],$Z21)="","",INDEX(tblBilling[Payment Status],$Z21)),"") | G21: =IF($Z21<>"",IF(INDEX(tblBilling[Payments Count],$Z21)="","",INDEX(tblBilling[Payments Count],$Z21)),"") | H21: =IF($Z21<>"",IF(INDEX(tblBilling[Remarks],$Z21)="","",INDEX(tblBilling[Remarks],$Z21)),"") | Z21: =IF(Z20="","",IFERROR(Z20+MATCH(1,INDEX(tblBilling[Stmt Match],Z20+1):INDEX(tblBilling[Stmt Match],ROWS(tblBilling[Stmt Match])),0),"")) | AA21: =ROW()-14-COUNTIF(tblBilling[Stmt Match],1)
A22: =IF($Z22<>"",IF(INDEX(tblBilling[Month Name],$Z22)="","",INDEX(tblBilling[Month Name],$Z22)),CHOOSE(MIN(MAX($AA22,0),5)+1,"","TOTAL","","Total Billing: "&CFG_CurrencySymbol&" "&TEXT(SUMIFS(tblBilling[Monthly Fee],tblBilling[Stmt Match],1),"#,##0"),"Total Paid: "&CFG_CurrencySymbol&" "&TEXT(SUMIFS(tblBilling[Amount Paid],tblBilling[Stmt Match],1),"#,##0"),"Total Outstanding: "&CFG_CurrencySymbol&" "&TEXT(SUMIFS(tblBilling[Balance],tblBilling[Stmt Match],1),"#,##0"))) | B22: =IF($Z22<>"",IF(INDEX(tblBilling[Monthly Fee],$Z22)="","",INDEX(tblBilling[Monthly Fee],$Z22)),IF($AA22=1,SUMIFS(tblBilling[Monthly Fee],tblBilling[Stmt Match],1),"")) | C22: =IF($Z22<>"",IF(INDEX(tblBilling[Amount Paid],$Z22)="","",INDEX(tblBilling[Amount Paid],$Z22)),IF($AA22=1,SUMIFS(tblBilling[Amount Paid],tblBilling[Stmt Match],1),"")) | D22: =IF($Z22<>"",IF(INDEX(tblBilling[Last Payment Date],$Z22)="","",INDEX(tblBilling[Last Payment Date],$Z22)),"") | E22: =IF($Z22<>"",IF(INDEX(tblBilling[Balance],$Z22)="","",INDEX(tblBilling[Balance],$Z22)),IF($AA22=1,SUMIFS(tblBilling[Balance],tblBilling[Stmt Match],1),"")) | F22: =IF($Z22<>"",IF(INDEX(tblBilling[Payment Status],$Z22)="","",INDEX(tblBilling[Payment Status],$Z22)),"") | G22: =IF($Z22<>"",IF(INDEX(tblBilling[Payments Count],$Z22)="","",INDEX(tblBilling[Payments Count],$Z22)),"") | H22: =IF($Z22<>"",IF(INDEX(tblBilling[Remarks],$Z22)="","",INDEX(tblBilling[Remarks],$Z22)),"") | Z22: =IF(Z21="","",IFERROR(Z21+MATCH(1,INDEX(tblBilling[Stmt Match],Z21+1):INDEX(tblBilling[Stmt Match],ROWS(tblBilling[Stmt Match])),0),"")) | AA22: =ROW()-14-COUNTIF(tblBilling[Stmt Match],1)
A23: =IF($Z23<>"",IF(INDEX(tblBilling[Month Name],$Z23)="","",INDEX(tblBilling[Month Name],$Z23)),CHOOSE(MIN(MAX($AA23,0),5)+1,"","TOTAL","","Total Billing: "&CFG_CurrencySymbol&" "&TEXT(SUMIFS(tblBilling[Monthly Fee],tblBilling[Stmt Match],1),"#,##0"),"Total Paid: "&CFG_CurrencySymbol&" "&TEXT(SUMIFS(tblBilling[Amount Paid],tblBilling[Stmt Match],1),"#,##0"),"Total Outstanding: "&CFG_CurrencySymbol&" "&TEXT(SUMIFS(tblBilling[Balance],tblBilling[Stmt Match],1),"#,##0"))) | B23: =IF($Z23<>"",IF(INDEX(tblBilling[Monthly Fee],$Z23)="","",INDEX(tblBilling[Monthly Fee],$Z23)),IF($AA23=1,SUMIFS(tblBilling[Monthly Fee],tblBilling[Stmt Match],1),"")) | C23: =IF($Z23<>"",IF(INDEX(tblBilling[Amount Paid],$Z23)="","",INDEX(tblBilling[Amount Paid],$Z23)),IF($AA23=1,SUMIFS(tblBilling[Amount Paid],tblBilling[Stmt Match],1),"")) | D23: =IF($Z23<>"",IF(INDEX(tblBilling[Last Payment Date],$Z23)="","",INDEX(tblBilling[Last Payment Date],$Z23)),"") | E23: =IF($Z23<>"",IF(INDEX(tblBilling[Balance],$Z23)="","",INDEX(tblBilling[Balance],$Z23)),IF($AA23=1,SUMIFS(tblBilling[Balance],tblBilling[Stmt Match],1),"")) | F23: =IF($Z23<>"",IF(INDEX(tblBilling[Payment Status],$Z23)="","",INDEX(tblBilling[Payment Status],$Z23)),"") | G23: =IF($Z23<>"",IF(INDEX(tblBilling[Payments Count],$Z23)="","",INDEX(tblBilling[Payments Count],$Z23)),"") | H23: =IF($Z23<>"",IF(INDEX(tblBilling[Remarks],$Z23)="","",INDEX(tblBilling[Remarks],$Z23)),"") | Z23: =IF(Z22="","",IFERROR(Z22+MATCH(1,INDEX(tblBilling[Stmt Match],Z22+1):INDEX(tblBilling[Stmt Match],ROWS(tblBilling[Stmt Match])),0),"")) | AA23: =ROW()-14-COUNTIF(tblBilling[Stmt Match],1)
A24: =IF($Z24<>"",IF(INDEX(tblBilling[Month Name],$Z24)="","",INDEX(tblBilling[Month Name],$Z24)),CHOOSE(MIN(MAX($AA24,0),5)+1,"","TOTAL","","Total Billing: "&CFG_CurrencySymbol&" "&TEXT(SUMIFS(tblBilling[Monthly Fee],tblBilling[Stmt Match],1),"#,##0"),"Total Paid: "&CFG_CurrencySymbol&" "&TEXT(SUMIFS(tblBilling[Amount Paid],tblBilling[Stmt Match],1),"#,##0"),"Total Outstanding: "&CFG_CurrencySymbol&" "&TEXT(SUMIFS(tblBilling[Balance],tblBilling[Stmt Match],1),"#,##0"))) | B24: =IF($Z24<>"",IF(INDEX(tblBilling[Monthly Fee],$Z24)="","",INDEX(tblBilling[Monthly Fee],$Z24)),IF($AA24=1,SUMIFS(tblBilling[Monthly Fee],tblBilling[Stmt Match],1),"")) | C24: =IF($Z24<>"",IF(INDEX(tblBilling[Amount Paid],$Z24)="","",INDEX(tblBilling[Amount Paid],$Z24)),IF($AA24=1,SUMIFS(tblBilling[Amount Paid],tblBilling[Stmt Match],1),"")) | D24: =IF($Z24<>"",IF(INDEX(tblBilling[Last Payment Date],$Z24)="","",INDEX(tblBilling[Last Payment Date],$Z24)),"") | E24: =IF($Z24<>"",IF(INDEX(tblBilling[Balance],$Z24)="","",INDEX(tblBilling[Balance],$Z24)),IF($AA24=1,SUMIFS(tblBilling[Balance],tblBilling[Stmt Match],1),"")) | F24: =IF($Z24<>"",IF(INDEX(tblBilling[Payment Status],$Z24)="","",INDEX(tblBilling[Payment Status],$Z24)),"") | G24: =IF($Z24<>"",IF(INDEX(tblBilling[Payments Count],$Z24)="","",INDEX(tblBilling[Payments Count],$Z24)),"") | H24: =IF($Z24<>"",IF(INDEX(tblBilling[Remarks],$Z24)="","",INDEX(tblBilling[Remarks],$Z24)),"") | Z24: =IF(Z23="","",IFERROR(Z23+MATCH(1,INDEX(tblBilling[Stmt Match],Z23+1):INDEX(tblBilling[Stmt Match],ROWS(tblBilling[Stmt Match])),0),"")) | AA24: =ROW()-14-COUNTIF(tblBilling[Stmt Match],1)
A25: =IF($Z25<>"",IF(INDEX(tblBilling[Month Name],$Z25)="","",INDEX(tblBilling[Month Name],$Z25)),CHOOSE(MIN(MAX($AA25,0),5)+1,"","TOTAL","","Total Billing: "&CFG_CurrencySymbol&" "&TEXT(SUMIFS(tblBilling[Monthly Fee],tblBilling[Stmt Match],1),"#,##0"),"Total Paid: "&CFG_CurrencySymbol&" "&TEXT(SUMIFS(tblBilling[Amount Paid],tblBilling[Stmt Match],1),"#,##0"),"Total Outstanding: "&CFG_CurrencySymbol&" "&TEXT(SUMIFS(tblBilling[Balance],tblBilling[Stmt Match],1),"#,##0"))) | B25: =IF($Z25<>"",IF(INDEX(tblBilling[Monthly Fee],$Z25)="","",INDEX(tblBilling[Monthly Fee],$Z25)),IF($AA25=1,SUMIFS(tblBilling[Monthly Fee],tblBilling[Stmt Match],1),"")) | C25: =IF($Z25<>"",IF(INDEX(tblBilling[Amount Paid],$Z25)="","",INDEX(tblBilling[Amount Paid],$Z25)),IF($AA25=1,SUMIFS(tblBilling[Amount Paid],tblBilling[Stmt Match],1),"")) | D25: =IF($Z25<>"",IF(INDEX(tblBilling[Last Payment Date],$Z25)="","",INDEX(tblBilling[Last Payment Date],$Z25)),"") | E25: =IF($Z25<>"",IF(INDEX(tblBilling[Balance],$Z25)="","",INDEX(tblBilling[Balance],$Z25)),IF($AA25=1,SUMIFS(tblBilling[Balance],tblBilling[Stmt Match],1),"")) | F25: =IF($Z25<>"",IF(INDEX(tblBilling[Payment Status],$Z25)="","",INDEX(tblBilling[Payment Status],$Z25)),"") | G25: =IF($Z25<>"",IF(INDEX(tblBilling[Payments Count],$Z25)="","",INDEX(tblBilling[Payments Count],$Z25)),"") | H25: =IF($Z25<>"",IF(INDEX(tblBilling[Remarks],$Z25)="","",INDEX(tblBilling[Remarks],$Z25)),"") | Z25: =IF(Z24="","",IFERROR(Z24+MATCH(1,INDEX(tblBilling[Stmt Match],Z24+1):INDEX(tblBilling[Stmt Match],ROWS(tblBilling[Stmt Match])),0),"")) | AA25: =ROW()-14-COUNTIF(tblBilling[Stmt Match],1)
A26: =IF($Z26<>"",IF(INDEX(tblBilling[Month Name],$Z26)="","",INDEX(tblBilling[Month Name],$Z26)),CHOOSE(MIN(MAX($AA26,0),5)+1,"","TOTAL","","Total Billing: "&CFG_CurrencySymbol&" "&TEXT(SUMIFS(tblBilling[Monthly Fee],tblBilling[Stmt Match],1),"#,##0"),"Total Paid: "&CFG_CurrencySymbol&" "&TEXT(SUMIFS(tblBilling[Amount Paid],tblBilling[Stmt Match],1),"#,##0"),"Total Outstanding: "&CFG_CurrencySymbol&" "&TEXT(SUMIFS(tblBilling[Balance],tblBilling[Stmt Match],1),"#,##0"))) | B26: =IF($Z26<>"",IF(INDEX(tblBilling[Monthly Fee],$Z26)="","",INDEX(tblBilling[Monthly Fee],$Z26)),IF($AA26=1,SUMIFS(tblBilling[Monthly Fee],tblBilling[Stmt Match],1),"")) | C26: =IF($Z26<>"",IF(INDEX(tblBilling[Amount Paid],$Z26)="","",INDEX(tblBilling[Amount Paid],$Z26)),IF($AA26=1,SUMIFS(tblBilling[Amount Paid],tblBilling[Stmt Match],1),"")) | D26: =IF($Z26<>"",IF(INDEX(tblBilling[Last Payment Date],$Z26)="","",INDEX(tblBilling[Last Payment Date],$Z26)),"") | E26: =IF($Z26<>"",IF(INDEX(tblBilling[Balance],$Z26)="","",INDEX(tblBilling[Balance],$Z26)),IF($AA26=1,SUMIFS(tblBilling[Balance],tblBilling[Stmt Match],1),"")) | F26: =IF($Z26<>"",IF(INDEX(tblBilling[Payment Status],$Z26)="","",INDEX(tblBilling[Payment Status],$Z26)),"") | G26: =IF($Z26<>"",IF(INDEX(tblBilling[Payments Count],$Z26)="","",INDEX(tblBilling[Payments Count],$Z26)),"") | H26: =IF($Z26<>"",IF(INDEX(tblBilling[Remarks],$Z26)="","",INDEX(tblBilling[Remarks],$Z26)),"") | Z26: =IF(Z25="","",IFERROR(Z25+MATCH(1,INDEX(tblBilling[Stmt Match],Z25+1):INDEX(tblBilling[Stmt Match],ROWS(tblBilling[Stmt Match])),0),"")) | AA26: =ROW()-14-COUNTIF(tblBilling[Stmt Match],1)
A27: =IF($Z27<>"",IF(INDEX(tblBilling[Month Name],$Z27)="","",INDEX(tblBilling[Month Name],$Z27)),CHOOSE(MIN(MAX($AA27,0),5)+1,"","TOTAL","","Total Billing: "&CFG_CurrencySymbol&" "&TEXT(SUMIFS(tblBilling[Monthly Fee],tblBilling[Stmt Match],1),"#,##0"),"Total Paid: "&CFG_CurrencySymbol&" "&TEXT(SUMIFS(tblBilling[Amount Paid],tblBilling[Stmt Match],1),"#,##0"),"Total Outstanding: "&CFG_CurrencySymbol&" "&TEXT(SUMIFS(tblBilling[Balance],tblBilling[Stmt Match],1),"#,##0"))) | B27: =IF($Z27<>"",IF(INDEX(tblBilling[Monthly Fee],$Z27)="","",INDEX(tblBilling[Monthly Fee],$Z27)),IF($AA27=1,SUMIFS(tblBilling[Monthly Fee],tblBilling[Stmt Match],1),"")) | C27: =IF($Z27<>"",IF(INDEX(tblBilling[Amount Paid],$Z27)="","",INDEX(tblBilling[Amount Paid],$Z27)),IF($AA27=1,SUMIFS(tblBilling[Amount Paid],tblBilling[Stmt Match],1),"")) | D27: =IF($Z27<>"",IF(INDEX(tblBilling[Last Payment Date],$Z27)="","",INDEX(tblBilling[Last Payment Date],$Z27)),"") | E27: =IF($Z27<>"",IF(INDEX(tblBilling[Balance],$Z27)="","",INDEX(tblBilling[Balance],$Z27)),IF($AA27=1,SUMIFS(tblBilling[Balance],tblBilling[Stmt Match],1),"")) | F27: =IF($Z27<>"",IF(INDEX(tblBilling[Payment Status],$Z27)="","",INDEX(tblBilling[Payment Status],$Z27)),"") | G27: =IF($Z27<>"",IF(INDEX(tblBilling[Payments Count],$Z27)="","",INDEX(tblBilling[Payments Count],$Z27)),"") | H27: =IF($Z27<>"",IF(INDEX(tblBilling[Remarks],$Z27)="","",INDEX(tblBilling[Remarks],$Z27)),"") | Z27: =IF(Z26="","",IFERROR(Z26+MATCH(1,INDEX(tblBilling[Stmt Match],Z26+1):INDEX(tblBilling[Stmt Match],ROWS(tblBilling[Stmt Match])),0),"")) | AA27: =ROW()-14-COUNTIF(tblBilling[Stmt Match],1)
... A86: =IF($Z86<>"",IF(INDEX(tblBilling[Month Name],$Z86)="","",INDEX(tblBilling[Month Name],$Z86)),CHOOSE(MIN(MAX($AA86,0),5)+1,"","TOTAL","","Total Billing: "&CFG_CurrencySymbol&" "&TEXT(SUMIFS(tblBilling[Monthly Fee],tblBilling[Stmt Match],1),"#,##0"),"Total Paid: "&CFG_CurrencySymbol&" "&TEXT(SUMIFS(tblBilling[Amount Paid],tblBilling[Stmt Match],1),"#,##0"),"Total Outstanding: "&CFG_CurrencySymbol&" "&TEXT(SUMIFS(tblBilling[Balance],tblBilling[Stmt Match],1),"#,##0"))) | B86: =IF($Z86<>"",IF(INDEX(tblBilling[Monthly Fee],$Z86)="","",INDEX(tblBilling[Monthly Fee],$Z86)),IF($AA86=1,SUMIFS(tblBilling[Monthly Fee],tblBilling[Stmt Match],1),"")) | C86: =IF($Z86<>"",IF(INDEX(tblBilling[Amount Paid],$Z86)="","",INDEX(tblBilling[Amount Paid],$Z86)),IF($AA86=1,SUMIFS(tblBilling[Amount Paid],tblBilling[Stmt Match],1),"")) | D86: =IF($Z86<>"",IF(INDEX(tblBilling[Last Payment Date],$Z86)="","",INDEX(tblBilling[Last Payment Date],$Z86)),"") | E86: =IF($Z86<>"",IF(INDEX(tblBilling[Balance],$Z86)="","",INDEX(tblBilling[Balance],$Z86)),IF($AA86=1,SUMIFS(tblBilling[Balance],tblBilling[Stmt Match],1),"")) | F86: =IF($Z86<>"",IF(INDEX(tblBilling[Payment Status],$Z86)="","",INDEX(tblBilling[Payment Status],$Z86)),"") | G86: =IF($Z86<>"",IF(INDEX(tblBilling[Payments Count],$Z86)="","",INDEX(tblBilling[Payments Count],$Z86)),"") | H86: =IF($Z86<>"",IF(INDEX(tblBilling[Remarks],$Z86)="","",INDEX(tblBilling[Remarks],$Z86)),"") | Z86: =IF(Z85="","",IFERROR(Z85+MATCH(1,INDEX(tblBilling[Stmt Match],Z85+1):INDEX(tblBilling[Stmt Match],ROWS(tblBilling[Stmt Match])),0),"")) | AA86: =ROW()-14-COUNTIF(tblBilling[Stmt Match],1)

Sheet CASH_RECONCILIATION
A1: CASH RECONCILIATION | L1: ◄ HOME
A2: Expected = cash payments recorded under the collector for that month. Enter the cash actually handed over in Actual Cash Submitted.
A3: Header colours: dark blue = you type | mid blue = system generated (do not edit) | grey = calculated formula (never type)
A4: Month | B4: Collector ID | C4: Collector Name | D4: Expected Collection | E4: Non Cash Collected | F4: Actual Cash Submitted | G4: Cash Difference | H4: Reconciliation Status | I4: Submission Date | J4: Received By | K4: Remarks
C5: =IFERROR(INDEX(tblCollectors[Collector Name],MATCH(tblCash[[#This Row],[Collector ID]],tblCollectors[Collector ID],0)),"") | D5: =SUMIFS(tblPayments[Amount],tblPayments[Collector ID],tblCash[[#This Row],[Collector ID]],tblPayments[Month],tblCash[[#This Row],[Month]],tblPayments[Payment Method],"Cash",tblPayments[Voided],"<>Yes") | E5: =SUMIFS(tblPayments[Amount],tblPayments[Collector ID],tblCash[[#This Row],[Collector ID]],tblPayments[Month],tblCash[[#This Row],[Month]],tblPayments[Voided],"<>Yes")-tblCash[[#This Row],[Expected Collection]] | G5: =IF(tblCash[[#This Row],[Actual Cash Submitted]]="","",tblCash[[#This Row],[Actual Cash Submitted]]-tblCash[[#This Row],[Expected Collection]]) | H5: =IF(tblCash[[#This Row],[Actual Cash Submitted]]="","NOT SUBMITTED",IF(tblCash[[#This Row],[Cash Difference]]=0,"MATCHED","CASH DIFFERENCE"))

Sheet RECOVERY_ASSIGNMENTS
A1: RECOVERY ASSIGNMENTS | L1: ◄ HOME
A2: Which recovery boy collects which customer in which month. Old assignments are marked Reassigned, never deleted.
A3: Header colours: dark blue = you type | mid blue = system generated (do not edit) | grey = calculated formula (never type)
A4: Assignment ID | B4: Month | C4: Customer ID | D4: Customer Name | E4: Location Code | F4: Collector ID | G4: Collector Name | H4: Assigned Date | I4: Assignment Status | J4: Remarks | K4: Key
D5: =IFERROR(INDEX(tblCustomers[Customer Name],MATCH(tblAssignments[[#This Row],[Customer ID]],tblCustomers[Customer ID],0)),"CUSTOMER NOT FOUND") | E5: =IFERROR(INDEX(tblCustomers[Location Code],MATCH(tblAssignments[[#This Row],[Customer ID]],tblCustomers[Customer ID],0)),"") | G5: =IFERROR(INDEX(tblCollectors[Collector Name],MATCH(tblAssignments[[#This Row],[Collector ID]],tblCollectors[Collector ID],0)),"COLLECTOR NOT FOUND") | K5: =IF(OR(tblAssignments[[#This Row],[Assignment Status]]="Reassigned",tblAssignments[[#This Row],[Assignment Status]]="Cancelled"),"",tblAssignments[[#This Row],[Month]]&"|"&tblAssignments[[#This Row],[Customer ID]])

Sheet REPORTS
A1: REPORTS | J1: ◄ HOME
A2: Monthly comparison and street-wise report. Full report packs (Excel) are exported by the menu program.
B4: MONTHLY COMPARISON
B5: Month A
B6: Month B | C6: =CFG_CurrentMonth
B8: Metric | C8: Month A | D8: Month B | E8: Change | F8: Change %
B9: Customers Billed | C9: =COUNTIF(tblBilling[Month],$C$5) | D9: =COUNTIF(tblBilling[Month],$C$6) | E9: =D9-C9 | F9: =IF(N(C9)=0,"",(D9-C9)/C9)
B10: Billing | C10: =SUMIFS(tblBilling[Monthly Fee],tblBilling[Month],$C$5) | D10: =SUMIFS(tblBilling[Monthly Fee],tblBilling[Month],$C$6) | E10: =D10-C10 | F10: =IF(N(C10)=0,"",(D10-C10)/C10)
B11: Recovered | C11: =SUMIFS(tblBilling[Amount Paid],tblBilling[Month],$C$5) | D11: =SUMIFS(tblBilling[Amount Paid],tblBilling[Month],$C$6) | E11: =D11-C11 | F11: =IF(N(C11)=0,"",(D11-C11)/C11)
B12: Pending (Balance) | C12: =SUMIFS(tblBilling[Balance],tblBilling[Month],$C$5) | D12: =SUMIFS(tblBilling[Balance],tblBilling[Month],$C$6) | E12: =D12-C12 | F12: =IF(N(C12)=0,"",(D12-C12)/C12)
B13: Paid Customers | C13: =COUNTIFS(tblBilling[Month],$C$5,tblBilling[Payment Status],"PAID") | D13: =COUNTIFS(tblBilling[Month],$C$6,tblBilling[Payment Status],"PAID") | E13: =D13-C13 | F13: =IF(N(C13)=0,"",(D13-C13)/C13)
B14: Partial Customers | C14: =COUNTIFS(tblBilling[Month],$C$5,tblBilling[Payment Status],"PARTIAL") | D14: =COUNTIFS(tblBilling[Month],$C$6,tblBilling[Payment Status],"PARTIAL") | E14: =D14-C14 | F14: =IF(N(C14)=0,"",(D14-C14)/C14)
B15: Pending Customers | C15: =COUNTIFS(tblBilling[Month],$C$5,tblBilling[Payment Status],"PENDING") | D15: =COUNTIFS(tblBilling[Month],$C$6,tblBilling[Payment Status],"PENDING") | E15: =D15-C15 | F15: =IF(N(C15)=0,"",(D15-C15)/C15)
B16: Recovery % | C16: =IF(SUMIFS(tblBilling[Monthly Fee],tblBilling[Month],$C$5)=0,0,SUMIFS(tblBilling[Amount Paid],tblBilling[Month],$C$5)/SUMIFS(tblBilling[Monthly Fee],tblBilling[Month],$C$5)) | D16: =IF(SUMIFS(tblBilling[Monthly Fee],tblBilling[Month],$C$6)=0,0,SUMIFS(tblBilling[Amount Paid],tblBilling[Month],$C$6)/SUMIFS(tblBilling[Monthly Fee],tblBilling[Month],$C$6)) | E16: =D16-C16 | F16: =IF(N(C16)=0,"",(D16-C16)/C16)
B18: Month-by-month totals for every generated month are in MONTHS (Monthly Archive).
B19: ► Open Monthly Archive
B21: STREET / LOCATION-WISE REPORT (month below)
B22: Month | C22: =CFG_CurrentMonth
B23: Location | C23: Full Address | D23: Billed | E23: Billing | F23: Recovered | G23: Pending | H23: Recovery % | I23: Unpaid Customers | J23: Active Customers
B24: =IFERROR(INDEX(tblLocations[Location Code],1)&"","") | C24: =IF($B24="","",INDEX(tblLocations[Full Address],1)) | D24: =IF($B24="","",COUNTIFS(tblBilling[Month],$C$22,tblBilling[Location Code],$B24)) | E24: =IF($B24="","",SUMIFS(tblBilling[Monthly Fee],tblBilling[Month],$C$22,tblBilling[Location Code],$B24)) | F24: =IF($B24="","",SUMIFS(tblBilling[Amount Paid],tblBilling[Month],$C$22,tblBilling[Location Code],$B24)) | G24: =IF($B24="","",SUMIFS(tblBilling[Balance],tblBilling[Month],$C$22,tblBilling[Location Code],$B24)) | H24: =IF(OR($B24="",N(E24)=0),"",F24/E24) | I24: =IF($B24="","",COUNTIFS(tblBilling[Month],$C$22,tblBilling[Location Code],$B24,tblBilling[Balance],">0")) | J24: =IF($B24="","",COUNTIFS(tblCustomers[Location Code],$B24,tblCustomers[Customer Status],"Active"))
B25: =IFERROR(INDEX(tblLocations[Location Code],2)&"","") | C25: =IF($B25="","",INDEX(tblLocations[Full Address],2)) | D25: =IF($B25="","",COUNTIFS(tblBilling[Month],$C$22,tblBilling[Location Code],$B25)) | E25: =IF($B25="","",SUMIFS(tblBilling[Monthly Fee],tblBilling[Month],$C$22,tblBilling[Location Code],$B25)) | F25: =IF($B25="","",SUMIFS(tblBilling[Amount Paid],tblBilling[Month],$C$22,tblBilling[Location Code],$B25)) | G25: =IF($B25="","",SUMIFS(tblBilling[Balance],tblBilling[Month],$C$22,tblBilling[Location Code],$B25)) | H25: =IF(OR($B25="",N(E25)=0),"",F25/E25) | I25: =IF($B25="","",COUNTIFS(tblBilling[Month],$C$22,tblBilling[Location Code],$B25,tblBilling[Balance],">0")) | J25: =IF($B25="","",COUNTIFS(tblCustomers[Location Code],$B25,tblCustomers[Customer Status],"Active"))
B26: =IFERROR(INDEX(tblLocations[Location Code],3)&"","") | C26: =IF($B26="","",INDEX(tblLocations[Full Address],3)) | D26: =IF($B26="","",COUNTIFS(tblBilling[Month],$C$22,tblBilling[Location Code],$B26)) | E26: =IF($B26="","",SUMIFS(tblBilling[Monthly Fee],tblBilling[Month],$C$22,tblBilling[Location Code],$B26)) | F26: =IF($B26="","",SUMIFS(tblBilling[Amount Paid],tblBilling[Month],$C$22,tblBilling[Location Code],$B26)) | G26: =IF($B26="","",SUMIFS(tblBilling[Balance],tblBilling[Month],$C$22,tblBilling[Location Code],$B26)) | H26: =IF(OR($B26="",N(E26)=0),"",F26/E26) | I26: =IF($B26="","",COUNTIFS(tblBilling[Month],$C$22,tblBilling[Location Code],$B26,tblBilling[Balance],">0")) | J26: =IF($B26="","",COUNTIFS(tblCustomers[Location Code],$B26,tblCustomers[Customer Status],"Active"))
B27: =IFERROR(INDEX(tblLocations[Location Code],4)&"","") | C27: =IF($B27="","",INDEX(tblLocations[Full Address],4)) | D27: =IF($B27="","",COUNTIFS(tblBilling[Month],$C$22,tblBilling[Location Code],$B27)) | E27: =IF($B27="","",SUMIFS(tblBilling[Monthly Fee],tblBilling[Month],$C$22,tblBilling[Location Code],$B27)) | F27: =IF($B27="","",SUMIFS(tblBilling[Amount Paid],tblBilling[Month],$C$22,tblBilling[Location Code],$B27)) | G27: =IF($B27="","",SUMIFS(tblBilling[Balance],tblBilling[Month],$C$22,tblBilling[Location Code],$B27)) | H27: =IF(OR($B27="",N(E27)=0),"",F27/E27) | I27: =IF($B27="","",COUNTIFS(tblBilling[Month],$C$22,tblBilling[Location Code],$B27,tblBilling[Balance],">0")) | J27: =IF($B27="","",COUNTIFS(tblCustomers[Location Code],$B27,tblCustomers[Customer Status],"Active"))
B28: =IFERROR(INDEX(tblLocations[Location Code],5)&"","") | C28: =IF($B28="","",INDEX(tblLocations[Full Address],5)) | D28: =IF($B28="","",COUNTIFS(tblBilling[Month],$C$22,tblBilling[Location Code],$B28)) | E28: =IF($B28="","",SUMIFS(tblBilling[Monthly Fee],tblBilling[Month],$C$22,tblBilling[Location Code],$B28)) | F28: =IF($B28="","",SUMIFS(tblBilling[Amount Paid],tblBilling[Month],$C$22,tblBilling[Location Code],$B28)) | G28: =IF($B28="","",SUMIFS(tblBilling[Balance],tblBilling[Month],$C$22,tblBilling[Location Code],$B28)) | H28: =IF(OR($B28="",N(E28)=0),"",F28/E28) | I28: =IF($B28="","",COUNTIFS(tblBilling[Month],$C$22,tblBilling[Location Code],$B28,tblBilling[Balance],">0")) | J28: =IF($B28="","",COUNTIFS(tblCustomers[Location Code],$B28,tblCustomers[Customer Status],"Active"))
B29: =IFERROR(INDEX(tblLocations[Location Code],6)&"","") | C29: =IF($B29="","",INDEX(tblLocations[Full Address],6)) | D29: =IF($B29="","",COUNTIFS(tblBilling[Month],$C$22,tblBilling[Location Code],$B29)) | E29: =IF($B29="","",SUMIFS(tblBilling[Monthly Fee],tblBilling[Month],$C$22,tblBilling[Location Code],$B29)) | F29: =IF($B29="","",SUMIFS(tblBilling[Amount Paid],tblBilling[Month],$C$22,tblBilling[Location Code],$B29)) | G29: =IF($B29="","",SUMIFS(tblBilling[Balance],tblBilling[Month],$C$22,tblBilling[Location Code],$B29)) | H29: =IF(OR($B29="",N(E29)=0),"",F29/E29) | I29: =IF($B29="","",COUNTIFS(tblBilling[Month],$C$22,tblBilling[Location Code],$B29,tblBilling[Balance],">0")) | J29: =IF($B29="","",COUNTIFS(tblCustomers[Location Code],$B29,tblCustomers[Customer Status],"Active"))
B30: =IFERROR(INDEX(tblLocations[Location Code],7)&"","") | C30: =IF($B30="","",INDEX(tblLocations[Full Address],7)) | D30: =IF($B30="","",COUNTIFS(tblBilling[Month],$C$22,tblBilling[Location Code],$B30)) | E30: =IF($B30="","",SUMIFS(tblBilling[Monthly Fee],tblBilling[Month],$C$22,tblBilling[Location Code],$B30)) | F30: =IF($B30="","",SUMIFS(tblBilling[Amount Paid],tblBilling[Month],$C$22,tblBilling[Location Code],$B30)) | G30: =IF($B30="","",SUMIFS(tblBilling[Balance],tblBilling[Month],$C$22,tblBilling[Location Code],$B30)) | H30: =IF(OR($B30="",N(E30)=0),"",F30/E30) | I30: =IF($B30="","",COUNTIFS(tblBilling[Month],$C$22,tblBilling[Location Code],$B30,tblBilling[Balance],">0")) | J30: =IF($B30="","",COUNTIFS(tblCustomers[Location Code],$B30,tblCustomers[Customer Status],"Active"))
B31: =IFERROR(INDEX(tblLocations[Location Code],8)&"","") | C31: =IF($B31="","",INDEX(tblLocations[Full Address],8)) | D31: =IF($B31="","",COUNTIFS(tblBilling[Month],$C$22,tblBilling[Location Code],$B31)) | E31: =IF($B31="","",SUMIFS(tblBilling[Monthly Fee],tblBilling[Month],$C$22,tblBilling[Location Code],$B31)) | F31: =IF($B31="","",SUMIFS(tblBilling[Amount Paid],tblBilling[Month],$C$22,tblBilling[Location Code],$B31)) | G31: =IF($B31="","",SUMIFS(tblBilling[Balance],tblBilling[Month],$C$22,tblBilling[Location Code],$B31)) | H31: =IF(OR($B31="",N(E31)=0),"",F31/E31) | I31: =IF($B31="","",COUNTIFS(tblBilling[Month],$C$22,tblBilling[Location Code],$B31,tblBilling[Balance],">0")) | J31: =IF($B31="","",COUNTIFS(tblCustomers[Location Code],$B31,tblCustomers[Customer Status],"Active"))
B32: =IFERROR(INDEX(tblLocations[Location Code],9)&"","") | C32: =IF($B32="","",INDEX(tblLocations[Full Address],9)) | D32: =IF($B32="","",COUNTIFS(tblBilling[Month],$C$22,tblBilling[Location Code],$B32)) | E32: =IF($B32="","",SUMIFS(tblBilling[Monthly Fee],tblBilling[Month],$C$22,tblBilling[Location Code],$B32)) | F32: =IF($B32="","",SUMIFS(tblBilling[Amount Paid],tblBilling[Month],$C$22,tblBilling[Location Code],$B32)) | G32: =IF($B32="","",SUMIFS(tblBilling[Balance],tblBilling[Month],$C$22,tblBilling[Location Code],$B32)) | H32: =IF(OR($B32="",N(E32)=0),"",F32/E32) | I32: =IF($B32="","",COUNTIFS(tblBilling[Month],$C$22,tblBilling[Location Code],$B32,tblBilling[Balance],">0")) | J32: =IF($B32="","",COUNTIFS(tblCustomers[Location Code],$B32,tblCustomers[Customer Status],"Active"))
B33: =IFERROR(INDEX(tblLocations[Location Code],10)&"","") | C33: =IF($B33="","",INDEX(tblLocations[Full Address],10)) | D33: =IF($B33="","",COUNTIFS(tblBilling[Month],$C$22,tblBilling[Location Code],$B33)) | E33: =IF($B33="","",SUMIFS(tblBilling[Monthly Fee],tblBilling[Month],$C$22,tblBilling[Location Code],$B33)) | F33: =IF($B33="","",SUMIFS(tblBilling[Amount Paid],tblBilling[Month],$C$22,tblBilling[Location Code],$B33)) | G33: =IF($B33="","",SUMIFS(tblBilling[Balance],tblBilling[Month],$C$22,tblBilling[Location Code],$B33)) | H33: =IF(OR($B33="",N(E33)=0),"",F33/E33) | I33: =IF($B33="","",COUNTIFS(tblBilling[Month],$C$22,tblBilling[Location Code],$B33,tblBilling[Balance],">0")) | J33: =IF($B33="","",COUNTIFS(tblCustomers[Location Code],$B33,tblCustomers[Customer Status],"Active"))
B34: =IFERROR(INDEX(tblLocations[Location Code],11)&"","") | C34: =IF($B34="","",INDEX(tblLocations[Full Address],11)) | D34: =IF($B34="","",COUNTIFS(tblBilling[Month],$C$22,tblBilling[Location Code],$B34)) | E34: =IF($B34="","",SUMIFS(tblBilling[Monthly Fee],tblBilling[Month],$C$22,tblBilling[Location Code],$B34)) | F34: =IF($B34="","",SUMIFS(tblBilling[Amount Paid],tblBilling[Month],$C$22,tblBilling[Location Code],$B34)) | G34: =IF($B34="","",SUMIFS(tblBilling[Balance],tblBilling[Month],$C$22,tblBilling[Location Code],$B34)) | H34: =IF(OR($B34="",N(E34)=0),"",F34/E34) | I34: =IF($B34="","",COUNTIFS(tblBilling[Month],$C$22,tblBilling[Location Code],$B34,tblBilling[Balance],">0")) | J34: =IF($B34="","",COUNTIFS(tblCustomers[Location Code],$B34,tblCustomers[Customer Status],"Active"))
B35: =IFERROR(INDEX(tblLocations[Location Code],12)&"","") | C35: =IF($B35="","",INDEX(tblLocations[Full Address],12)) | D35: =IF($B35="","",COUNTIFS(tblBilling[Month],$C$22,tblBilling[Location Code],$B35)) | E35: =IF($B35="","",SUMIFS(tblBilling[Monthly Fee],tblBilling[Month],$C$22,tblBilling[Location Code],$B35)) | F35: =IF($B35="","",SUMIFS(tblBilling[Amount Paid],tblBilling[Month],$C$22,tblBilling[Location Code],$B35)) | G35: =IF($B35="","",SUMIFS(tblBilling[Balance],tblBilling[Month],$C$22,tblBilling[Location Code],$B35)) | H35: =IF(OR($B35="",N(E35)=0),"",F35/E35) | I35: =IF($B35="","",COUNTIFS(tblBilling[Month],$C$22,tblBilling[Location Code],$B35,tblBilling[Balance],">0")) | J35: =IF($B35="","",COUNTIFS(tblCustomers[Location Code],$B35,tblCustomers[Customer Status],"Active"))
B36: =IFERROR(INDEX(tblLocations[Location Code],13)&"","") | C36: =IF($B36="","",INDEX(tblLocations[Full Address],13)) | D36: =IF($B36="","",COUNTIFS(tblBilling[Month],$C$22,tblBilling[Location Code],$B36)) | E36: =IF($B36="","",SUMIFS(tblBilling[Monthly Fee],tblBilling[Month],$C$22,tblBilling[Location Code],$B36)) | F36: =IF($B36="","",SUMIFS(tblBilling[Amount Paid],tblBilling[Month],$C$22,tblBilling[Location Code],$B36)) | G36: =IF($B36="","",SUMIFS(tblBilling[Balance],tblBilling[Month],$C$22,tblBilling[Location Code],$B36)) | H36: =IF(OR($B36="",N(E36)=0),"",F36/E36) | I36: =IF($B36="","",COUNTIFS(tblBilling[Month],$C$22,tblBilling[Location Code],$B36,tblBilling[Balance],">0")) | J36: =IF($B36="","",COUNTIFS(tblCustomers[Location Code],$B36,tblCustomers[Customer Status],"Active"))
B37: =IFERROR(INDEX(tblLocations[Location Code],14)&"","") | C37: =IF($B37="","",INDEX(tblLocations[Full Address],14)) | D37: =IF($B37="","",COUNTIFS(tblBilling[Month],$C$22,tblBilling[Location Code],$B37)) | E37: =IF($B37="","",SUMIFS(tblBilling[Monthly Fee],tblBilling[Month],$C$22,tblBilling[Location Code],$B37)) | F37: =IF($B37="","",SUMIFS(tblBilling[Amount Paid],tblBilling[Month],$C$22,tblBilling[Location Code],$B37)) | G37: =IF($B37="","",SUMIFS(tblBilling[Balance],tblBilling[Month],$C$22,tblBilling[Location Code],$B37)) | H37: =IF(OR($B37="",N(E37)=0),"",F37/E37) | I37: =IF($B37="","",COUNTIFS(tblBilling[Month],$C$22,tblBilling[Location Code],$B37,tblBilling[Balance],">0")) | J37: =IF($B37="","",COUNTIFS(tblCustomers[Location Code],$B37,tblCustomers[Customer Status],"Active"))
B38: =IFERROR(INDEX(tblLocations[Location Code],15)&"","") | C38: =IF($B38="","",INDEX(tblLocations[Full Address],15)) | D38: =IF($B38="","",COUNTIFS(tblBilling[Month],$C$22,tblBilling[Location Code],$B38)) | E38: =IF($B38="","",SUMIFS(tblBilling[Monthly Fee],tblBilling[Month],$C$22,tblBilling[Location Code],$B38)) | F38: =IF($B38="","",SUMIFS(tblBilling[Amount Paid],tblBilling[Month],$C$22,tblBilling[Location Code],$B38)) | G38: =IF($B38="","",SUMIFS(tblBilling[Balance],tblBilling[Month],$C$22,tblBilling[Location Code],$B38)) | H38: =IF(OR($B38="",N(E38)=0),"",F38/E38) | I38: =IF($B38="","",COUNTIFS(tblBilling[Month],$C$22,tblBilling[Location Code],$B38,tblBilling[Balance],">0")) | J38: =IF($B38="","",COUNTIFS(tblCustomers[Location Code],$B38,tblCustomers[Customer Status],"Active"))
B39: =IFERROR(INDEX(tblLocations[Location Code],16)&"","") | C39: =IF($B39="","",INDEX(tblLocations[Full Address],16)) | D39: =IF($B39="","",COUNTIFS(tblBilling[Month],$C$22,tblBilling[Location Code],$B39)) | E39: =IF($B39="","",SUMIFS(tblBilling[Monthly Fee],tblBilling[Month],$C$22,tblBilling[Location Code],$B39)) | F39: =IF($B39="","",SUMIFS(tblBilling[Amount Paid],tblBilling[Month],$C$22,tblBilling[Location Code],$B39)) | G39: =IF($B39="","",SUMIFS(tblBilling[Balance],tblBilling[Month],$C$22,tblBilling[Location Code],$B39)) | H39: =IF(OR($B39="",N(E39)=0),"",F39/E39) | I39: =IF($B39="","",COUNTIFS(tblBilling[Month],$C$22,tblBilling[Location Code],$B39,tblBilling[Balance],">0")) | J39: =IF($B39="","",COUNTIFS(tblCustomers[Location Code],$B39,tblCustomers[Customer Status],"Active"))
B40: =IFERROR(INDEX(tblLocations[Location Code],17)&"","") | C40: =IF($B40="","",INDEX(tblLocations[Full Address],17)) | D40: =IF($B40="","",COUNTIFS(tblBilling[Month],$C$22,tblBilling[Location Code],$B40)) | E40: =IF($B40="","",SUMIFS(tblBilling[Monthly Fee],tblBilling[Month],$C$22,tblBilling[Location Code],$B40)) | F40: =IF($B40="","",SUMIFS(tblBilling[Amount Paid],tblBilling[Month],$C$22,tblBilling[Location Code],$B40)) | G40: =IF($B40="","",SUMIFS(tblBilling[Balance],tblBilling[Month],$C$22,tblBilling[Location Code],$B40)) | H40: =IF(OR($B40="",N(E40)=0),"",F40/E40) | I40: =IF($B40="","",COUNTIFS(tblBilling[Month],$C$22,tblBilling[Location Code],$B40,tblBilling[Balance],">0")) | J40: =IF($B40="","",COUNTIFS(tblCustomers[Location Code],$B40,tblCustomers[Customer Status],"Active"))
B41: =IFERROR(INDEX(tblLocations[Location Code],18)&"","") | C41: =IF($B41="","",INDEX(tblLocations[Full Address],18)) | D41: =IF($B41="","",COUNTIFS(tblBilling[Month],$C$22,tblBilling[Location Code],$B41)) | E41: =IF($B41="","",SUMIFS(tblBilling[Monthly Fee],tblBilling[Month],$C$22,tblBilling[Location Code],$B41)) | F41: =IF($B41="","",SUMIFS(tblBilling[Amount Paid],tblBilling[Month],$C$22,tblBilling[Location Code],$B41)) | G41: =IF($B41="","",SUMIFS(tblBilling[Balance],tblBilling[Month],$C$22,tblBilling[Location Code],$B41)) | H41: =IF(OR($B41="",N(E41)=0),"",F41/E41) | I41: =IF($B41="","",COUNTIFS(tblBilling[Month],$C$22,tblBilling[Location Code],$B41,tblBilling[Balance],">0")) | J41: =IF($B41="","",COUNTIFS(tblCustomers[Location Code],$B41,tblCustomers[Customer Status],"Active"))
B42: =IFERROR(INDEX(tblLocations[Location Code],19)&"","") | C42: =IF($B42="","",INDEX(tblLocations[Full Address],19)) | D42: =IF($B42="","",COUNTIFS(tblBilling[Month],$C$22,tblBilling[Location Code],$B42)) | E42: =IF($B42="","",SUMIFS(tblBilling[Monthly Fee],tblBilling[Month],$C$22,tblBilling[Location Code],$B42)) | F42: =IF($B42="","",SUMIFS(tblBilling[Amount Paid],tblBilling[Month],$C$22,tblBilling[Location Code],$B42)) | G42: =IF($B42="","",SUMIFS(tblBilling[Balance],tblBilling[Month],$C$22,tblBilling[Location Code],$B42)) | H42: =IF(OR($B42="",N(E42)=0),"",F42/E42) | I42: =IF($B42="","",COUNTIFS(tblBilling[Month],$C$22,tblBilling[Location Code],$B42,tblBilling[Balance],">0")) | J42: =IF($B42="","",COUNTIFS(tblCustomers[Location Code],$B42,tblCustomers[Customer Status],"Active"))
